Workbook
Name _E4110: #REF!
Name a: #REF!
Name a1A32: [1]AD24101!$A$31
Name 出荷元: #REF!
Name 出荷方法: #REF!
Name 生地品番: [3]生地・色リスト!$A$2:$A$18
Name 色: [3]生地・色リスト!$C$2:$C$40

Sheet Dữ Liệu
B1: TAIYO NISSHIN VIETNAM CO.,LTD 太陽日新ベトナム株式会社
A2: P1. THÔNG TIN CHI TIẾT HÀNG HÓA 製品詳細
A3: 1 | B3: 2 | C3: 3 | D3: 4 | E3: 5 | F3: 6 | G3: 7 | H3: 8 | I3: 9 | J3: 10 | K3: GĐĐ | L3: TIỀN XE
A4: TÊN KHÁCH HÀNG | B4: NHÀ MÁY | C4: Mã hàng | D4: Thương hiệu | E4: Tên hàng | F4: Màu | G4: Size | H4: Số Lượng | I4: Ngày nhận | J4: Ngày xuất
A5: CUSTOMER | B5: FACTORY | C5: Style No | D5: Brand | E5: Item | F5: Color | G5: Size | H5: Quantity | I5: Date | J5: Date
A6: お客様 | B6: 工場 | C6: 品番 | D6: ブランド | E6: 品目 | F6: カラー | G6: サイズ | H6: サイズ | I6: サイズ | J6: サイズ
A7: TAMURAKOMA | B7: TPA | C7: BR1144 | D7: GUA | E7: SHIRT | F7: WH | H7: 100 | K7: 1 | L7: 650000 | M7: 100
A8: TAMURAKOMA | B8: TPA | C8: BR1109 | D8: GUA | E8: SHIRT | F8: WH | H8: 300
A9: TAMURAKOMA | B9: TPA | C9: BR9071 | D9: GUA | E9: SHIRT | F9: WH
A10: TAMURAKOMA | B10: TPA | C10: HS8078 | D10: GUA | E10: SHIRT | F10: WH
A11: TAMURAKOMA | B11: TPA | C11: BR1108 | D11: GUA | E11: SHIRT | F11: WH
A12: TAMURAKOMA | B12: TPA | C12: BR9125 | D12: GUA | E12: SHIRT | F12: WH
A13: TAMURAKOMA | B13: TPA | C13: BR9070 | D13: GUA | E13: SHIRT | F13: WH
A14: TAMURAKOMA | B14: TPA | C14: HS8073 | D14: GUA | E14: SHIRT | F14: WH
A15: TAMURAKOMA | B15: AA | C15: HS8072 | D15: SSK | E15: PANT | F15: BLACK | H15: 1000 | K15: 1.5 | L15: 800000

Sheet Daily Report
B1: TAIYO NISSHIN VIETNAM CO.,LTD 太陽日新ベトナム株式会社
A2: BÁO CÁO KẾT QUẢ KIỂM HÀNG 検品 結 果 報 告 書
A3: P1. THÔNG TIN CHI TIẾT HÀNG HÓA | H3: P2. BÁO CÁO KIỂM HÀNG CHI TIẾT HẰNG NGÀY | T3: P3. THEO DỎI NĂNG SUẤT
A4: Ngày kiểm hàng | B4: Nội dung kiểm hàng | C4: Mã hàng | D4: Thương hiệu | E4: Tên hàng | F4: Màu | G4: Size | H4: SL kiểm hàng | I4: Hàng đạt | J4: Hàng hư | K4: Thông số | L4: Phụ liệu | M4: Ngoại quan | N4: Vải | O4: Dơ | P4: Lổi may | Q4: Khác | R4: Kiểm Kim | S4: Tỉ lệ lỗi | T4: SL BOOK | U4: SL BOOK CHÊNH LỆCH | V4: SL QC | W4: GIỜ ĐI ĐƯỜNG | X4: THỜI GIAN LÀM VIỆC | Y4: THỜI GIAN TĂNG CA | Z4: MD | AA4: TỔ TRƯỞNG | AB4: ĐIỂM NĂNG SUẤT | AC4: GHI CHÚ
A5: Date | B5: Inspection | C5: Style No | D5: Brand | E5: Item | F5: Color | G5: Size | H5: Inspection Qty | I5: A-Grade Qty | J5: Defect Qty | K5: Measurment | L5: Material | M5: Appearance | N5: Fabric | O5: Dirt | P5: Sewing | Q5: Other | R5: Needle Inspection | S5: rate | T5: BOOKING Q'TY | U5: Q'TY DIFFERENCE | V5: QC Q'TY | X5: TIME | Y5: OT | Z5: MD | AA5: LEADER | AB5: PRODUCTIVITY SCORE | AC5: NOTE
A6: 日付 | B6: 検品内容 | C6: 品番 | D6: ブランド | E6: 品目 | F6: カラー | G6: サイズ | H6: 検品数 | I6: 良品数 | J6: 不良品数 | K6: 採寸不良 | L6: 付属不良 | M6: 外観不良 | N6: 生地不良 | O6: 汚れ不良 | P6: 縫製不良 | Q6: その他 | R6: 検針 | S6: 不良率 | T6: 予約数量 | U6: 数量差 | V6: 人数 | X6: 作業時間 | Y6: 残業時間 | Z6: 担当者 | AA6: リーダー
A7: 46086 | B7: KIEM | C7: BR1144 | D7: =IF(C7=" "," ",VLOOKUP(C7,'Dữ Liệu'!$C$7:$D$134,2,FALSE)) -> GUA | E7: SHIRT | F7: WH | G7: L | H7: 51 | I7: =H7-J7 -> 47 | J7: =SUM(K7:Q7) -> 4 | O7: 3 | P7: 1 | S7: =J7/H7 -> 0.078431373 | V7: 4 | W7: 1.5 | Y7: 1 | AD7: =C7&F7&G7&B7 -> BR1144WHLKIEM | AE7: =C7&F7&G7 -> BR1144WHL
A8: 46086 | B8: KIEM | C8: BR1144 | D8: =IF(C8=" "," ",VLOOKUP(C8,'Dữ Liệu'!$C$7:$D$134,2,FALSE)) -> GUA | E8: SHIRT | F8: WH | G8: LL | H8: 67 | I8: =H8-J8 -> 60 | J8: =SUM(K8:Q8) -> 7 | O8: 5 | P8: 2 | S8: =J8/H8 -> 0.10447761 | V8: 4 | W8: 1.5 | Y8: 1 | AD8: =C8&F8&G8&B8 -> BR1144WHLLKIEM | AE8: =C8&F8&G8 -> BR1144WHLL
A9: 46086 | B9: KIEM | C9: BR9071 | D9: =IF(C9=" "," ",VLOOKUP(C9,'Dữ Liệu'!$C$7:$D$134,2,FALSE)) -> GUA | E9: SHIRT | F9: WH | G9: M | H9: 114 | I9: =H9-J9 -> 102 | J9: =SUM(K9:Q9) -> 12 | O9: 9 | P9: 3 | S9: =J9/H9 -> 0.10526316 | V9: 4 | W9: 1.5 | Y9: 1 | AD9: =C9&F9&G9&B9 -> BR9071WHMKIEM | AE9: =C9&F9&G9 -> BR9071WHM
A10: 46086 | B10: KIEM | C10: HS8078 | D10: =IF(C10=" "," ",VLOOKUP(C10,'Dữ Liệu'!$C$7:$D$134,2,FALSE)) -> GUA | E10: SHIRT | F10: WH | G10: M | H10: 91 | I10: =H10-J10 -> 85 | J10: =SUM(K10:Q10) -> 6 | O10: 4 | P10: 2 | S10: =J10/H10 -> 0.065934066 | V10: 4 | W10: 1.5 | Y10: 1 | AD10: =C10&F10&G10&B10 -> HS8078WHMKIEM | AE10: =C10&F10&G10 -> HS8078WHM
A11: 46086 | B11: KIEM | C11: HS8078 | D11: =IF(C11=" "," ",VLOOKUP(C11,'Dữ Liệu'!$C$7:$D$134,2,FALSE)) -> GUA | E11: SHIRT | F11: WH | G11: L | H11: 111 | I11: =H11-J11 -> 101 | J11: =SUM(K11:Q11) -> 10 | O11: 6 | P11: 4 | S11: =J11/H11 -> 0.09009009 | V11: 4 | W11: 1.5 | Y11: 1 | AD11: =C11&F11&G11&B11 -> HS8078WHLKIEM | AE11: =C11&F11&G11 -> HS8078WHL
A12: 46086 | B12: KIEM | C12: HS8078 | D12: =IF(C12=" "," ",VLOOKUP(C12,'Dữ Liệu'!$C$7:$D$134,2,FALSE)) -> GUA | E12: SHIRT | F12: WH | G12: LL | H12: 66 | I12: =H12-J12 -> 63 | J12: =SUM(K12:Q12) -> 3 | O12: 2 | P12: 1 | S12: =J12/H12 -> 0.045454545 | V12: 4 | W12: 1.5 | Y12: 1 | AD12: =C12&F12&G12&B12 -> HS8078WHLLKIEM | AE12: =C12&F12&G12 -> HS8078WHLL
A13: 46086 | B13: KIEM | C13: BR9070 | D13: =IF(C13=" "," ",VLOOKUP(C13,'Dữ Liệu'!$C$7:$D$134,2,FALSE)) -> GUA | E13: SHIRT | F13: WH | G13: S | H13: 2 | I13: =H13-J13 -> 2 | J13: =SUM(K13:Q13) -> 0 | S13: =J13/H13 -> 0 | V13: 4 | W13: 1.5 | Y13: 1 | AD13: =C13&F13&G13&B13 -> BR9070WHSKIEM | AE13: =C13&F13&G13 -> BR9070WHS
A14: 46086 | B14: KIEM | C14: BR9070 | D14: =IF(C14=" "," ",VLOOKUP(C14,'Dữ Liệu'!$C$7:$D$134,2,FALSE)) -> GUA | E14: SHIRT | F14: WH | G14: M | H14: 2 | I14: =H14-J14 -> 2 | J14: =SUM(K14:Q14) -> 0 | S14: =J14/H14 -> 0 | AD14: =C14&F14&G14&B14 -> BR9070WHMKIEM | AE14: =C14&F14&G14 -> BR9070WHM
A15: 46086 | B15: KIEM | C15: BR9070 | D15: =IF(C15=" "," ",VLOOKUP(C15,'Dữ Liệu'!$C$7:$D$134,2,FALSE)) -> GUA | E15: SHIRT | F15: WH | G15: LL | H15: 1 | I15: =H15-J15 -> 1 | J15: =SUM(K15:Q15) -> 0 | S15: =J15/H15 -> 0 | AD15: =C15&F15&G15&B15 -> BR9070WHLLKIEM | AE15: =C15&F15&G15 -> BR9070WHLL
A16: 46086 | B16: KIEM | C16: HS8073 | D16: =IF(C16=" "," ",VLOOKUP(C16,'Dữ Liệu'!$C$7:$D$134,2,FALSE)) -> GUA | E16: SHIRT | F16: WH | G16: M | H16: 2 | I16: =H16-J16 -> 2 | J16: =SUM(K16:Q16) -> 0 | S16: =J16/H16 -> 0 | AD16: =C16&F16&G16&B16 -> HS8073WHMKIEM | AE16: =C16&F16&G16 -> HS8073WHM
A17: 46086 | B17: KIEM | C17: HS8073 | D17: =IF(C17=" "," ",VLOOKUP(C17,'Dữ Liệu'!$C$7:$D$134,2,FALSE)) -> GUA | E17: SHIRT | F17: WH | G17: L | H17: 1 | I17: =H17-J17 -> 1 | J17: =SUM(K17:Q17) -> 0 | S17: =J17/H17 -> 0 | AD17: =C17&F17&G17&B17 -> HS8073WHLKIEM | AE17: =C17&F17&G17 -> HS8073WHL
A18: 46086 | B18: KIEM | C18: BR1109 | D18: =IF(C18=" "," ",VLOOKUP(C18,'Dữ Liệu'!$C$7:$D$134,2,FALSE)) -> GUA | E18: SHIRT | F18: WH | G18: L | H18: 2 | I18: =H18-J18 -> 2 | J18: =SUM(K18:Q18) -> 0 | S18: =J18/H18 -> 0 | AD18: =C18&F18&G18&B18 -> BR1109WHLKIEM | AE18: =C18&F18&G18 -> BR1109WHL
A19: 46086 | B19: TAIKIEM | C19: BR1144 | D19: =IF(C19=" "," ",VLOOKUP(C19,'Dữ Liệu'!$C$7:$D$134,2,FALSE)) -> GUA | E19: SHIRT | F19: WH | G19: L | H19: 4 | I19: =H19-J19 -> 4 | J19: =SUM(K19:Q19) -> 0 | S19: =J19/H19 -> 0 | AD19: =C19&F19&G19&B19 -> BR1144WHLTAIKIEM | AE19: =C19&F19&G19 -> BR1144WHL
A20: 46086 | B20: TAIKIEM | C20: BR1144 | D20: =IF(C20=" "," ",VLOOKUP(C20,'Dữ Liệu'!$C$7:$D$134,2,FALSE)) -> GUA | E20: SHIRT | F20: WH | G20: LL | H20: 7 | I20: =H20-J20 -> 7 | J20: =SUM(K20:Q20) -> 0 | S20: =J20/H20 -> 0 | AD20: =C20&F20&G20&B20 -> BR1144WHLLTAIKIEM | AE20: =C20&F20&G20 -> BR1144WHLL
A21: 46086 | B21: TAIKIEM | C21: BR9071 | D21: =IF(C21=" "," ",VLOOKUP(C21,'Dữ Liệu'!$C$7:$D$134,2,FALSE)) -> GUA | E21: SHIRT | F21: WH | G21: M | H21: 12 | I21: =H21-J21 -> 12 | J21: =SUM(K21:Q21) -> 0 | S21: =J21/H21 -> 0 | AD21: =C21&F21&G21&B21 -> BR9071WHMTAIKIEM | AE21: =C21&F21&G21 -> BR9071WHM
A22: 46086 | B22: TAIKIEM | C22: HS8078 | D22: =IF(C22=" "," ",VLOOKUP(C22,'Dữ Liệu'!$C$7:$D$134,2,FALSE)) -> GUA | E22: SHIRT | F22: WH | G22: M | H22: 6 | I22: =H22-J22 -> 6 | J22: =SUM(K22:Q22) -> 0 | S22: =J22/H22 -> 0 | AD22: =C22&F22&G22&B22 -> HS8078WHMTAIKIEM | AE22: =C22&F22&G22 -> HS8078WHM
A23: 46086 | B23: TAIKIEM | C23: HS8078 | D23: =IF(C23=" "," ",VLOOKUP(C23,'Dữ Liệu'!$C$7:$D$134,2,FALSE)) -> GUA | E23: SHIRT | F23: WH | G23: L | H23: 10 | I23: =H23-J23 -> 10 | J23: =SUM(K23:Q23) -> 0 | S23: =J23/H23 -> 0 | AD23: =C23&F23&G23&B23 -> HS8078WHLTAIKIEM | AE23: =C23&F23&G23 -> HS8078WHL
A24: 46086 | B24: TAIKIEM | C24: HS8078 | D24: =IF(C24=" "," ",VLOOKUP(C24,'Dữ Liệu'!$C$7:$D$134,2,FALSE)) -> GUA | E24: SHIRT | F24: WH | G24: LL | H24: 3 | I24: =H24-J24 -> 3 | J24: =SUM(K24:Q24) -> 0 | S24: =J24/H24 -> 0 | AD24: =C24&F24&G24&B24 -> HS8078WHLLTAIKIEM | AE24: =C24&F24&G24 -> HS8078WHLL
A25: 46090 | B25: KIEM | C25: BR9071 | D25: =IF(C25=" "," ",VLOOKUP(C25,'Dữ Liệu'!$C$7:$D$134,2,FALSE)) -> GUA | E25: SHIRT | F25: WH | G25: S | H25: 100 | I25: =H25-J25 -> 89 | J25: =SUM(K25:Q25) -> 11 | O25: 9 | P25: 2 | S25: =J25/H25 -> 0.11 | AD25: =C25&F25&G25&B25 -> BR9071WHSKIEM | AE25: =C25&F25&G25 -> BR9071WHS
A26: 46090 | B26: KIEM | C26: BR9071 | D26: =IF(C26=" "," ",VLOOKUP(C26,'Dữ Liệu'!$C$7:$D$134,2,FALSE)) -> GUA | E26: SHIRT | F26: WH | G26: M | H26: 86 | I26: =H26-J26 -> 81 | J26: =SUM(K26:Q26) -> 5 | O26: 5 | S26: =J26/H26 -> 0.058139535 | AD26: =C26&F26&G26&B26 -> BR9071WHMKIEM | AE26: =C26&F26&G26 -> BR9071WHM
A27: 46090 | B27: KIEM | C27: BR9071 | D27: =IF(C27=" "," ",VLOOKUP(C27,'Dữ Liệu'!$C$7:$D$134,2,FALSE)) -> GUA | E27: SHIRT | F27: WH | G27: L | H27: 100 | I27: =H27-J27 -> 88 | J27: =SUM(K27:Q27) -> 12 | O27: 9 | P27: 3 | S27: =J27/H27 -> 0.12 | AD27: =C27&F27&G27&B27 -> BR9071WHLKIEM | AE27: =C27&F27&G27 -> BR9071WHL
A28: 46090 | B28: KIEM | C28: BR9071 | D28: =IF(C28=" "," ",VLOOKUP(C28,'Dữ Liệu'!$C$7:$D$134,2,FALSE)) -> GUA | E28: SHIRT | F28: WH | G28: LL | H28: 50 | I28: =H28-J28 -> 47 | J28: =SUM(K28:Q28) -> 3 | O28: 2 | P28: 1 | S28: =J28/H28 -> 0.06 | AD28: =C28&F28&G28&B28 -> BR9071WHLLKIEM | AE28: =C28&F28&G28 -> BR9071WHLL
A29: 46090 | B29: KIEM | C29: BR9071 | D29: =IF(C29=" "," ",VLOOKUP(C29,'Dữ Liệu'!$C$7:$D$134,2,FALSE)) -> GUA | E29: SHIRT | F29: WH | G29: EL | H29: 28 | I29: =H29-J29 -> 27 | J29: =SUM(K29:Q29) -> 1 | O29: 1 | S29: =J29/H29 -> 0.035714286 | AD29: =C29&F29&G29&B29 -> BR9071WHELKIEM | AE29: =C29&F29&G29 -> BR9071WHEL
A30: 46090 | B30: KIEM | C30: BR9071 | D30: =IF(C30=" "," ",VLOOKUP(C30,'Dữ Liệu'!$C$7:$D$134,2,FALSE)) -> GUA | E30: SHIRT | F30: WH | G30: 4L | H30: 20 | I30: =H30-J30 -> 19 | J30: =SUM(K30:Q30) -> 1 | O30: 1 | S30: =J30/H30 -> 0.05 | AD30: =C30&F30&G30&B30 -> BR9071WH4LKIEM | AE30: =C30&F30&G30 -> BR9071WH4L
A31: 46090 | B31: KIEM | C31: BR1144 | D31: =IF(C31=" "," ",VLOOKUP(C31,'Dữ Liệu'!$C$7:$D$134,2,FALSE)) -> GUA | E31: SHIRT | F31: WH | G31: LL | H31: 38 | I31: =H31-J31 -> 37 | J31: =SUM(K31:Q31) -> 1 | O31: 1 | S31: =J31/H31 -> 0.026315789 | AD31: =C31&F31&G31&B31 -> BR1144WHLLKIEM | AE31: =C31&F31&G31 -> BR1144WHLL
A32: 46090 | B32: TAIKIEM | C32: BR9071 | D32: =IF(C32=" "," ",VLOOKUP(C32,'Dữ Liệu'!$C$7:$D$134,2,FALSE)) -> GUA | E32: SHIRT | F32: WH | G32: S | H32: 11 | I32: =H32-J32 -> 11 | J32: =SUM(K32:Q32) -> 0 | S32: =J32/H32 -> 0 | AD32: =C32&F32&G32&B32 -> BR9071WHSTAIKIEM | AE32: =C32&F32&G32 -> BR9071WHS
A33: 46090 | B33: TAIKIEM | C33: BR9071 | D33: =IF(C33=" "," ",VLOOKUP(C33,'Dữ Liệu'!$C$7:$D$134,2,FALSE)) -> GUA | E33: SHIRT | F33: WH | G33: M | H33: 5 | I33: =H33-J33 -> 5 | J33: =SUM(K33:Q33) -> 0 | S33: =J33/H33 -> 0 | AD33: =C33&F33&G33&B33 -> BR9071WHMTAIKIEM | AE33: =C33&F33&G33 -> BR9071WHM
A34: 46090 | B34: TAIKIEM | C34: BR9071 | D34: =IF(C34=" "," ",VLOOKUP(C34,'Dữ Liệu'!$C$7:$D$134,2,FALSE)) -> GUA | E34: SHIRT | F34: WH | G34: L | H34: 12 | I34: =H34-J34 -> 12 | J34: =SUM(K34:Q34) -> 0 | S34: =J34/H34 -> 0 | AD34: =C34&F34&G34&B34 -> BR9071WHLTAIKIEM | AE34: =C34&F34&G34 -> BR9071WHL
A35: 46090 | B35: TAIKIEM | C35: BR9071 | D35: =IF(C35=" "," ",VLOOKUP(C35,'Dữ Liệu'!$C$7:$D$134,2,FALSE)) -> GUA | E35: SHIRT | F35: WH | G35: LL | H35: 3 | I35: =H35-J35 -> 3 | J35: =SUM(K35:Q35) -> 0 | S35: =J35/H35 -> 0 | AD35: =C35&F35&G35&B35 -> BR9071WHLLTAIKIEM | AE35: =C35&F35&G35 -> BR9071WHLL
A36: 46090 | B36: TAIKIEM | C36: BR9071 | D36: =IF(C36=" "," ",VLOOKUP(C36,'Dữ Liệu'!$C$7:$D$134,2,FALSE)) -> GUA | E36: SHIRT | F36: WH | G36: EL | H36: 1 | I36: =H36-J36 -> 1 | J36: =SUM(K36:Q36) -> 0 | S36: =J36/H36 -> 0 | AD36: =C36&F36&G36&B36 -> BR9071WHELTAIKIEM | AE36: =C36&F36&G36 -> BR9071WHEL
A37: 46090 | B37: TAIKIEM | C37: BR9071 | D37: =IF(C37=" "," ",VLOOKUP(C37,'Dữ Liệu'!$C$7:$D$134,2,FALSE)) -> GUA | E37: SHIRT | F37: WH | G37: 4L | H37: 1 | I37: =H37-J37 -> 1 | J37: =SUM(K37:Q37) -> 0 | S37: =J37/H37 -> 0 | AD37: =C37&F37&G37&B37 -> BR9071WH4LTAIKIEM | AE37: =C37&F37&G37 -> BR9071WH4L
A38: 46090 | B38: TAIKIEM | C38: BR1144 | D38: =IF(C38=" "," ",VLOOKUP(C38,'Dữ Liệu'!$C$7:$D$134,2,FALSE)) -> GUA | E38: SHIRT | F38: WH | G38: LL | H38: 1 | I38: =H38-J38 -> 1 | J38: =SUM(K38:Q38) -> 0 | S38: =J38/H38 -> 0 | AD38: =C38&F38&G38&B38 -> BR1144WHLLTAIKIEM | AE38: =C38&F38&G38 -> BR1144WHLL
A39: 46091 | B39: KIEM | C39: BR1144 | D39: =IF(C39=" "," ",VLOOKUP(C39,'Dữ Liệu'!$C$7:$D$134,2,FALSE)) -> GUA | E39: SHIRT | F39: WH | G39: SS | H39: 15 | I39: =H39-J39 -> 14 | J39: =SUM(K39:Q39) -> 1 | O39: 1 | S39: =J39/H39 -> 0.066666667 | AD39: =C39&F39&G39&B39 -> BR1144WHSSKIEM | AE39: =C39&F39&G39 -> BR1144WHSS
A40: 46091 | B40: KIEM | C40: BR1144 | D40: =IF(C40=" "," ",VLOOKUP(C40,'Dữ Liệu'!$C$7:$D$134,2,FALSE)) -> GUA | E40: SHIRT | F40: WH | G40: S | H40: 71 | I40: =H40-J40 -> 65 | J40: =SUM(K40:Q40) -> 6 | O40: 1 | P40: 5 | S40: =J40/H40 -> 0.084507042 | AD40: =C40&F40&G40&B40 -> BR1144WHSKIEM | AE40: =C40&F40&G40 -> BR1144WHS
A41: 46091 | B41: KIEM | C41: BR1144 | D41: =IF(C41=" "," ",VLOOKUP(C41,'Dữ Liệu'!$C$7:$D$134,2,FALSE)) -> GUA | E41: SHIRT | F41: WH | G41: M | H41: 112 | I41: =H41-J41 -> 100 | J41: =SUM(K41:Q41) -> 12 | O41: 3 | P41: 9 | S41: =J41/H41 -> 0.10714286 | AD41: =C41&F41&G41&B41 -> BR1144WHMKIEM | AE41: =C41&F41&G41 -> BR1144WHM
A42: 46091 | B42: KIEM | C42: BR1144 | D42: =IF(C42=" "," ",VLOOKUP(C42,'Dữ Liệu'!$C$7:$D$134,2,FALSE)) -> GUA | E42: SHIRT | F42: WH | G42: L | H42: 7 | I42: =H42-J42 -> 7 | J42: =SUM(K42:Q42) -> 0 | S42: =J42/H42 -> 0 | AD42: =C42&F42&G42&B42 -> BR1144WHLKIEM | AE42: =C42&F42&G42 -> BR1144WHL
A43: 46091 | B43: KIEM | C43: BR1144 | D43: =IF(C43=" "," ",VLOOKUP(C43,'Dữ Liệu'!$C$7:$D$134,2,FALSE)) -> GUA | E43: SHIRT | F43: WH | G43: LL | H43: 1 | I43: =H43-J43 -> 1 | J43: =SUM(K43:Q43) -> 0 | S43: =J43/H43 -> 0 | AD43: =C43&F43&G43&B43 -> BR1144WHLLKIEM | AE43: =C43&F43&G43 -> BR1144WHLL
A44: 46091 | B44: KIEM | C44: BR1144 | D44: =IF(C44=" "," ",VLOOKUP(C44,'Dữ Liệu'!$C$7:$D$134,2,FALSE)) -> GUA | E44: SHIRT | F44: WH | G44: EL | H44: 51 | I44: =H44-J44 -> 48 | J44: =SUM(K44:Q44) -> 3 | P44: 3 | S44: =J44/H44 -> 0.058823529 | AD44: =C44&F44&G44&B44 -> BR1144WHELKIEM | AE44: =C44&F44&G44 -> BR1144WHEL
A45: 46091 | B45: KIEM | C45: BR1144 | D45: =IF(C45=" "," ",VLOOKUP(C45,'Dữ Liệu'!$C$7:$D$134,2,FALSE)) -> GUA | E45: SHIRT | F45: WH | G45: 4L | H45: 30 | I45: =H45-J45 -> 28 | J45: =SUM(K45:Q45) -> 2 | O45: 1 | P45: 1 | S45: =J45/H45 -> 0.066666667 | AD45: =C45&F45&G45&B45 -> BR1144WH4LKIEM | AE45: =C45&F45&G45 -> BR1144WH4L
A46: 46091 | B46: KIEM | C46: BR1144 | D46: =IF(C46=" "," ",VLOOKUP(C46,'Dữ Liệu'!$C$7:$D$134,2,FALSE)) -> GUA | E46: SHIRT | F46: WH | G46: 5L | H46: 10 | I46: =H46-J46 -> 9 | J46: =SUM(K46:Q46) -> 1 | O46: 1 | S46: =J46/H46 -> 0.1 | AD46: =C46&F46&G46&B46 -> BR1144WH5LKIEM | AE46: =C46&F46&G46 -> BR1144WH5L
A47: 46091 | B47: KIEM | C47: BR1144 | D47: =IF(C47=" "," ",VLOOKUP(C47,'Dữ Liệu'!$C$7:$D$134,2,FALSE)) -> GUA | E47: SHIRT | F47: WH | G47: 6L | H47: 10 | I47: =H47-J47 -> 9 | J47: =SUM(K47:Q47) -> 1 | P47: 1 | S47: =J47/H47 -> 0.1 | AD47: =C47&F47&G47&B47 -> BR1144WH6LKIEM | AE47: =C47&F47&G47 -> BR1144WH6L
A48: 46091 | B48: KIEM | C48: BR9071 | D48: =IF(C48=" "," ",VLOOKUP(C48,'Dữ Liệu'!$C$7:$D$134,2,FALSE)) -> GUA | E48: SHIRT | F48: WH | G48: S | H48: 1 | I48: =H48-J48 -> 1 | J48: =SUM(K48:Q48) -> 0 | S48: =J48/H48 -> 0 | AD48: =C48&F48&G48&B48 -> BR9071WHSKIEM | AE48: =C48&F48&G48 -> BR9071WHS
A49: 46091 | B49: KIEM | C49: BR9071 | D49: =IF(C49=" "," ",VLOOKUP(C49,'Dữ Liệu'!$C$7:$D$134,2,FALSE)) -> GUA | E49: SHIRT | F49: WH | G49: M | H49: 2 | I49: =H49-J49 -> 2 | J49: =SUM(K49:Q49) -> 0 | S49: =J49/H49 -> 0 | AD49: =C49&F49&G49&B49 -> BR9071WHMKIEM | AE49: =C49&F49&G49 -> BR9071WHM
A50: 46091 | B50: KIEM | C50: BR9071 | D50: =IF(C50=" "," ",VLOOKUP(C50,'Dữ Liệu'!$C$7:$D$134,2,FALSE)) -> GUA | E50: SHIRT | F50: WH | G50: L | H50: 1 | I50: =H50-J50 -> 1 | J50: =SUM(K50:Q50) -> 0 | S50: =J50/H50 -> 0 | AD50: =C50&F50&G50&B50 -> BR9071WHLKIEM | AE50: =C50&F50&G50 -> BR9071WHL
A51: 46091 | B51: KIEM | C51: BR9071 | D51: =IF(C51=" "," ",VLOOKUP(C51,'Dữ Liệu'!$C$7:$D$134,2,FALSE)) -> GUA | E51: SHIRT | F51: WH | G51: LL | H51: 1 | I51: =H51-J51 -> 1 | J51: =SUM(K51:Q51) -> 0 | S51: =J51/H51 -> 0 | AD51: =C51&F51&G51&B51 -> BR9071WHLLKIEM | AE51: =C51&F51&G51 -> BR9071WHLL
A52: 46091 | B52: KIEM | C52: BR9071 | D52: =IF(C52=" "," ",VLOOKUP(C52,'Dữ Liệu'!$C$7:$D$134,2,FALSE)) -> GUA | E52: SHIRT | F52: WH | G52: EL | H52: 2 | I52: =H52-J52 -> 1 | J52: =SUM(K52:Q52) -> 1 | O52: 1 | S52: =J52/H52 -> 0.5 | AD52: =C52&F52&G52&B52 -> BR9071WHELKIEM | AE52: =C52&F52&G52 -> BR9071WHEL
A53: 46091 | B53: TAIKIEM | C53: BR1144 | D53: =IF(C53=" "," ",VLOOKUP(C53,'Dữ Liệu'!$C$7:$D$134,2,FALSE)) -> GUA | E53: SHIRT | F53: WH | G53: SS | H53: 1 | I53: =H53-J53 -> 1 | J53: =SUM(K53:Q53) -> 0 | S53: =J53/H53 -> 0 | AD53: =C53&F53&G53&B53 -> BR1144WHSSTAIKIEM | AE53: =C53&F53&G53 -> BR1144WHSS
A54: 46091 | B54: TAIKIEM | C54: BR1144 | D54: =IF(C54=" "," ",VLOOKUP(C54,'Dữ Liệu'!$C$7:$D$134,2,FALSE)) -> GUA | E54: SHIRT | F54: WH | G54: S | H54: 6 | I54: =H54-J54 -> 6 | J54: =SUM(K54:Q54) -> 0 | S54: =J54/H54 -> 0 | AD54: =C54&F54&G54&B54 -> BR1144WHSTAIKIEM | AE54: =C54&F54&G54 -> BR1144WHS
A55: 46091 | B55: TAIKIEM | C55: BR1144 | D55: =IF(C55=" "," ",VLOOKUP(C55,'Dữ Liệu'!$C$7:$D$134,2,FALSE)) -> GUA | E55: SHIRT | F55: WH | G55: M | H55: 12 | I55: =H55-J55 -> 12 | J55: =SUM(K55:Q55) -> 0 | S55: =J55/H55 -> 0 | AD55: =C55&F55&G55&B55 -> BR1144WHMTAIKIEM | AE55: =C55&F55&G55 -> BR1144WHM
A56: 46091 | B56: TAIKIEM | C56: BR1144 | D56: =IF(C56=" "," ",VLOOKUP(C56,'Dữ Liệu'!$C$7:$D$134,2,FALSE)) -> GUA | E56: SHIRT | F56: WH | G56: EL | H56: 3 | I56: =H56-J56 -> 3 | J56: =SUM(K56:Q56) -> 0 | S56: =J56/H56 -> 0 | AD56: =C56&F56&G56&B56 -> BR1144WHELTAIKIEM | AE56: =C56&F56&G56 -> BR1144WHEL
A57: 46091 | B57: TAIKIEM | C57: BR1144 | D57: =IF(C57=" "," ",VLOOKUP(C57,'Dữ Liệu'!$C$7:$D$134,2,FALSE)) -> GUA | E57: SHIRT | F57: WH | G57: 4L | H57: 2 | I57: =H57-J57 -> 2 | J57: =SUM(K57:Q57) -> 0 | S57: =J57/H57 -> 0 | AD57: =C57&F57&G57&B57 -> BR1144WH4LTAIKIEM | AE57: =C57&F57&G57 -> BR1144WH4L
A58: 46091 | B58: TAIKIEM | C58: BR1144 | D58: =IF(C58=" "," ",VLOOKUP(C58,'Dữ Liệu'!$C$7:$D$134,2,FALSE)) -> GUA | E58: SHIRT | F58: WH | G58: 5L | H58: 1 | I58: =H58-J58 -> 1 | J58: =SUM(K58:Q58) -> 0 | S58: =J58/H58 -> 0 | AD58: =C58&F58&G58&B58 -> BR1144WH5LTAIKIEM | AE58: =C58&F58&G58 -> BR1144WH5L
A59: 46091 | B59: TAIKIEM | C59: BR1144 | D59: =IF(C59=" "," ",VLOOKUP(C59,'Dữ Liệu'!$C$7:$D$134,2,FALSE)) -> GUA | E59: SHIRT | F59: WH | G59: 6L | H59: 1 | I59: =H59-J59 -> 1 | J59: =SUM(K59:Q59) -> 0 | S59: =J59/H59 -> 0 | AD59: =C59&F59&G59&B59 -> BR1144WH6LTAIKIEM | AE59: =C59&F59&G59 -> BR1144WH6L
A60: 46091 | B60: TAIKIEM | C60: BR9071 | D60: =IF(C60=" "," ",VLOOKUP(C60,'Dữ Liệu'!$C$7:$D$134,2,FALSE)) -> GUA | E60: SHIRT | F60: WH | G60: EL | H60: 1 | I60: =H60-J60 -> 1 | J60: =SUM(K60:Q60) -> 0 | S60: =J60/H60 -> 0 | AD60: =C60&F60&G60&B60 -> BR9071WHELTAIKIEM | AE60: =C60&F60&G60 -> BR9071WHEL
A61: 46091 | B61: KIEM | C61: HS8078 | D61: =IF(C61=" "," ",VLOOKUP(C61,'Dữ Liệu'!$C$7:$D$134,2,FALSE)) -> GUA | E61: SHIRT | F61: WH | G61: SS | H61: 20 | I61: =H61-J61 -> 18 | J61: =SUM(K61:Q61) -> 2 | P61: 2 | S61: =J61/H61 -> 0.1 | AD61: =C61&F61&G61&B61 -> HS8078WHSSKIEM | AE61: =C61&F61&G61 -> HS8078WHSS
A62: 46091 | B62: KIEM | C62: HS8078 | D62: =IF(C62=" "," ",VLOOKUP(C62,'Dữ Liệu'!$C$7:$D$134,2,FALSE)) -> GUA | E62: SHIRT | F62: WH | G62: S | H62: 70 | I62: =H62-J62 -> 64 | J62: =SUM(K62:Q62) -> 6 | O62: 1 | P62: 5 | S62: =J62/H62 -> 0.085714286 | AD62: =C62&F62&G62&B62 -> HS8078WHSKIEM | AE62: =C62&F62&G62 -> HS8078WHS
A63: 46091 | B63: KIEM | C63: HS8078 | D63: =IF(C63=" "," ",VLOOKUP(C63,'Dữ Liệu'!$C$7:$D$134,2,FALSE)) -> GUA | E63: SHIRT | F63: WH | G63: M | H63: 40 | I63: =H63-J63 -> 36 | J63: =SUM(K63:Q63) -> 4 | O63: 1 | P63: 3 | S63: =J63/H63 -> 0.1 | AD63: =C63&F63&G63&B63 -> HS8078WHMKIEM | AE63: =C63&F63&G63 -> HS8078WHM
A64: 46091 | B64: KIEM | C64: HS8078 | D64: =IF(C64=" "," ",VLOOKUP(C64,'Dữ Liệu'!$C$7:$D$134,2,FALSE)) -> GUA | E64: SHIRT | F64: WH | G64: L | H64: 19 | I64: =H64-J64 -> 17 | J64: =SUM(K64:Q64) -> 2 | O64: 1 | P64: 1 | S64: =J64/H64 -> 0.10526316 | AD64: =C64&F64&G64&B64 -> HS8078WHLKIEM | AE64: =C64&F64&G64 -> HS8078WHL
A65: 46091 | B65: KIEM | C65: HS8078 | D65: =IF(C65=" "," ",VLOOKUP(C65,'Dữ Liệu'!$C$7:$D$134,2,FALSE)) -> GUA | E65: SHIRT | F65: WH | G65: LL | H65: 24 | I65: =H65-J65 -> 22 | J65: =SUM(K65:Q65) -> 2 | P65: 2 | S65: =J65/H65 -> 0.083333333 | AD65: =C65&F65&G65&B65 -> HS8078WHLLKIEM | AE65: =C65&F65&G65 -> HS8078WHLL
A66: 46091 | B66: KIEM | C66: HS8078 | D66: =IF(C66=" "," ",VLOOKUP(C66,'Dữ Liệu'!$C$7:$D$134,2,FALSE)) -> GUA | E66: SHIRT | F66: WH | G66: BL | H66: 30 | I66: =H66-J66 -> 27 | J66: =SUM(K66:Q66) -> 3 | O66: 1 | P66: 2 | S66: =J66/H66 -> 0.1 | AD66: =C66&F66&G66&B66 -> HS8078WHBLKIEM | AE66: =C66&F66&G66 -> HS8078WHBL
A67: 46091 | B67: KIEM | C67: HS8078 | D67: =IF(C67=" "," ",VLOOKUP(C67,'Dữ Liệu'!$C$7:$D$134,2,FALSE)) -> GUA | E67: SHIRT | F67: WH | G67: 4L | H67: 20 | I67: =H67-J67 -> 19 | J67: =SUM(K67:Q67) -> 1 | P67: 1 | S67: =J67/H67 -> 0.05 | AD67: =C67&F67&G67&B67 -> HS8078WH4LKIEM | AE67: =C67&F67&G67 -> HS8078WH4L
A68: 46091 | B68: KIEM | C68: HS8078 | D68: =IF(C68=" "," ",VLOOKUP(C68,'Dữ Liệu'!$C$7:$D$134,2,FALSE)) -> GUA | E68: SHIRT | F68: WH | G68: 5L | H68: 10 | I68: =H68-J68 -> 9 | J68: =SUM(K68:Q68) -> 1 | P68: 1 | S68: =J68/H68 -> 0.1 | AD68: =C68&F68&G68&B68 -> HS8078WH5LKIEM | AE68: =C68&F68&G68 -> HS8078WH5L
A69: 46091 | B69: TAIKIEM | C69: HS8078 | D69: =IF(C69=" "," ",VLOOKUP(C69,'Dữ Liệu'!$C$7:$D$134,2,FALSE)) -> GUA | E69: SHIRT | F69: WH | G69: SS | H69: 2 | I69: =H69-J69 -> 2 | J69: =SUM(K69:Q69) -> 0 | S69: =J69/H69 -> 0 | AD69: =C69&F69&G69&B69 -> HS8078WHSSTAIKIEM | AE69: =C69&F69&G69 -> HS8078WHSS
A70: 46091 | B70: TAIKIEM | C70: HS8078 | D70: =IF(C70=" "," ",VLOOKUP(C70,'Dữ Liệu'!$C$7:$D$134,2,FALSE)) -> GUA | E70: SHIRT | F70: WH | G70: S | H70: 6 | I70: =H70-J70 -> 6 | J70: =SUM(K70:Q70) -> 0 | S70: =J70/H70 -> 0 | AD70: =C70&F70&G70&B70 -> HS8078WHSTAIKIEM | AE70: =C70&F70&G70 -> HS8078WHS
A71: 46091 | B71: TAIKIEM | C71: HS8078 | D71: =IF(C71=" "," ",VLOOKUP(C71,'Dữ Liệu'!$C$7:$D$134,2,FALSE)) -> GUA | E71: SHIRT | F71: WH | G71: M | H71: 4 | I71: =H71-J71 -> 4 | J71: =SUM(K71:Q71) -> 0 | S71: =J71/H71 -> 0 | AD71: =C71&F71&G71&B71 -> HS8078WHMTAIKIEM | AE71: =C71&F71&G71 -> HS8078WHM
A72: 46091 | B72: TAIKIEM | C72: HS8078 | D72: =IF(C72=" "," ",VLOOKUP(C72,'Dữ Liệu'!$C$7:$D$134,2,FALSE)) -> GUA | E72: SHIRT | F72: WH | G72: L | H72: 2 | I72: =H72-J72 -> 2 | J72: =SUM(K72:Q72) -> 0 | S72: =J72/H72 -> 0 | AD72: =C72&F72&G72&B72 -> HS8078WHLTAIKIEM | AE72: =C72&F72&G72 -> HS8078WHL
A73: 46091 | B73: TAIKIEM | C73: HS8078 | D73: =IF(C73=" "," ",VLOOKUP(C73,'Dữ Liệu'!$C$7:$D$134,2,FALSE)) -> GUA | E73: SHIRT | F73: WH | G73: LL | H73: 2 | I73: =H73-J73 -> 2 | J73: =SUM(K73:Q73) -> 0 | S73: =J73/H73 -> 0 | AD73: =C73&F73&G73&B73 -> HS8078WHLLTAIKIEM | AE73: =C73&F73&G73 -> HS8078WHLL | AH73: 46086
A74: 46091 | B74: TAIKIEM | C74: HS8078 | D74: =IF(C74=" "," ",VLOOKUP(C74,'Dữ Liệu'!$C$7:$D$134,2,FALSE)) -> GUA | E74: SHIRT | F74: WH | G74: BL | H74: 3 | I74: =H74-J74 -> 3 | J74: =SUM(K74:Q74) -> 0 | S74: =J74/H74 -> 0 | AD74: =C74&F74&G74&B74 -> HS8078WHBLTAIKIEM | AE74: =C74&F74&G74 -> HS8078WHBL
A75: 46091 | B75: TAIKIEM | C75: HS8078 | D75: =IF(C75=" "," ",VLOOKUP(C75,'Dữ Liệu'!$C$7:$D$134,2,FALSE)) -> GUA | E75: SHIRT | F75: WH | G75: 4L | H75: 1 | I75: =H75-J75 -> 1 | J75: =SUM(K75:Q75) -> 0 | S75: =J75/H75 -> 0 | AD75: =C75&F75&G75&B75 -> HS8078WH4LTAIKIEM | AE75: =C75&F75&G75 -> HS8078WH4L
A76: 46091 | B76: TAIKIEM | C76: HS8078 | D76: =IF(C76=" "," ",VLOOKUP(C76,'Dữ Liệu'!$C$7:$D$134,2,FALSE)) -> GUA | E76: SHIRT | F76: WH | G76: 5L | H76: 1 | I76: =H76-J76 -> 1 | J76: =SUM(K76:Q76) -> 0 | S76: =J76/H76 -> 0 | AD76: =C76&F76&G76&B76 -> HS8078WH5LTAIKIEM | AE76: =C76&F76&G76 -> HS8078WH5L
A77: 46093 | B77: KIEM | C77: BR1108 | D77: =IF(C77=" "," ",VLOOKUP(C77,'Dữ Liệu'!$C$7:$D$134,2,FALSE)) -> GUA | E77: SHIRT | F77: WH | G77: S | H77: 33 | I77: =H77-J77 -> 30 | J77: =SUM(K77:Q77) -> 3 | M77: 1 | O77: 1 | P77: 1 | S77: =J77/H77 -> 0.090909091 | AD77: =C77&F77&G77&B77 -> BR1108WHSKIEM | AE77: =C77&F77&G77 -> BR1108WHS
A78: 46093 | B78: KIEM | C78: BR1108 | D78: =IF(C78=" "," ",VLOOKUP(C78,'Dữ Liệu'!$C$7:$D$134,2,FALSE)) -> GUA | E78: SHIRT | F78: WH | G78: M | H78: 192 | I78: =H78-J78 -> 165 | J78: =SUM(K78:Q78) -> 27 | M78: 5 | O78: 14 | P78: 8 | S78: =J78/H78 -> 0.140625 | AD78: =C78&F78&G78&B78 -> BR1108WHMKIEM | AE78: =C78&F78&G78 -> BR1108WHM
A79: 46093 | B79: KIEM | C79: BR1108 | D79: =IF(C79=" "," ",VLOOKUP(C79,'Dữ Liệu'!$C$7:$D$134,2,FALSE)) -> GUA | E79: SHIRT | F79: WH | G79: L | H79: 143 | I79: =H79-J79 -> 131 | J79: =SUM(K79:Q79) -> 12 | M79: 2 | O79: 7 | P79: 3 | S79: =J79/H79 -> 0.083916084 | AD79: =C79&F79&G79&B79 -> BR1108WHLKIEM | AE79: =C79&F79&G79 -> BR1108WHL
A80: 46093 | B80: KIEM | C80: BR1108 | D80: =IF(C80=" "," ",VLOOKUP(C80,'Dữ Liệu'!$C$7:$D$134,2,FALSE)) -> GUA | E80: SHIRT | F80: WH | G80: LL | H80: 35 | I80: =H80-J80 -> 30 | J80: =SUM(K80:Q80) -> 5 | M80: 1 | O80: 1 | P80: 3 | S80: =J80/H80 -> 0.14285714 | AD80: =C80&F80&G80&B80 -> BR1108WHLLKIEM | AE80: =C80&F80&G80 -> BR1108WHLL
A81: 46093 | B81: TAIKIEM | C81: BR1108 | D81: =IF(C81=" "," ",VLOOKUP(C81,'Dữ Liệu'!$C$7:$D$134,2,FALSE)) -> GUA | E81: SHIRT | F81: WH | G81: S | H81: 3 | I81: =H81-J81 -> 3 | J81: =SUM(K81:Q81) -> 0 | S81: =J81/H81 -> 0 | AD81: =C81&F81&G81&B81 -> BR1108WHSTAIKIEM | AE81: =C81&F81&G81 -> BR1108WHS
A82: 46093 | B82: TAIKIEM | C82: BR1108 | D82: =IF(C82=" "," ",VLOOKUP(C82,'Dữ Liệu'!$C$7:$D$134,2,FALSE)) -> GUA | E82: SHIRT | F82: WH | G82: M | H82: 27 | I82: =H82-J82 -> 27 | J82: =SUM(K82:Q82) -> 0 | S82: =J82/H82 -> 0 | AD82: =C82&F82&G82&B82 -> BR1108WHMTAIKIEM | AE82: =C82&F82&G82 -> BR1108WHM
A83: 46093 | B83: TAIKIEM | C83: BR1108 | D83: =IF(C83=" "," ",VLOOKUP(C83,'Dữ Liệu'!$C$7:$D$134,2,FALSE)) -> GUA | E83: SHIRT | F83: WH | G83: L | H83: 12 | I83: =H83-J83 -> 12 | J83: =SUM(K83:Q83) -> 0 | S83: =J83/H83 -> 0 | AD83: =C83&F83&G83&B83 -> BR1108WHLTAIKIEM | AE83: =C83&F83&G83 -> BR1108WHL
A84: 46093 | B84: TAIKIEM | C84: BR1108 | D84: =IF(C84=" "," ",VLOOKUP(C84,'Dữ Liệu'!$C$7:$D$134,2,FALSE)) -> GUA | E84: SHIRT | F84: WH | G84: LL | H84: 5 | I84: =H84-J84 -> 5 | J84: =SUM(K84:Q84) -> 0 | S84: =J84/H84 -> 0 | AD84: =C84&F84&G84&B84 -> BR1108WHLLTAIKIEM | AE84: =C84&F84&G84 -> BR1108WHLL
A85: 46093 | B85: KIEM | C85: HS8078 | D85: =IF(C85=" "," ",VLOOKUP(C85,'Dữ Liệu'!$C$7:$D$134,2,FALSE)) -> GUA | E85: SHIRT | F85: WH | G85: S | H85: 1 | I85: =H85-J85 -> 1 | J85: =SUM(K85:Q85) -> 0 | S85: =J85/H85 -> 0 | AD85: =C85&F85&G85&B85 -> HS8078WHSKIEM | AE85: =C85&F85&G85 -> HS8078WHS
A86: 46093 | B86: KIEM | C86: HS8078 | D86: =IF(C86=" "," ",VLOOKUP(C86,'Dữ Liệu'!$C$7:$D$134,2,FALSE)) -> GUA | E86: SHIRT | F86: WH | G86: L | H86: 2 | I86: =H86-J86 -> 2 | J86: =SUM(K86:Q86) -> 0 | S86: =J86/H86 -> 0 | AD86: =C86&F86&G86&B86 -> HS8078WHLKIEM | AE86: =C86&F86&G86 -> HS8078WHL
A87: 46093 | B87: KIEM | C87: HS8078 | D87: =IF(C87=" "," ",VLOOKUP(C87,'Dữ Liệu'!$C$7:$D$134,2,FALSE)) -> GUA | E87: SHIRT | F87: WH | G87: LL | H87: 1 | I87: =H87-J87 -> 1 | J87: =SUM(K87:Q87) -> 0 | S87: =J87/H87 -> 0 | AD87: =C87&F87&G87&B87 -> HS8078WHLLKIEM | AE87: =C87&F87&G87 -> HS8078WHLL
A88: 46094 | B88: KIEM | C88: BR9125 | D88: =IF(C88=" "," ",VLOOKUP(C88,'Dữ Liệu'!$C$7:$D$134,2,FALSE)) -> GUA | E88: SHIRT | F88: WH | G88: M | H88: 419 | I88: =H88-J88 -> 367 | J88: =SUM(K88:Q88) -> 52 | K88: 2 | M88: 7 | N88: 5 | O88: 29 | P88: 9 | S88: =J88/H88 -> 0.12410501 | AD88: =C88&F88&G88&B88 -> BR9125WHMKIEM | AE88: =C88&F88&G88 -> BR9125WHM
A89: 46094 | B89: TAIKIEM | C89: BR9125 | D89: =IF(C89=" "," ",VLOOKUP(C89,'Dữ Liệu'!$C$7:$D$134,2,FALSE)) -> GUA | E89: SHIRT | F89: WH | G89: M | H89: 52 | I89: =H89-J89 -> 52 | J89: =SUM(K89:Q89) -> 0 | S89: =J89/H89 -> 0 | AD89: =C89&F89&G89&B89 -> BR9125WHMTAIKIEM | AE89: =C89&F89&G89 -> BR9125WHM
A90: 46095 | B90: KIEM | C90: BR1108 | D90: =IF(C90=" "," ",VLOOKUP(C90,'Dữ Liệu'!$C$7:$D$134,2,FALSE)) -> GUA | E90: SHIRT | F90: WH | G90: S | H90: 17 | I90: =H90-J90 -> 16 | J90: =SUM(K90:Q90) -> 1 | O90: 1 | S90: =J90/H90 -> 0.058823529 | AD90: =C90&F90&G90&B90 -> BR1108WHSKIEM | AE90: =C90&F90&G90 -> BR1108WHS
A91: 46095 | B91: KIEM | C91: BR1108 | D91: =IF(C91=" "," ",VLOOKUP(C91,'Dữ Liệu'!$C$7:$D$134,2,FALSE)) -> GUA | E91: SHIRT | F91: WH | G91: M | H91: 38 | I91: =H91-J91 -> 33 | J91: =SUM(K91:Q91) -> 5 | M91: 2 | O91: 2 | P91: 1 | S91: =J91/H91 -> 0.13157895 | AD91: =C91&F91&G91&B91 -> BR1108WHMKIEM | AE91: =C91&F91&G91 -> BR1108WHM
A92: 46095 | B92: KIEM | C92: BR1108 | D92: =IF(C92=" "," ",VLOOKUP(C92,'Dữ Liệu'!$C$7:$D$134,2,FALSE)) -> GUA | E92: SHIRT | F92: WH | G92: L | H92: 28 | I92: =H92-J92 -> 26 | J92: =SUM(K92:Q92) -> 2 | O92: 1 | P92: 1 | S92: =J92/H92 -> 0.071428571 | AD92: =C92&F92&G92&B92 -> BR1108WHLKIEM | AE92: =C92&F92&G92 -> BR1108WHL
A93: 46095 | B93: KIEM | C93: BR1108 | D93: =IF(C93=" "," ",VLOOKUP(C93,'Dữ Liệu'!$C$7:$D$134,2,FALSE)) -> GUA | E93: SHIRT | F93: WH | G93: LL | H93: 10 | I93: =H93-J93 -> 9 | J93: =SUM(K93:Q93) -> 1 | O93: 1 | S93: =J93/H93 -> 0.1 | AD93: =C93&F93&G93&B93 -> BR1108WHLLKIEM | AE93: =C93&F93&G93 -> BR1108WHLL
A94: 46095 | B94: TAIKIEM | C94: BR1108 | D94: =IF(C94=" "," ",VLOOKUP(C94,'Dữ Liệu'!$C$7:$D$134,2,FALSE)) -> GUA | E94: SHIRT | F94: WH | G94: S | H94: 1 | I94: =H94-J94 -> 1 | J94: =SUM(K94:Q94) -> 0 | S94: =J94/H94 -> 0 | AD94: =C94&F94&G94&B94 -> BR1108WHSTAIKIEM | AE94: =C94&F94&G94 -> BR1108WHS
A95: 46095 | B95: TAIKIEM | C95: BR1108 | D95: =IF(C95=" "," ",VLOOKUP(C95,'Dữ Liệu'!$C$7:$D$134,2,FALSE)) -> GUA | E95: SHIRT | F95: WH | G95: M | H95: 5 | I95: =H95-J95 -> 5 | J95: =SUM(K95:Q95) -> 0 | S95: =J95/H95 -> 0 | AD95: =C95&F95&G95&B95 -> BR1108WHMTAIKIEM | AE95: =C95&F95&G95 -> BR1108WHM
A96: 46095 | B96: TAIKIEM | C96: BR1108 | D96: =IF(C96=" "," ",VLOOKUP(C96,'Dữ Liệu'!$C$7:$D$134,2,FALSE)) -> GUA | E96: SHIRT | F96: WH | G96: L | H96: 2 | I96: =H96-J96 -> 2 | J96: =SUM(K96:Q96) -> 0 | S96: =J96/H96 -> 0 | AD96: =C96&F96&G96&B96 -> BR1108WHLTAIKIEM | AE96: =C96&F96&G96 -> BR1108WHL
A97: 46095 | B97: TAIKIEM | C97: BR1108 | D97: =IF(C97=" "," ",VLOOKUP(C97,'Dữ Liệu'!$C$7:$D$134,2,FALSE)) -> GUA | E97: SHIRT | F97: WH | G97: LL | H97: 1 | I97: =H97-J97 -> 1 | J97: =SUM(K97:Q97) -> 0 | S97: =J97/H97 -> 0 | AD97: =C97&F97&G97&B97 -> BR1108WHLLTAIKIEM | AE97: =C97&F97&G97 -> BR1108WHLL
A98: 46095 | B98: KIEM | C98: BR9125 | D98: =IF(C98=" "," ",VLOOKUP(C98,'Dữ Liệu'!$C$7:$D$134,2,FALSE)) -> GUA | E98: SHIRT | F98: WH | G98: L | H98: 188 | I98: =H98-J98 -> 163 | J98: =SUM(K98:Q98) -> 25 | K98: 1 | M98: 3 | O98: 14 | P98: 7 | S98: =J98/H98 -> 0.13297872 | AD98: =C98&F98&G98&B98 -> BR9125WHLKIEM | AE98: =C98&F98&G98 -> BR9125WHL
A99: 46095 | B99: KIEM | C99: BR9125 | D99: =IF(C99=" "," ",VLOOKUP(C99,'Dữ Liệu'!$C$7:$D$134,2,FALSE)) -> GUA | E99: SHIRT | F99: WH | G99: LL | H99: 104 | I99: =H99-J99 -> 93 | J99: =SUM(K99:Q99) -> 11 | M99: 2 | O99: 6 | P99: 3 | S99: =J99/H99 -> 0.10576923 | AD99: =C99&F99&G99&B99 -> BR9125WHLLKIEM | AE99: =C99&F99&G99 -> BR9125WHLL
A100: 46095 | B100: TAIKIEM | C100: BR9125 | D100: =IF(C100=" "," ",VLOOKUP(C100,'Dữ Liệu'!$C$7:$D$134,2,FALSE)) -> GUA | E100: SHIRT | F100: WH | G100: L | H100: 25 | I100: =H100-J100 -> 25 | J100: =SUM(K100:Q100) -> 0 | S100: =J100/H100 -> 0 | AD100: =C100&F100&G100&B100 -> BR9125WHLTAIKIEM | AE100: =C100&F100&G100 -> BR9125WHL
...

Sheet Cumulative Table
A1: TAIYO NISSHIN VIETNAM CO.,LTD 太陽日新ベトナム株式会社
A2: BÁO CÁO KẾT QUẢ KIỂM HÀNG 検品 結 果 報 告 書
A3: 累計表(Cumulative Table)
A4: 品番 | B4: ブランド | C4: 品目 | D4: カラー | E4: サイズ | F4: ロット数 | G4: 検品数(初回検品のみ) | H4: 再検品数量(2回目以降の検査も含む) | I4: 良品数(初回・それ以降の検査分含む) | J4: 検針良品数(初回・それ以降の検査分含む) | K4: 出荷済み数量 | O4: Thông số | P4: Phụ liệu | Q4: Ngoại quan | R4: Vải | S4: Dơ | T4: Lổi may | U4: Khác | V4: Kiểm Kim | W4: Tỉ lệ lỗi
A5: Style No | B5: Brand | C5: Item | D5: Color | E5: Size | F5: Order Qty | G5: Inspection Qty | H5: Re-inspection Qty | I5: A-Grade Qty | J5: A-Grade Qty | K5: Shipment Qty | O5: Measurment | P5: Material | Q5: Appearance | R5: Fabric | S5: Dirt | T5: Sewing | U5: Other | V5: Needle Inspection | W5: rate | Y5: KIỂM | AF5: TỔNG NGÀY KIỂM
A6: Mã hàng | B6: Thương hiệu | C6: Tên hàng | D6: Màu | E6: Size | F6: Số lượng đơn hàng | G6: SL kiểm hàng | H6: SL tái kiểm | I6: SL Hàng đạt | J6: SL Hàng đạt Kiểm kim | K6: SL xuất 1 | L6: SL xuất 2 | M6: SL xuất 3 | N6: TỔNG XUẤT | O6: 採寸不良 | P6: 付属不良 | Q6: 外観不良 | R6: 生地不良 | S6: 汚れ不良 | T6: 縫製不良 | U6: その他 | V6: 検針 | W6: 不良率 | Y6: NGÀY 2026/03/05 | AA6: NGÀY 2026/03/09 | AC6: NGÀY 2026/03/10 | AE6: 2026/03/05 - 03/10 | AF6: NGÀY BẮT ĐẦU | AG6: NGÀY KẾT THÚC | AH6: TỔNG SỐ HÀNG KIỂM | AI6: TỔNG SỐ HÀNG TÁI
A7: BR9125 | B7: =VLOOKUP($A7,'Daily Report'!$C$7:$E$263,2,FALSE) -> GUA | C7: =VLOOKUP($A7,'Daily Report'!$C$7:$E$263,3,FALSE) -> SHIRT | D7: WH | E7: SS | F7: =SUMIF('Dữ Liệu'!#REF!,'Cumulative Table'!$X7,'Dữ Liệu'!$H$7:$H$134) -> #REF! | G7: =SUMIF('Daily Report'!$AD$7:$AD$263,'Cumulative Table'!$X7&"KIEM",'Daily Report'!$H$7:$H$263) -> 0 | H7: =SUMIF('Daily Report'!$AD$7:$AD$263,'Cumulative Table'!$X7&"TAIKIEM",'Daily Report'!$H$7:$H$263) -> 0 | I7: =SUMIF('Daily Report'!$AE$7:$AE$263,'Cumulative Table'!$X7,'Daily Report'!$I$7:$I$263) -> 0 | J7: =SUMIF('Daily Report'!AE7:AE263,'Cumulative Table'!X7:X201,'Daily Report'!R7:R263) -> 0 | N7: =SUM(K7:M7) -> 0 | O7: =SUMIF('Daily Report'!$AE$7:$AE$263,'Cumulative Table'!$X7,'Daily Report'!$K$7:$K$263) -> 0 | P7: =SUMIF('Daily Report'!$AE$7:$AE$263,'Cumulative Table'!$X7,'Daily Report'!$L$7:$L$263) -> 0 | Q7: =SUMIF('Daily Report'!$AE$7:$AE$263,'Cumulative Table'!$X7,'Daily Report'!$M$7:$M$263) -> 0 | R7: =SUMIF('Daily Report'!$AE$7:$AE$263,'Cumulative Table'!$X7,'Daily Report'!$N$7:$N$263) -> 0 | S7: =SUMIF('Daily Report'!$AE$7:$AE$263,'Cumulative Table'!$X7,'Daily Report'!$O$7:$O$263) -> 0 | T7: =SUMIF('Daily Report'!$AE$7:$AE$263,'Cumulative Table'!$X7,'Daily Report'!$P$7:$P$263) -> 0 | U7: =SUMIF('Daily Report'!$AE$7:$AE$263,'Cumulative Table'!$X7,'Daily Report'!$Q$7:$Q$263) -> 0 | W7: =H7/G7 -> #DIV/0! | X7: =A$7&D7&E7 -> BR9125WHSS | Y7: 46095 | Z7: =SUMIFS('Daily Report'!$H$7:$H$263, 'Daily Report'!$AD$7:$AD$263, $X7&"KIEM", 'Daily Report'!$A$7:$A$263, $Y$7) -> 0 | AA7: 46096 | AB7: =SUMIFS('Daily Report'!$H$7:$H$200,'Daily Report'!$AD$7:$AD$200,'Cumulative Table'!$X7&"KIEM",'Daily Report'!$A$7:$A$200,'Cumulative Table'!$AA$7) -> 0 | AC7: 46097 | AD7: =SUMIFS('Daily Report'!$H$7:$H$200,'Daily Report'!$AD$7:$AD$200,'Cumulative Table'!$X7&"KIEM",'Daily Report'!$A$7:$A$200,'Cumulative Table'!$AC$7) -> 0 | AE7: =SUMIFS('Daily Report'!$H$7:$H$200,'Daily Report'!$AD$7:$AD$200,'Cumulative Table'!$X7&"KIEM",'Daily Report'!$A$7:$A$200,">="&'Cumulative Table'!$Y$7,'Daily Report'!$A$7:$A$200,"<="&'Cumulative Table'!$AC$7) -> 0 | AF7: 46095 | AG7: 46097 | AH7: =SUMIFS('Daily Report'!$H$7:$H$200,'Daily Report'!$AD$7:$AD$200,'Cumulative Table'!$X7&"KIEM",'Daily Report'!$A$7:$A$200,">="&'Cumulative Table'!$AF$7,'Daily Report'!$A$7:$A$200,"<="&'Cumulative Table'!$AG$7) -> 0 | AI7: =SUMIFS('Daily Report'!$H$7:$H$200,'Daily Report'!$AD$7:$AD$200,'Cumulative Table'!$X7&"TAIKIEM",'Daily Report'!$A$7:$A$200,">="&'Cumulative Table'!$AF$7,'Daily Report'!$A$7:$A$200,"<="&'Cumulative Table'!$AG$7) -> 0
D8: WH | E8: S | F8: =SUMIF('Dữ Liệu'!#REF!,'Cumulative Table'!$X8,'Dữ Liệu'!$H$7:$H$134) -> #REF! | G8: =SUMIF('Daily Report'!$AD$7:$AD$263,'Cumulative Table'!$X8&"KIEM",'Daily Report'!$H$7:$H$263) -> 133 | H8: =SUMIF('Daily Report'!$AD$7:$AD$263,'Cumulative Table'!$X8&"TAIKIEM",'Daily Report'!$H$7:$H$263) -> 18 | I8: =SUMIF('Daily Report'!$AE$7:$AE$263,'Cumulative Table'!$X8,'Daily Report'!$I$7:$I$263) -> 133 | J8: =SUMIF('Daily Report'!AE8:AE264,'Cumulative Table'!X8:X202,'Daily Report'!R8:R264) -> 0 | N8: =SUM(K8:M8) -> 0 | O8: =SUMIF('Daily Report'!$AE$7:$AE$263,'Cumulative Table'!$X8,'Daily Report'!$K$7:$K$263) -> 0 | P8: =SUMIF('Daily Report'!$AE$7:$AE$263,'Cumulative Table'!$X8,'Daily Report'!$L$7:$L$263) -> 0 | Q8: =SUMIF('Daily Report'!$AE$7:$AE$263,'Cumulative Table'!$X8,'Daily Report'!$M$7:$M$263) -> 2 | R8: =SUMIF('Daily Report'!$AE$7:$AE$263,'Cumulative Table'!$X8,'Daily Report'!$N$7:$N$263) -> 0 | S8: =SUMIF('Daily Report'!$AE$7:$AE$263,'Cumulative Table'!$X8,'Daily Report'!$O$7:$O$263) -> 12 | T8: =SUMIF('Daily Report'!$AE$7:$AE$263,'Cumulative Table'!$X8,'Daily Report'!$P$7:$P$263) -> 4 | U8: =SUMIF('Daily Report'!$AE$7:$AE$263,'Cumulative Table'!$X8,'Daily Report'!$Q$7:$Q$263) -> 0 | W8: =H8/G8 -> 0.13533835 | X8: =A$7&D8&E8 -> BR9125WHS | Z8: =SUMIFS('Daily Report'!$H$7:$H$263, 'Daily Report'!$AD$7:$AD$263, $X8&"KIEM", 'Daily Report'!$A$7:$A$263, $Y$7) -> 0 | AB8: =SUMIFS('Daily Report'!$H$7:$H$200,'Daily Report'!$AD$7:$AD$200,'Cumulative Table'!$X8&"KIEM",'Daily Report'!$A$7:$A$200,'Cumulative Table'!$AA$7) -> 0 | AD8: =SUMIFS('Daily Report'!$H$7:$H$200,'Daily Report'!$AD$7:$AD$200,'Cumulative Table'!$X8&"KIEM",'Daily Report'!$A$7:$A$200,'Cumulative Table'!$AC$7) -> 133 | AE8: =SUMIFS('Daily Report'!$H$7:$H$200,'Daily Report'!$AD$7:$AD$200,'Cumulative Table'!$X8&"KIEM",'Daily Report'!$A$7:$A$200,">="&'Cumulative Table'!$Y$7,'Daily Report'!$A$7:$A$200,"<="&'Cumulative Table'!$AC$7) -> 133 | AH8: =SUMIFS('Daily Report'!$H$7:$H$200,'Daily Report'!$AD$7:$AD$200,'Cumulative Table'!$X8&"KIEM",'Daily Report'!$A$7:$A$200,">="&'Cumulative Table'!$AF$7,'Daily Report'!$A$7:$A$200,"<="&'Cumulative Table'!$AG$7) -> 133 | AI8: =SUMIFS('Daily Report'!$H$7:$H$200,'Daily Report'!$AD$7:$AD$200,'Cumulative Table'!$X8&"TAIKIEM",'Daily Report'!$A$7:$A$200,">="&'Cumulative Table'!$AF$7,'Daily Report'!$A$7:$A$200,"<="&'Cumulative Table'!$AG$7) -> 18
D9: WH | E9: M | F9: =SUMIF('Dữ Liệu'!#REF!,'Cumulative Table'!$X9,'Dữ Liệu'!$H$7:$H$134) -> #REF! | G9: =SUMIF('Daily Report'!$AD$7:$AD$263,'Cumulative Table'!$X9&"KIEM",'Daily Report'!$H$7:$H$263) -> 603 | H9: =SUMIF('Daily Report'!$AD$7:$AD$263,'Cumulative Table'!$X9&"TAIKIEM",'Daily Report'!$H$7:$H$263) -> 76 | I9: =SUMIF('Daily Report'!$AE$7:$AE$263,'Cumulative Table'!$X9,'Daily Report'!$I$7:$I$263) -> 603 | J9: =SUMIF('Daily Report'!AE9:AE265,'Cumulative Table'!X9:X203,'Daily Report'!R9:R265) -> 0 | N9: =SUM(K9:M9) -> 0 | O9: =SUMIF('Daily Report'!$AE$7:$AE$263,'Cumulative Table'!$X9,'Daily Report'!$K$7:$K$263) -> 2 | P9: =SUMIF('Daily Report'!$AE$7:$AE$263,'Cumulative Table'!$X9,'Daily Report'!$L$7:$L$263) -> 0 | Q9: =SUMIF('Daily Report'!$AE$7:$AE$263,'Cumulative Table'!$X9,'Daily Report'!$M$7:$M$263) -> 11 | R9: =SUMIF('Daily Report'!$AE$7:$AE$263,'Cumulative Table'!$X9,'Daily Report'!$N$7:$N$263) -> 5 | S9: =SUMIF('Daily Report'!$AE$7:$AE$263,'Cumulative Table'!$X9,'Daily Report'!$O$7:$O$263) -> 42 | T9: =SUMIF('Daily Report'!$AE$7:$AE$263,'Cumulative Table'!$X9,'Daily Report'!$P$7:$P$263) -> 16 | U9: =SUMIF('Daily Report'!$AE$7:$AE$263,'Cumulative Table'!$X9,'Daily Report'!$Q$7:$Q$263) -> 0 | W9: =H9/G9 -> 0.12603648 | X9: =A$7&D9&E9 -> BR9125WHM | Z9: =SUMIFS('Daily Report'!$H$7:$H$263, 'Daily Report'!$AD$7:$AD$263, $X9&"KIEM", 'Daily Report'!$A$7:$A$263, $Y$7) -> 0 | AB9: =SUMIFS('Daily Report'!$H$7:$H$200,'Daily Report'!$AD$7:$AD$200,'Cumulative Table'!$X9&"KIEM",'Daily Report'!$A$7:$A$200,'Cumulative Table'!$AA$7) -> 0 | AD9: =SUMIFS('Daily Report'!$H$7:$H$200,'Daily Report'!$AD$7:$AD$200,'Cumulative Table'!$X9&"KIEM",'Daily Report'!$A$7:$A$200,'Cumulative Table'!$AC$7) -> 184 | AE9: =SUMIFS('Daily Report'!$H$7:$H$200,'Daily Report'!$AD$7:$AD$200,'Cumulative Table'!$X9&"KIEM",'Daily Report'!$A$7:$A$200,">="&'Cumulative Table'!$Y$7,'Daily Report'!$A$7:$A$200,"<="&'Cumulative Table'!$AC$7) -> 184 | AH9: =SUMIFS('Daily Report'!$H$7:$H$200,'Daily Report'!$AD$7:$AD$200,'Cumulative Table'!$X9&"KIEM",'Daily Report'!$A$7:$A$200,">="&'Cumulative Table'!$AF$7,'Daily Report'!$A$7:$A$200,"<="&'Cumulative Table'!$AG$7) -> 184 | AI9: =SUMIFS('Daily Report'!$H$7:$H$200,'Daily Report'!$AD$7:$AD$200,'Cumulative Table'!$X9&"TAIKIEM",'Daily Report'!$A$7:$A$200,">="&'Cumulative Table'!$AF$7,'Daily Report'!$A$7:$A$200,"<="&'Cumulative Table'!$AG$7) -> 24
D10: WH | E10: L | F10: =SUMIF('Dữ Liệu'!#REF!,'Cumulative Table'!$X10,'Dữ Liệu'!$H$7:$H$134) -> #REF! | G10: =SUMIF('Daily Report'!$AD$7:$AD$263,'Cumulative Table'!$X10&"KIEM",'Daily Report'!$H$7:$H$263) -> 188 | H10: =SUMIF('Daily Report'!$AD$7:$AD$263,'Cumulative Table'!$X10&"TAIKIEM",'Daily Report'!$H$7:$H$263) -> 25 | I10: =SUMIF('Daily Report'!$AE$7:$AE$263,'Cumulative Table'!$X10,'Daily Report'!$I$7:$I$263) -> 188 | J10: =SUMIF('Daily Report'!AE10:AE266,'Cumulative Table'!X10:X204,'Daily Report'!R10:R266) -> 0 | N10: =SUM(K10:M10) -> 0 | O10: =SUMIF('Daily Report'!$AE$7:$AE$263,'Cumulative Table'!$X10,'Daily Report'!$K$7:$K$263) -> 1 | P10: =SUMIF('Daily Report'!$AE$7:$AE$263,'Cumulative Table'!$X10,'Daily Report'!$L$7:$L$263) -> 0 | Q10: =SUMIF('Daily Report'!$AE$7:$AE$263,'Cumulative Table'!$X10,'Daily Report'!$M$7:$M$263) -> 3 | R10: =SUMIF('Daily Report'!$AE$7:$AE$263,'Cumulative Table'!$X10,'Daily Report'!$N$7:$N$263) -> 0 | S10: =SUMIF('Daily Report'!$AE$7:$AE$263,'Cumulative Table'!$X10,'Daily Report'!$O$7:$O$263) -> 14 | T10: =SUMIF('Daily Report'!$AE$7:$AE$263,'Cumulative Table'!$X10,'Daily Report'!$P$7:$P$263) -> 7 | U10: =SUMIF('Daily Report'!$AE$7:$AE$263,'Cumulative Table'!$X10,'Daily Report'!$Q$7:$Q$263) -> 0 | W10: =H10/G10 -> 0.13297872 | X10: =A$7&D10&E10 -> BR9125WHL | Z10: =SUMIFS('Daily Report'!$H$7:$H$263, 'Daily Report'!$AD$7:$AD$263, $X10&"KIEM", 'Daily Report'!$A$7:$A$263, $Y$7) -> 188 | AB10: =SUMIFS('Daily Report'!$H$7:$H$200,'Daily Report'!$AD$7:$AD$200,'Cumulative Table'!$X10&"KIEM",'Daily Report'!$A$7:$A$200,'Cumulative Table'!$AA$7) -> 0 | AD10: =SUMIFS('Daily Report'!$H$7:$H$200,'Daily Report'!$AD$7:$AD$200,'Cumulative Table'!$X10&"KIEM",'Daily Report'!$A$7:$A$200,'Cumulative Table'!$AC$7) -> 0 | AE10: =SUMIFS('Daily Report'!$H$7:$H$200,'Daily Report'!$AD$7:$AD$200,'Cumulative Table'!$X10&"KIEM",'Daily Report'!$A$7:$A$200,">="&'Cumulative Table'!$Y$7,'Daily Report'!$A$7:$A$200,"<="&'Cumulative Table'!$AC$7) -> 188 | AH10: =SUMIFS('Daily Report'!$H$7:$H$200,'Daily Report'!$AD$7:$AD$200,'Cumulative Table'!$X10&"KIEM",'Daily Report'!$A$7:$A$200,">="&'Cumulative Table'!$AF$7,'Daily Report'!$A$7:$A$200,"<="&'Cumulative Table'!$AG$7) -> 188 | AI10: =SUMIFS('Daily Report'!$H$7:$H$200,'Daily Report'!$AD$7:$AD$200,'Cumulative Table'!$X10&"TAIKIEM",'Daily Report'!$A$7:$A$200,">="&'Cumulative Table'!$AF$7,'Daily Report'!$A$7:$A$200,"<="&'Cumulative Table'!$AG$7) -> 25
D11: WH | E11: LL | F11: =SUMIF('Dữ Liệu'!#REF!,'Cumulative Table'!$X11,'Dữ Liệu'!$H$7:$H$134) -> #REF! | G11: =SUMIF('Daily Report'!$AD$7:$AD$263,'Cumulative Table'!$X11&"KIEM",'Daily Report'!$H$7:$H$263) -> 128 | H11: =SUMIF('Daily Report'!$AD$7:$AD$263,'Cumulative Table'!$X11&"TAIKIEM",'Daily Report'!$H$7:$H$263) -> 14 | I11: =SUMIF('Daily Report'!$AE$7:$AE$263,'Cumulative Table'!$X11,'Daily Report'!$I$7:$I$263) -> 128 | J11: =SUMIF('Daily Report'!AE11:AE267,'Cumulative Table'!X11:X205,'Daily Report'!R11:R267) -> 0 | N11: =SUM(K11:M11) -> 0 | O11: =SUMIF('Daily Report'!$AE$7:$AE$263,'Cumulative Table'!$X11,'Daily Report'!$K$7:$K$263) -> 0 | P11: =SUMIF('Daily Report'!$AE$7:$AE$263,'Cumulative Table'!$X11,'Daily Report'!$L$7:$L$263) -> 0 | Q11: =SUMIF('Daily Report'!$AE$7:$AE$263,'Cumulative Table'!$X11,'Daily Report'!$M$7:$M$263) -> 3 | R11: =SUMIF('Daily Report'!$AE$7:$AE$263,'Cumulative Table'!$X11,'Daily Report'!$N$7:$N$263) -> 0 | S11: =SUMIF('Daily Report'!$AE$7:$AE$263,'Cumulative Table'!$X11,'Daily Report'!$O$7:$O$263) -> 8 | T11: =SUMIF('Daily Report'!$AE$7:$AE$263,'Cumulative Table'!$X11,'Daily Report'!$P$7:$P$263) -> 3 | U11: =SUMIF('Daily Report'!$AE$7:$AE$263,'Cumulative Table'!$X11,'Daily Report'!$Q$7:$Q$263) -> 0 | W11: =H11/G11 -> 0.109375 | X11: =A$7&D11&E11 -> BR9125WHLL | Z11: =SUMIFS('Daily Report'!$H$7:$H$263, 'Daily Report'!$AD$7:$AD$263, $X11&"KIEM", 'Daily Report'!$A$7:$A$263, $Y$7) -> 104 | AB11: =SUMIFS('Daily Report'!$H$7:$H$200,'Daily Report'!$AD$7:$AD$200,'Cumulative Table'!$X11&"KIEM",'Daily Report'!$A$7:$A$200,'Cumulative Table'!$AA$7) -> 0 | AD11: =SUMIFS('Daily Report'!$H$7:$H$200,'Daily Report'!$AD$7:$AD$200,'Cumulative Table'!$X11&"KIEM",'Daily Report'!$A$7:$A$200,'Cumulative Table'!$AC$7) -> 24 | AE11: =SUMIFS('Daily Report'!$H$7:$H$200,'Daily Report'!$AD$7:$AD$200,'Cumulative Table'!$X11&"KIEM",'Daily Report'!$A$7:$A$200,">="&'Cumulative Table'!$Y$7,'Daily Report'!$A$7:$A$200,"<="&'Cumulative Table'!$AC$7) -> 128 | AH11: =SUMIFS('Daily Report'!$H$7:$H$200,'Daily Report'!$AD$7:$AD$200,'Cumulative Table'!$X11&"KIEM",'Daily Report'!$A$7:$A$200,">="&'Cumulative Table'!$AF$7,'Daily Report'!$A$7:$A$200,"<="&'Cumulative Table'!$AG$7) -> 128 | AI11: =SUMIFS('Daily Report'!$H$7:$H$200,'Daily Report'!$AD$7:$AD$200,'Cumulative Table'!$X11&"TAIKIEM",'Daily Report'!$A$7:$A$200,">="&'Cumulative Table'!$AF$7,'Daily Report'!$A$7:$A$200,"<="&'Cumulative Table'!$AG$7) -> 14
D12: WH | E12: EL | F12: =SUMIF('Dữ Liệu'!#REF!,'Cumulative Table'!$X12,'Dữ Liệu'!$H$7:$H$134) -> #REF! | G12: =SUMIF('Daily Report'!$AD$7:$AD$263,'Cumulative Table'!$X12&"KIEM",'Daily Report'!$H$7:$H$263) -> 23 | H12: =SUMIF('Daily Report'!$AD$7:$AD$263,'Cumulative Table'!$X12&"TAIKIEM",'Daily Report'!$H$7:$H$263) -> 2 | I12: =SUMIF('Daily Report'!$AE$7:$AE$263,'Cumulative Table'!$X12,'Daily Report'!$I$7:$I$263) -> 23 | J12: =SUMIF('Daily Report'!AE12:AE268,'Cumulative Table'!X12:X206,'Daily Report'!R12:R268) -> 0 | N12: =SUM(K12:M12) -> 0 | O12: =SUMIF('Daily Report'!$AE$7:$AE$263,'Cumulative Table'!$X12,'Daily Report'!$K$7:$K$263) -> 0 | P12: =SUMIF('Daily Report'!$AE$7:$AE$263,'Cumulative Table'!$X12,'Daily Report'!$L$7:$L$263) -> 0 | Q12: =SUMIF('Daily Report'!$AE$7:$AE$263,'Cumulative Table'!$X12,'Daily Report'!$M$7:$M$263) -> 0 | R12: =SUMIF('Daily Report'!$AE$7:$AE$263,'Cumulative Table'!$X12,'Daily Report'!$N$7:$N$263) -> 0 | S12: =SUMIF('Daily Report'!$AE$7:$AE$263,'Cumulative Table'!$X12,'Daily Report'!$O$7:$O$263) -> 2 | T12: =SUMIF('Daily Report'!$AE$7:$AE$263,'Cumulative Table'!$X12,'Daily Report'!$P$7:$P$263) -> 0 | U12: =SUMIF('Daily Report'!$AE$7:$AE$263,'Cumulative Table'!$X12,'Daily Report'!$Q$7:$Q$263) -> 0 | W12: =H12/G12 -> 0.086956522 | X12: =A$7&D12&E12 -> BR9125WHEL | Z12: =SUMIFS('Daily Report'!$H$7:$H$263, 'Daily Report'!$AD$7:$AD$263, $X12&"KIEM", 'Daily Report'!$A$7:$A$263, $Y$7) -> 0 | AB12: =SUMIFS('Daily Report'!$H$7:$H$200,'Daily Report'!$AD$7:$AD$200,'Cumulative Table'!$X12&"KIEM",'Daily Report'!$A$7:$A$200,'Cumulative Table'!$AA$7) -> 0 | AD12: =SUMIFS('Daily Report'!$H$7:$H$200,'Daily Report'!$AD$7:$AD$200,'Cumulative Table'!$X12&"KIEM",'Daily Report'!$A$7:$A$200,'Cumulative Table'!$AC$7) -> 23 | AE12: =SUMIFS('Daily Report'!$H$7:$H$200,'Daily Report'!$AD$7:$AD$200,'Cumulative Table'!$X12&"KIEM",'Daily Report'!$A$7:$A$200,">="&'Cumulative Table'!$Y$7,'Daily Report'!$A$7:$A$200,"<="&'Cumulative Table'!$AC$7) -> 23 | AH12: =SUMIFS('Daily Report'!$H$7:$H$200,'Daily Report'!$AD$7:$AD$200,'Cumulative Table'!$X12&"KIEM",'Daily Report'!$A$7:$A$200,">="&'Cumulative Table'!$AF$7,'Daily Report'!$A$7:$A$200,"<="&'Cumulative Table'!$AG$7) -> 23 | AI12: =SUMIFS('Daily Report'!$H$7:$H$200,'Daily Report'!$AD$7:$AD$200,'Cumulative Table'!$X12&"TAIKIEM",'Daily Report'!$A$7:$A$200,">="&'Cumulative Table'!$AF$7,'Daily Report'!$A$7:$A$200,"<="&'Cumulative Table'!$AG$7) -> 2
D13: WH | E13: 4L | F13: =SUMIF('Dữ Liệu'!#REF!,'Cumulative Table'!$X13,'Dữ Liệu'!$H$7:$H$134) -> #REF! | G13: =SUMIF('Daily Report'!$AD$7:$AD$263,'Cumulative Table'!$X13&"KIEM",'Daily Report'!$H$7:$H$263) -> 14 | H13: =SUMIF('Daily Report'!$AD$7:$AD$263,'Cumulative Table'!$X13&"TAIKIEM",'Daily Report'!$H$7:$H$263) -> 1 | I13: =SUMIF('Daily Report'!$AE$7:$AE$263,'Cumulative Table'!$X13,'Daily Report'!$I$7:$I$263) -> 14 | J13: =SUMIF('Daily Report'!AE13:AE269,'Cumulative Table'!X13:X207,'Daily Report'!R13:R269) -> 0 | N13: =SUM(K13:M13) -> 0 | O13: =SUMIF('Daily Report'!$AE$7:$AE$263,'Cumulative Table'!$X13,'Daily Report'!$K$7:$K$263) -> 0 | P13: =SUMIF('Daily Report'!$AE$7:$AE$263,'Cumulative Table'!$X13,'Daily Report'!$L$7:$L$263) -> 0 | Q13: =SUMIF('Daily Report'!$AE$7:$AE$263,'Cumulative Table'!$X13,'Daily Report'!$M$7:$M$263) -> 1 | R13: =SUMIF('Daily Report'!$AE$7:$AE$263,'Cumulative Table'!$X13,'Daily Report'!$N$7:$N$263) -> 0 | S13: =SUMIF('Daily Report'!$AE$7:$AE$263,'Cumulative Table'!$X13,'Daily Report'!$O$7:$O$263) -> 0 | T13: =SUMIF('Daily Report'!$AE$7:$AE$263,'Cumulative Table'!$X13,'Daily Report'!$P$7:$P$263) -> 0 | U13: =SUMIF('Daily Report'!$AE$7:$AE$263,'Cumulative Table'!$X13,'Daily Report'!$Q$7:$Q$263) -> 0 | W13: =H13/G13 -> 0.071428571 | X13: =A$7&D13&E13 -> BR9125WH4L | Z13: =SUMIFS('Daily Report'!$H$7:$H$263, 'Daily Report'!$AD$7:$AD$263, $X13&"KIEM", 'Daily Report'!$A$7:$A$263, $Y$7) -> 0 | AB13: =SUMIFS('Daily Report'!$H$7:$H$200,'Daily Report'!$AD$7:$AD$200,'Cumulative Table'!$X13&"KIEM",'Daily Report'!$A$7:$A$200,'Cumulative Table'!$AA$7) -> 0 | AD13: =SUMIFS('Daily Report'!$H$7:$H$200,'Daily Report'!$AD$7:$AD$200,'Cumulative Table'!$X13&"KIEM",'Daily Report'!$A$7:$A$200,'Cumulative Table'!$AC$7) -> 14 | AE13: =SUMIFS('Daily Report'!$H$7:$H$200,'Daily Report'!$AD$7:$AD$200,'Cumulative Table'!$X13&"KIEM",'Daily Report'!$A$7:$A$200,">="&'Cumulative Table'!$Y$7,'Daily Report'!$A$7:$A$200,"<="&'Cumulative Table'!$AC$7) -> 14 | AH13: =SUMIFS('Daily Report'!$H$7:$H$200,'Daily Report'!$AD$7:$AD$200,'Cumulative Table'!$X13&"KIEM",'Daily Report'!$A$7:$A$200,">="&'Cumulative Table'!$AF$7,'Daily Report'!$A$7:$A$200,"<="&'Cumulative Table'!$AG$7) -> 14 | AI13: =SUMIFS('Daily Report'!$H$7:$H$200,'Daily Report'!$AD$7:$AD$200,'Cumulative Table'!$X13&"TAIKIEM",'Daily Report'!$A$7:$A$200,">="&'Cumulative Table'!$AF$7,'Daily Report'!$A$7:$A$200,"<="&'Cumulative Table'!$AG$7) -> 1
D14: WH | E14: 5L | F14: =SUMIF('Dữ Liệu'!#REF!,'Cumulative Table'!$X14,'Dữ Liệu'!$H$7:$H$134) -> #REF! | G14: =SUMIF('Daily Report'!$AD$7:$AD$263,'Cumulative Table'!$X14&"KIEM",'Daily Report'!$H$7:$H$263) -> 13 | H14: =SUMIF('Daily Report'!$AD$7:$AD$263,'Cumulative Table'!$X14&"TAIKIEM",'Daily Report'!$H$7:$H$263) -> 1 | I14: =SUMIF('Daily Report'!$AE$7:$AE$263,'Cumulative Table'!$X14,'Daily Report'!$I$7:$I$263) -> 13 | J14: =SUMIF('Daily Report'!AE13:AE269,'Cumulative Table'!X14:X207,'Daily Report'!R13:R269) -> 0 | N14: =SUM(K14:M14) -> 0 | O14: =SUMIF('Daily Report'!$AE$7:$AE$263,'Cumulative Table'!$X14,'Daily Report'!$K$7:$K$263) -> 0 | P14: =SUMIF('Daily Report'!$AE$7:$AE$263,'Cumulative Table'!$X14,'Daily Report'!$L$7:$L$263) -> 0 | Q14: =SUMIF('Daily Report'!$AE$7:$AE$263,'Cumulative Table'!$X14,'Daily Report'!$M$7:$M$263) -> 0 | R14: =SUMIF('Daily Report'!$AE$7:$AE$263,'Cumulative Table'!$X14,'Daily Report'!$N$7:$N$263) -> 0 | S14: =SUMIF('Daily Report'!$AE$7:$AE$263,'Cumulative Table'!$X14,'Daily Report'!$O$7:$O$263) -> 1 | T14: =SUMIF('Daily Report'!$AE$7:$AE$263,'Cumulative Table'!$X14,'Daily Report'!$P$7:$P$263) -> 0 | U14: =SUMIF('Daily Report'!$AE$7:$AE$263,'Cumulative Table'!$X14,'Daily Report'!$Q$7:$Q$263) -> 0 | W14: =H14/G14 -> 0.076923077 | X14: =A$7&D14&E14 -> BR9125WH5L | Z14: =SUMIFS('Daily Report'!$H$7:$H$263, 'Daily Report'!$AD$7:$AD$263, $X14&"KIEM", 'Daily Report'!$A$7:$A$263, $Y$7) -> 0 | AB14: =SUMIFS('Daily Report'!$H$7:$H$200,'Daily Report'!$AD$7:$AD$200,'Cumulative Table'!$X14&"KIEM",'Daily Report'!$A$7:$A$200,'Cumulative Table'!$AA$7) -> 0 | AD14: =SUMIFS('Daily Report'!$H$7:$H$200,'Daily Report'!$AD$7:$AD$200,'Cumulative Table'!$X14&"KIEM",'Daily Report'!$A$7:$A$200,'Cumulative Table'!$AC$7) -> 13 | AE14: =SUMIFS('Daily Report'!$H$7:$H$200,'Daily Report'!$AD$7:$AD$200,'Cumulative Table'!$X14&"KIEM",'Daily Report'!$A$7:$A$200,">="&'Cumulative Table'!$Y$7,'Daily Report'!$A$7:$A$200,"<="&'Cumulative Table'!$AC$7) -> 13 | AH14: =SUMIFS('Daily Report'!$H$7:$H$200,'Daily Report'!$AD$7:$AD$200,'Cumulative Table'!$X14&"KIEM",'Daily Report'!$A$7:$A$200,">="&'Cumulative Table'!$AF$7,'Daily Report'!$A$7:$A$200,"<="&'Cumulative Table'!$AG$7) -> 13 | AI14: =SUMIFS('Daily Report'!$H$7:$H$200,'Daily Report'!$AD$7:$AD$200,'Cumulative Table'!$X14&"TAIKIEM",'Daily Report'!$A$7:$A$200,">="&'Cumulative Table'!$AF$7,'Daily Report'!$A$7:$A$200,"<="&'Cumulative Table'!$AG$7) -> 1
D15: WH | E15: 6L | F15: =SUMIF('Dữ Liệu'!#REF!,'Cumulative Table'!$X15,'Dữ Liệu'!$H$7:$H$134) -> #REF! | G15: =SUMIF('Daily Report'!$AD$7:$AD$263,'Cumulative Table'!$X15&"KIEM",'Daily Report'!$H$7:$H$263) -> 0 | H15: =SUMIF('Daily Report'!$AD$7:$AD$263,'Cumulative Table'!$X15&"TAIKIEM",'Daily Report'!$H$7:$H$263) -> 0 | I15: =SUMIF('Daily Report'!$AE$7:$AE$263,'Cumulative Table'!$X15,'Daily Report'!$I$7:$I$263) -> 0 | J15: =SUMIF('Daily Report'!AE14:AE270,'Cumulative Table'!X15:X208,'Daily Report'!R14:R270) -> 0 | N15: =SUM(K15:M15) -> 0 | O15: =SUMIF('Daily Report'!$AE$7:$AE$263,'Cumulative Table'!$X15,'Daily Report'!$K$7:$K$263) -> 0 | P15: =SUMIF('Daily Report'!$AE$7:$AE$263,'Cumulative Table'!$X15,'Daily Report'!$L$7:$L$263) -> 0 | Q15: =SUMIF('Daily Report'!$AE$7:$AE$263,'Cumulative Table'!$X15,'Daily Report'!$M$7:$M$263) -> 0 | R15: =SUMIF('Daily Report'!$AE$7:$AE$263,'Cumulative Table'!$X15,'Daily Report'!$N$7:$N$263) -> 0 | S15: =SUMIF('Daily Report'!$AE$7:$AE$263,'Cumulative Table'!$X15,'Daily Report'!$O$7:$O$263) -> 0 | T15: =SUMIF('Daily Report'!$AE$7:$AE$263,'Cumulative Table'!$X15,'Daily Report'!$P$7:$P$263) -> 0 | U15: =SUMIF('Daily Report'!$AE$7:$AE$263,'Cumulative Table'!$X15,'Daily Report'!$Q$7:$Q$263) -> 0 | W15: =H15/G15 -> #DIV/0! | X15: =A$7&D15&E15 -> BR9125WH6L | Z15: =SUMIFS('Daily Report'!$H$7:$H$263, 'Daily Report'!$AD$7:$AD$263, $X15&"KIEM", 'Daily Report'!$A$7:$A$263, $Y$7) -> 0 | AB15: =SUMIFS('Daily Report'!$H$7:$H$200,'Daily Report'!$AD$7:$AD$200,'Cumulative Table'!$X15&"KIEM",'Daily Report'!$A$7:$A$200,'Cumulative Table'!$AA$7) -> 0 | AD15: =SUMIFS('Daily Report'!$H$7:$H$200,'Daily Report'!$AD$7:$AD$200,'Cumulative Table'!$X15&"KIEM",'Daily Report'!$A$7:$A$200,'Cumulative Table'!$AC$7) -> 0 | AE15: =SUMIFS('Daily Report'!$H$7:$H$200,'Daily Report'!$AD$7:$AD$200,'Cumulative Table'!$X15&"KIEM",'Daily Report'!$A$7:$A$200,">="&'Cumulative Table'!$Y$7,'Daily Report'!$A$7:$A$200,"<="&'Cumulative Table'!$AC$7) -> 0 | AH15: =SUMIFS('Daily Report'!$H$7:$H$200,'Daily Report'!$AD$7:$AD$200,'Cumulative Table'!$X15&"KIEM",'Daily Report'!$A$7:$A$200,">="&'Cumulative Table'!$AF$7,'Daily Report'!$A$7:$A$200,"<="&'Cumulative Table'!$AG$7) -> 0 | AI15: =SUMIFS('Daily Report'!$H$7:$H$200,'Daily Report'!$AD$7:$AD$200,'Cumulative Table'!$X15&"TAIKIEM",'Daily Report'!$A$7:$A$200,">="&'Cumulative Table'!$AF$7,'Daily Report'!$A$7:$A$200,"<="&'Cumulative Table'!$AG$7) -> 0
A16: 合計数 Tổng | F16: =SUM(F7:F15) -> #REF! | G16: =SUM(G7:G15) -> 1102 | H16: =SUM(H7:H15) -> 137 | I16: =SUM(I7:I15) -> 1102 | J16: =SUM(J7:J15) -> 0 | K16: =SUM(K7:K15) -> 0 | L16: =SUM(L7:L15) -> 0 | M16: =SUM(M7:M15) -> 0 | ... P16: =SUM(P7:P15) -> 0 | Q16: =SUMIF('Daily Report'!$AE$7:$AE$263,'Cumulative Table'!$X16,'Daily Report'!$M$7:$M$263) -> 0 | R16: =SUM(R7:R15) -> 5 | S16: =SUM(S7:S15) -> 79 | T16: =SUM(T7:T15) -> 30 | U16: =SUM(U7:U15) -> 0 | V16: =SUM(V7:V15) -> 0 | W16: =H16/G16 -> 0.12431942
A17: 不良項目 | C17: 寸法不良： | D17: 袖丈-1.5CM, 着丈-4CM, 袖丈-2CM | H17: 付属・装飾不良： | I17: テープ無し, 品質ネームサイズ違い, プリント不良, 品質ネーム汚れ, サイズネーム曲がり
C18: 外観・仕上げ不良： | D18: 袖非対称, アタリ, 衿バランス不良, ダブリ, しわ, 捻じれ | H18: 生地不良： | I18: スリップ, 生折れ, キズ
C19: 汚れ不良： | D19: 油汚れ | H19: 縫製不良： | I19: パンク, 縫い止め逆付け, 糸切れ, 縫い摘み, 縫いつまみ, 縫い止め無し
C20: その他：
A21: CHI TIẾT LỖI | C21: THÔNG SỐ： | D21: DAI TAY -1.5CM, DAI AO -4CM, DAI TAY -2CM | H21: PHỤ LIỆU: | I21: THIEU TEP, NHAN GIAT LON SIZE, IN DUN, NHAN GIAT DO MUC, IN NHAN SIZE XEO
C22: HÌNH DÁNG: | D22: TAY SOLE, CAN, CO MEO, DUN, NHAN, RAP BO CO VAN | H22: VẢI: | I22: BE VAI, SOC VAI, XUOC
C23: DƠ: | D23: DAU | H23: CÁCH MAY: | I23: XI, CHOT NGUOC, DUT CHI , XEP LY, NHIU, THIEU CHOT
X24: =A24&D24&E24
A25: 品番 | B25: ブランド | C25: 品目 | D25: カラー | E25: サイズ | F25: ロット数 | G25: 検品数(初回検品のみ) | H25: 再検品数量(2回目以降の検査も含む) | I25: 良品数(初回・それ以降の検査分含む) | J25: 検針良品数(初回・それ以降の検査分含む) | K25: 出荷済み数量 | O25: Thông số | P25: Phụ liệu | Q25: Ngoại quan | R25: Vải | S25: Dơ | T25: Lổi may | U25: Khác | V25: Kiểm Kim | W25: Tỉ lệ lỗi
A26: Style No | B26: Brand | C26: Item | D26: Color | E26: Size | F26: Order Qty | G26: Inspection Qty | H26: Re-inspection Qty | I26: A-Grade Qty | J26: A-Grade Qty | K26: Shipment Qty | O26: Measurment | P26: Material | Q26: Appearance | R26: Fabric | S26: Dirt | T26: Sewing | U26: Other | V26: Needle Inspection | W26: rate | Y26: KIỂM | AF26: TỔNG NGÀY KIỂM
A27: Mã hàng | B27: Thương hiệu | C27: Tên hàng | D27: Màu | E27: Size | F27: Số lượng đơn hàng | G27: SL kiểm hàng | H27: SL tái kiểm | I27: SL Hàng đạt | J27: SL Hàng đạt Kiểm kim | K27: SL xuất 1 | L27: SL xuất 2 | M27: SL xuất 3 | N27: TỔNG XUẤT | O27: 採寸不良 | P27: 付属不良 | Q27: 外観不良 | R27: 生地不良 | S27: 汚れ不良 | T27: 縫製不良 | U27: その他 | V27: 検針 | W27: 不良率 | Y27: NGÀY 2026/03/05 | AA27: NGÀY 2026/03/09 | AC27: NGÀY 2026/03/10 | AE27: 2026/03/05 - 03/10 | AF27: NGÀY BẮT ĐẦU | AG27: NGÀY KẾT THÚC | AH27: TỔNG SỐ HÀNG KIỂM | AI27: TỔNG SỐ HÀNG TÁI
A28: BR9125 | B28: =VLOOKUP($A$7,'Daily Report'!$C$7:$E$263,2,FALSE) -> GUA | C28: =VLOOKUP($A$7,'Daily Report'!$C$7:$E$263,3,FALSE) -> SHIRT | D28: WH | E28: SS | F28: =SUMIF('Dữ Liệu'!#REF!,'Cumulative Table'!$X7,'Dữ Liệu'!H7:H134) -> #REF! | G28: =SUMIF('Daily Report'!$AD$7:$AD$263,'Cumulative Table'!$X$7:$X$201&"KIEM",'Daily Report'!$H$7:$H$199) -> 0 | H28: =SUMIF('Daily Report'!$AD$7:$AD$263,'Cumulative Table'!$X$7:$X$201&"TAIKIEM",'Daily Report'!$H$7:$H$263) -> 0 | I28: =SUMIF('Daily Report'!$AE$7:$AE$263,'Cumulative Table'!$X$7:$X$201,'Daily Report'!$I$7:$I$263) -> 0 | J28: =SUMIF('Daily Report'!AE27:AE283,'Cumulative Table'!X28:X221,'Daily Report'!R27:R283) -> 0 | N28: =SUM(K28:M28) -> 0 | O28: =SUMIF('Daily Report'!$AE$7:$AE$199,'Cumulative Table'!$X$7:$X$201,'Daily Report'!$K$7:$K$199) -> 0 | P28: =SUMIF('Daily Report'!$AE$7:$AE$263,'Cumulative Table'!X$7:$X$201,'Daily Report'!$L$7:$L$263) -> 0 | Q28: =SUMIF('Daily Report'!$AE$7:$AE$263,'Cumulative Table'!$X$7:$X$201,'Daily Report'!$M$7:$M$263) -> 0 | R28: =SUMIF('Daily Report'!$AE$7:$AE$263,'Cumulative Table'!$X$7:$X$201,'Daily Report'!$N$7:$N$263) -> 0 | S28: =SUMIF('Daily Report'!$AE$7:$AE$263,'Cumulative Table'!$X$7:$X$201,'Daily Report'!$O$7:$O$263) -> 0 | T28: =SUMIF('Daily Report'!$AE$7:$AE$263,'Cumulative Table'!$X$8:$X$201,'Daily Report'!$P$7:$P$263) -> 0 | U28: =SUMIF('Daily Report'!$AE$7:$AE$263,'Cumulative Table'!$X$7:$X$201,'Daily Report'!$Q$7:$Q$263) -> 0 | W28: =H28/G28 -> #DIV/0! | X28: =$A$28&D28&E28 -> BR9125WHSS | Y28: 46095 | Z28: =SUMIFS('Daily Report'!$H$7:$H$263, 'Daily Report'!$AD$7:$AD$263, $X28&"KIEM", 'Daily Report'!$A$7:$A$263, $Y$28) -> 0 | AA28: 46096 | AB28: =SUMIFS('Daily Report'!$H$7:$H$200,'Daily Report'!$AD$7:$AD$200,'Cumulative Table'!$X28&"KIEM",'Daily Report'!$A$7:$A$200,'Cumulative Table'!$AA$28) -> 0 | AC28: 46097 | AD28: =SUMIFS('Daily Report'!$H$7:$H$200,'Daily Report'!$AD$7:$AD$200,'Cumulative Table'!$X28&"KIEM",'Daily Report'!$A$7:$A$200,'Cumulative Table'!$AC$28) -> 0 | AE28: =SUMIFS('Daily Report'!$H$7:$H$200,'Daily Report'!$AD$7:$AD$200,'Cumulative Table'!$X28&"KIEM",'Daily Report'!$A$7:$A$200,">="&'Cumulative Table'!$Y$28,'Daily Report'!$A$7:$A$200,"<="&'Cumulative Table'!$AC$28) -> 0 | AF28: 46096 | AG28: 46097 | AH28: =SUMIFS('Daily Report'!$H$7:$H$200,'Daily Report'!$AD$7:$AD$200,'Cumulative Table'!$X28&"KIEM",'Daily Report'!$A$7:$A$200,">="&'Cumulative Table'!$AF$28,'Daily Report'!$A$7:$A$200,"<="&'Cumulative Table'!$AG$28) -> 0 | AI28: =SUMIFS('Daily Report'!$H$7:$H$200,'Daily Report'!$AD$7:$AD$200,'Cumulative Table'!$X28&"TAIKIEM",'Daily Report'!$A$7:$A$200,">="&'Cumulative Table'!$AF$28,'Daily Report'!$A$7:$A$200,"<="&'Cumulative Table'!$AG$28) -> 0
D29: WH | E29: S | F29: =SUMIF('Dữ Liệu'!#REF!,'Cumulative Table'!$X8,'Dữ Liệu'!H8:H135) -> #REF! | G29: =SUMIF('Daily Report'!$AD$7:$AD$263,'Cumulative Table'!$X$7:$X$201&"KIEM",'Daily Report'!$H$7:$H$199) -> 133 | H29: =SUMIF('Daily Report'!$AD$7:$AD$263,'Cumulative Table'!$X$7:$X$201&"TAIKIEM",'Daily Report'!$H$7:$H$263) -> 18 | I29: =SUMIF('Daily Report'!$AE$7:$AE$263,'Cumulative Table'!$X$7:$X$201,'Daily Report'!$I$7:$I$263) -> 133 | J29: =SUMIF('Daily Report'!AE28:AE284,'Cumulative Table'!X29:X222,'Daily Report'!R28:R284) -> 0 | N29: =SUM(K29:M29) -> 0 | O29: =SUMIF('Daily Report'!$AE$7:$AE$199,'Cumulative Table'!$X$7:$X$201,'Daily Report'!$K$7:$K$199) -> 0 | P29: =SUMIF('Daily Report'!$AE$7:$AE$263,'Cumulative Table'!X$7:$X$201,'Daily Report'!$L$7:$L$263) -> 0 | Q29: =SUMIF('Daily Report'!$AE$7:$AE$263,'Cumulative Table'!$X$7:$X$201,'Daily Report'!$M$7:$M$263) -> 2 | R29: =SUMIF('Daily Report'!$AE$7:$AE$263,'Cumulative Table'!$X$7:$X$201,'Daily Report'!$N$7:$N$263) -> 0 | S29: =SUMIF('Daily Report'!$AE$7:$AE$263,'Cumulative Table'!$X$7:$X$201,'Daily Report'!$O$7:$O$263) -> 12 | T29: =SUMIF('Daily Report'!$AE$7:$AE$263,'Cumulative Table'!$X$8:$X$201,'Daily Report'!$P$7:$P$263) -> 4 | U29: =SUMIF('Daily Report'!$AE$7:$AE$263,'Cumulative Table'!$X$7:$X$201,'Daily Report'!$Q$7:$Q$263) -> 0 | W29: =H29/G29 -> 0.13533835 | X29: =$A$28&D29&E29 -> BR9125WHS | Z29: =SUMIFS('Daily Report'!$H$7:$H$263, 'Daily Report'!$AD$7:$AD$263, $X29&"KIEM", 'Daily Report'!$A$7:$A$263, $Y$28) -> 0 | AB29: =SUMIFS('Daily Report'!$H$7:$H$200,'Daily Report'!$AD$7:$AD$200,'Cumulative Table'!$X29&"KIEM",'Daily Report'!$A$7:$A$200,'Cumulative Table'!$AA$28) -> 0 | AD29: =SUMIFS('Daily Report'!$H$7:$H$200,'Daily Report'!$AD$7:$AD$200,'Cumulative Table'!$X29&"KIEM",'Daily Report'!$A$7:$A$200,'Cumulative Table'!$AC$28) -> 133 | AE29: =SUMIFS('Daily Report'!$H$7:$H$200,'Daily Report'!$AD$7:$AD$200,'Cumulative Table'!$X29&"KIEM",'Daily Report'!$A$7:$A$200,">="&'Cumulative Table'!$Y$28,'Daily Report'!$A$7:$A$200,"<="&'Cumulative Table'!$AC$28) -> 133 | AH29: =SUMIFS('Daily Report'!$H$7:$H$200,'Daily Report'!$AD$7:$AD$200,'Cumulative Table'!$X29&"KIEM",'Daily Report'!$A$7:$A$200,">="&'Cumulative Table'!$AF$28,'Daily Report'!$A$7:$A$200,"<="&'Cumulative Table'!$AG$28) -> 133 | AI29: =SUMIFS('Daily Report'!$H$7:$H$200,'Daily Report'!$AD$7:$AD$200,'Cumulative Table'!$X29&"TAIKIEM",'Daily Report'!$A$7:$A$200,">="&'Cumulative Table'!$AF$28,'Daily Report'!$A$7:$A$200,"<="&'Cumulative Table'!$AG$28) -> 18
D30: WH | E30: M | F30: =SUMIF('Dữ Liệu'!#REF!,'Cumulative Table'!$X9,'Dữ Liệu'!H8:H136) -> #REF! | G30: =SUMIF('Daily Report'!$AD$7:$AD$263,'Cumulative Table'!$X$7:$X$201&"KIEM",'Daily Report'!$H$7:$H$199) -> 603 | H30: =SUMIF('Daily Report'!$AD$7:$AD$263,'Cumulative Table'!$X$7:$X$201&"TAIKIEM",'Daily Report'!$H$7:$H$263) -> 76 | I30: =SUMIF('Daily Report'!$AE$7:$AE$263,'Cumulative Table'!$X$7:$X$201,'Daily Report'!$I$7:$I$263) -> 603 | J30: =SUMIF('Daily Report'!AE29:AE285,'Cumulative Table'!X30:X223,'Daily Report'!R29:R285) -> 0 | N30: =SUM(K30:M30) -> 0 | O30: =SUMIF('Daily Report'!$AE$7:$AE$199,'Cumulative Table'!$X$7:$X$201,'Daily Report'!$K$7:$K$199) -> 2 | P30: =SUMIF('Daily Report'!$AE$7:$AE$263,'Cumulative Table'!X$7:$X$201,'Daily Report'!$L$7:$L$263) -> 0 | Q30: =SUMIF('Daily Report'!$AE$7:$AE$263,'Cumulative Table'!$X$7:$X$201,'Daily Report'!$M$7:$M$263) -> 11 | R30: =SUMIF('Daily Report'!$AE$7:$AE$263,'Cumulative Table'!$X$7:$X$201,'Daily Report'!$N$7:$N$263) -> 5 | S30: =SUMIF('Daily Report'!$AE$7:$AE$263,'Cumulative Table'!$X$7:$X$201,'Daily Report'!$O$7:$O$263) -> 42 | T30: =SUMIF('Daily Report'!$AE$7:$AE$263,'Cumulative Table'!$X$8:$X$201,'Daily Report'!$P$7:$P$263) -> 16 | U30: =SUMIF('Daily Report'!$AE$7:$AE$263,'Cumulative Table'!$X$7:$X$201,'Daily Report'!$Q$7:$Q$263) -> 0 | W30: =H30/G30 -> 0.12603648 | X30: =$A$28&D30&E30 -> BR9125WHM | Z30: =SUMIFS('Daily Report'!$H$7:$H$263, 'Daily Report'!$AD$7:$AD$263, $X30&"KIEM", 'Daily Report'!$A$7:$A$263, $Y$28) -> 0 | AB30: =SUMIFS('Daily Report'!$H$7:$H$200,'Daily Report'!$AD$7:$AD$200,'Cumulative Table'!$X30&"KIEM",'Daily Report'!$A$7:$A$200,'Cumulative Table'!$AA$28) -> 0 | AD30: =SUMIFS('Daily Report'!$H$7:$H$200,'Daily Report'!$AD$7:$AD$200,'Cumulative Table'!$X30&"KIEM",'Daily Report'!$A$7:$A$200,'Cumulative Table'!$AC$28) -> 184 | AE30: =SUMIFS('Daily Report'!$H$7:$H$200,'Daily Report'!$AD$7:$AD$200,'Cumulative Table'!$X30&"KIEM",'Daily Report'!$A$7:$A$200,">="&'Cumulative Table'!$Y$28,'Daily Report'!$A$7:$A$200,"<="&'Cumulative Table'!$AC$28) -> 184 | AH30: =SUMIFS('Daily Report'!$H$7:$H$200,'Daily Report'!$AD$7:$AD$200,'Cumulative Table'!$X30&"KIEM",'Daily Report'!$A$7:$A$200,">="&'Cumulative Table'!$AF$28,'Daily Report'!$A$7:$A$200,"<="&'Cumulative Table'!$AG$28) -> 184 | AI30: =SUMIFS('Daily Report'!$H$7:$H$200,'Daily Report'!$AD$7:$AD$200,'Cumulative Table'!$X30&"TAIKIEM",'Daily Report'!$A$7:$A$200,">="&'Cumulative Table'!$AF$28,'Daily Report'!$A$7:$A$200,"<="&'Cumulative Table'!$AG$28) -> 24
D31: WH | E31: L | F31: =SUMIF('Dữ Liệu'!#REF!,'Cumulative Table'!$X10,'Dữ Liệu'!H8:H137) -> #REF! | G31: =SUMIF('Daily Report'!$AD$7:$AD$263,'Cumulative Table'!$X$7:$X$201&"KIEM",'Daily Report'!$H$7:$H$199) -> 188 | H31: =SUMIF('Daily Report'!$AD$7:$AD$263,'Cumulative Table'!$X$7:$X$201&"TAIKIEM",'Daily Report'!$H$7:$H$263) -> 25 | I31: =SUMIF('Daily Report'!$AE$7:$AE$263,'Cumulative Table'!$X$7:$X$201,'Daily Report'!$I$7:$I$263) -> 188 | J31: =SUMIF('Daily Report'!AE30:AE286,'Cumulative Table'!X31:X224,'Daily Report'!R30:R286) -> 0 | N31: =SUM(K31:M31) -> 0 | O31: =SUMIF('Daily Report'!$AE$7:$AE$199,'Cumulative Table'!$X$7:$X$201,'Daily Report'!$K$7:$K$199) -> 1 | P31: =SUMIF('Daily Report'!$AE$7:$AE$263,'Cumulative Table'!X$7:$X$201,'Daily Report'!$L$7:$L$263) -> 0 | Q31: =SUMIF('Daily Report'!$AE$7:$AE$263,'Cumulative Table'!$X$7:$X$201,'Daily Report'!$M$7:$M$263) -> 3 | R31: =SUMIF('Daily Report'!$AE$7:$AE$263,'Cumulative Table'!$X$7:$X$201,'Daily Report'!$N$7:$N$263) -> 0 | S31: =SUMIF('Daily Report'!$AE$7:$AE$263,'Cumulative Table'!$X$7:$X$201,'Daily Report'!$O$7:$O$263) -> 14 | T31: =SUMIF('Daily Report'!$AE$7:$AE$263,'Cumulative Table'!$X$8:$X$201,'Daily Report'!$P$7:$P$263) -> 7 | U31: =SUMIF('Daily Report'!$AE$7:$AE$263,'Cumulative Table'!$X$7:$X$201,'Daily Report'!$Q$7:$Q$263) -> 0 | W31: =H31/G31 -> 0.13297872 | X31: =$A$28&D31&E31 -> BR9125WHL | Z31: =SUMIFS('Daily Report'!$H$7:$H$263, 'Daily Report'!$AD$7:$AD$263, $X31&"KIEM", 'Daily Report'!$A$7:$A$263, $Y$28) -> 188 | AB31: =SUMIFS('Daily Report'!$H$7:$H$200,'Daily Report'!$AD$7:$AD$200,'Cumulative Table'!$X31&"KIEM",'Daily Report'!$A$7:$A$200,'Cumulative Table'!$AA$28) -> 0 | AD31: =SUMIFS('Daily Report'!$H$7:$H$200,'Daily Report'!$AD$7:$AD$200,'Cumulative Table'!$X31&"KIEM",'Daily Report'!$A$7:$A$200,'Cumulative Table'!$AC$28) -> 0 | AE31: =SUMIFS('Daily Report'!$H$7:$H$200,'Daily Report'!$AD$7:$AD$200,'Cumulative Table'!$X31&"KIEM",'Daily Report'!$A$7:$A$200,">="&'Cumulative Table'!$Y$28,'Daily Report'!$A$7:$A$200,"<="&'Cumulative Table'!$AC$28) -> 188 | AH31: =SUMIFS('Daily Report'!$H$7:$H$200,'Daily Report'!$AD$7:$AD$200,'Cumulative Table'!$X31&"KIEM",'Daily Report'!$A$7:$A$200,">="&'Cumulative Table'!$AF$28,'Daily Report'!$A$7:$A$200,"<="&'Cumulative Table'!$AG$28) -> 0 | AI31: =SUMIFS('Daily Report'!$H$7:$H$200,'Daily Report'!$AD$7:$AD$200,'Cumulative Table'!$X31&"TAIKIEM",'Daily Report'!$A$7:$A$200,">="&'Cumulative Table'!$AF$28,'Daily Report'!$A$7:$A$200,"<="&'Cumulative Table'!$AG$28) -> 0
D32: WH | E32: LL | F32: =SUMIF('Dữ Liệu'!#REF!,'Cumulative Table'!$X11,'Dữ Liệu'!H8:H138) -> #REF! | G32: =SUMIF('Daily Report'!$AD$7:$AD$263,'Cumulative Table'!$X$7:$X$201&"KIEM",'Daily Report'!$H$7:$H$199) -> 128 | H32: =SUMIF('Daily Report'!$AD$7:$AD$263,'Cumulative Table'!$X$7:$X$201&"TAIKIEM",'Daily Report'!$H$7:$H$263) -> 14 | I32: =SUMIF('Daily Report'!$AE$7:$AE$263,'Cumulative Table'!$X$7:$X$201,'Daily Report'!$I$7:$I$263) -> 128 | J32: =SUMIF('Daily Report'!AE31:AE287,'Cumulative Table'!X32:X225,'Daily Report'!R31:R287) -> 0 | N32: =SUM(K32:M32) -> 0 | O32: =SUMIF('Daily Report'!$AE$7:$AE$199,'Cumulative Table'!$X$7:$X$201,'Daily Report'!$K$7:$K$199) -> 0 | P32: =SUMIF('Daily Report'!$AE$7:$AE$263,'Cumulative Table'!X$7:$X$201,'Daily Report'!$L$7:$L$263) -> 0 | Q32: =SUMIF('Daily Report'!$AE$7:$AE$263,'Cumulative Table'!$X$7:$X$201,'Daily Report'!$M$7:$M$263) -> 3 | R32: =SUMIF('Daily Report'!$AE$7:$AE$263,'Cumulative Table'!$X$7:$X$201,'Daily Report'!$N$7:$N$263) -> 0 | S32: =SUMIF('Daily Report'!$AE$7:$AE$263,'Cumulative Table'!$X$7:$X$201,'Daily Report'!$O$7:$O$263) -> 8 | T32: =SUMIF('Daily Report'!$AE$7:$AE$263,'Cumulative Table'!$X$8:$X$201,'Daily Report'!$P$7:$P$263) -> 3 | U32: =SUMIF('Daily Report'!$AE$7:$AE$263,'Cumulative Table'!$X$7:$X$201,'Daily Report'!$Q$7:$Q$263) -> 0 | W32: =H32/G32 -> 0.109375 | X32: =$A$28&D32&E32 -> BR9125WHLL | Z32: =SUMIFS('Daily Report'!$H$7:$H$263, 'Daily Report'!$AD$7:$AD$263, $X32&"KIEM", 'Daily Report'!$A$7:$A$263, $Y$28) -> 104 | AB32: =SUMIFS('Daily Report'!$H$7:$H$200,'Daily Report'!$AD$7:$AD$200,'Cumulative Table'!$X32&"KIEM",'Daily Report'!$A$7:$A$200,'Cumulative Table'!$AA$28) -> 0 | AD32: =SUMIFS('Daily Report'!$H$7:$H$200,'Daily Report'!$AD$7:$AD$200,'Cumulative Table'!$X32&"KIEM",'Daily Report'!$A$7:$A$200,'Cumulative Table'!$AC$28) -> 24 | AE32: =SUMIFS('Daily Report'!$H$7:$H$200,'Daily Report'!$AD$7:$AD$200,'Cumulative Table'!$X32&"KIEM",'Daily Report'!$A$7:$A$200,">="&'Cumulative Table'!$Y$28,'Daily Report'!$A$7:$A$200,"<="&'Cumulative Table'!$AC$28) -> 128 | AH32: =SUMIFS('Daily Report'!$H$7:$H$200,'Daily Report'!$AD$7:$AD$200,'Cumulative Table'!$X32&"KIEM",'Daily Report'!$A$7:$A$200,">="&'Cumulative Table'!$AF$28,'Daily Report'!$A$7:$A$200,"<="&'Cumulative Table'!$AG$28) -> 24 | AI32: =SUMIFS('Daily Report'!$H$7:$H$200,'Daily Report'!$AD$7:$AD$200,'Cumulative Table'!$X32&"TAIKIEM",'Daily Report'!$A$7:$A$200,">="&'Cumulative Table'!$AF$28,'Daily Report'!$A$7:$A$200,"<="&'Cumulative Table'!$AG$28) -> 3
D33: WH | E33: EL | F33: =SUMIF('Dữ Liệu'!#REF!,'Cumulative Table'!$X12,'Dữ Liệu'!H8:H139) -> #REF! | G33: =SUMIF('Daily Report'!$AD$7:$AD$263,'Cumulative Table'!$X$7:$X$201&"KIEM",'Daily Report'!$H$7:$H$199) -> 23 | H33: =SUMIF('Daily Report'!$AD$7:$AD$263,'Cumulative Table'!$X$7:$X$201&"TAIKIEM",'Daily Report'!$H$7:$H$263) -> 2 | I33: =SUMIF('Daily Report'!$AE$7:$AE$263,'Cumulative Table'!$X$7:$X$201,'Daily Report'!$I$7:$I$263) -> 23 | J33: =SUMIF('Daily Report'!AE32:AE288,'Cumulative Table'!X33:X226,'Daily Report'!R32:R288) -> 0 | N33: =SUM(K33:M33) -> 0 | O33: =SUMIF('Daily Report'!$AE$7:$AE$199,'Cumulative Table'!$X$7:$X$201,'Daily Report'!$K$7:$K$199) -> 0 | P33: =SUMIF('Daily Report'!$AE$7:$AE$263,'Cumulative Table'!X$7:$X$201,'Daily Report'!$L$7:$L$263) -> 0 | Q33: =SUMIF('Daily Report'!$AE$7:$AE$263,'Cumulative Table'!$X$7:$X$201,'Daily Report'!$M$7:$M$263) -> 0 | R33: =SUMIF('Daily Report'!$AE$7:$AE$263,'Cumulative Table'!$X$7:$X$201,'Daily Report'!$N$7:$N$263) -> 0 | S33: =SUMIF('Daily Report'!$AE$7:$AE$263,'Cumulative Table'!$X$7:$X$201,'Daily Report'!$O$7:$O$263) -> 2 | T33: =SUMIF('Daily Report'!$AE$7:$AE$263,'Cumulative Table'!$X$8:$X$201,'Daily Report'!$P$7:$P$263) -> 0 | U33: =SUMIF('Daily Report'!$AE$7:$AE$263,'Cumulative Table'!$X$7:$X$201,'Daily Report'!$Q$7:$Q$263) -> 0 | W33: =H33/G33 -> 0.086956522 | X33: =$A$28&D33&E33 -> BR9125WHEL | Z33: =SUMIFS('Daily Report'!$H$7:$H$263, 'Daily Report'!$AD$7:$AD$263, $X33&"KIEM", 'Daily Report'!$A$7:$A$263, $Y$28) -> 0 | AB33: =SUMIFS('Daily Report'!$H$7:$H$200,'Daily Report'!$AD$7:$AD$200,'Cumulative Table'!$X33&"KIEM",'Daily Report'!$A$7:$A$200,'Cumulative Table'!$AA$28) -> 0 | AD33: =SUMIFS('Daily Report'!$H$7:$H$200,'Daily Report'!$AD$7:$AD$200,'Cumulative Table'!$X33&"KIEM",'Daily Report'!$A$7:$A$200,'Cumulative Table'!$AC$28) -> 23 | AE33: =SUMIFS('Daily Report'!$H$7:$H$200,'Daily Report'!$AD$7:$AD$200,'Cumulative Table'!$X33&"KIEM",'Daily Report'!$A$7:$A$200,">="&'Cumulative Table'!$Y$28,'Daily Report'!$A$7:$A$200,"<="&'Cumulative Table'!$AC$28) -> 23 | AH33: =SUMIFS('Daily Report'!$H$7:$H$200,'Daily Report'!$AD$7:$AD$200,'Cumulative Table'!$X33&"KIEM",'Daily Report'!$A$7:$A$200,">="&'Cumulative Table'!$AF$28,'Daily Report'!$A$7:$A$200,"<="&'Cumulative Table'!$AG$28) -> 23 | AI33: =SUMIFS('Daily Report'!$H$7:$H$200,'Daily Report'!$AD$7:$AD$200,'Cumulative Table'!$X33&"TAIKIEM",'Daily Report'!$A$7:$A$200,">="&'Cumulative Table'!$AF$28,'Daily Report'!$A$7:$A$200,"<="&'Cumulative Table'!$AG$28) -> 2
D34: WH | E34: 4L | F34: =SUMIF('Dữ Liệu'!#REF!,'Cumulative Table'!$X13,'Dữ Liệu'!H8:H140) -> #REF! | G34: =SUMIF('Daily Report'!$AD$7:$AD$263,'Cumulative Table'!$X$7:$X$201&"KIEM",'Daily Report'!$H$7:$H$199) -> 14 | H34: =SUMIF('Daily Report'!$AD$7:$AD$263,'Cumulative Table'!$X$7:$X$201&"TAIKIEM",'Daily Report'!$H$7:$H$263) -> 1 | I34: =SUMIF('Daily Report'!$AE$7:$AE$263,'Cumulative Table'!$X$7:$X$201,'Daily Report'!$I$7:$I$263) -> 14 | J34: =SUMIF('Daily Report'!AE33:AE289,'Cumulative Table'!X34:X227,'Daily Report'!R33:R289) -> 0 | N34: =SUM(K34:M34) -> 0 | O34: =SUMIF('Daily Report'!$AE$7:$AE$199,'Cumulative Table'!$X$7:$X$201,'Daily Report'!$K$7:$K$199) -> 0 | P34: =SUMIF('Daily Report'!$AE$7:$AE$263,'Cumulative Table'!X$7:$X$201,'Daily Report'!$L$7:$L$263) -> 0 | Q34: =SUMIF('Daily Report'!$AE$7:$AE$263,'Cumulative Table'!$X$7:$X$201,'Daily Report'!$M$7:$M$263) -> 1 | R34: =SUMIF('Daily Report'!$AE$7:$AE$263,'Cumulative Table'!$X$7:$X$201,'Daily Report'!$N$7:$N$263) -> 0 | S34: =SUMIF('Daily Report'!$AE$7:$AE$263,'Cumulative Table'!$X$7:$X$201,'Daily Report'!$O$7:$O$263) -> 0 | T34: =SUMIF('Daily Report'!$AE$7:$AE$263,'Cumulative Table'!$X$8:$X$201,'Daily Report'!$P$7:$P$263) -> 0 | U34: =SUMIF('Daily Report'!$AE$7:$AE$263,'Cumulative Table'!$X$7:$X$201,'Daily Report'!$Q$7:$Q$263) -> 0 | W34: =H34/G34 -> 0.071428571 | X34: =$A$28&D34&E34 -> BR9125WH4L | Z34: =SUMIFS('Daily Report'!$H$7:$H$263, 'Daily Report'!$AD$7:$AD$263, $X34&"KIEM", 'Daily Report'!$A$7:$A$263, $Y$28) -> 0 | AB34: =SUMIFS('Daily Report'!$H$7:$H$200,'Daily Report'!$AD$7:$AD$200,'Cumulative Table'!$X34&"KIEM",'Daily Report'!$A$7:$A$200,'Cumulative Table'!$AA$28) -> 0 | AD34: =SUMIFS('Daily Report'!$H$7:$H$200,'Daily Report'!$AD$7:$AD$200,'Cumulative Table'!$X34&"KIEM",'Daily Report'!$A$7:$A$200,'Cumulative Table'!$AC$28) -> 14 | AE34: =SUMIFS('Daily Report'!$H$7:$H$200,'Daily Report'!$AD$7:$AD$200,'Cumulative Table'!$X34&"KIEM",'Daily Report'!$A$7:$A$200,">="&'Cumulative Table'!$Y$28,'Daily Report'!$A$7:$A$200,"<="&'Cumulative Table'!$AC$28) -> 14 | AH34: =SUMIFS('Daily Report'!$H$7:$H$200,'Daily Report'!$AD$7:$AD$200,'Cumulative Table'!$X34&"KIEM",'Daily Report'!$A$7:$A$200,">="&'Cumulative Table'!$AF$28,'Daily Report'!$A$7:$A$200,"<="&'Cumulative Table'!$AG$28) -> 14 | AI34: =SUMIFS('Daily Report'!$H$7:$H$200,'Daily Report'!$AD$7:$AD$200,'Cumulative Table'!$X34&"TAIKIEM",'Daily Report'!$A$7:$A$200,">="&'Cumulative Table'!$AF$28,'Daily Report'!$A$7:$A$200,"<="&'Cumulative Table'!$AG$28) -> 1
D35: WH | E35: 5L | F35: =SUMIF('Dữ Liệu'!#REF!,'Cumulative Table'!$X14,'Dữ Liệu'!H8:H141) -> #REF! | G35: =SUMIF('Daily Report'!$AD$7:$AD$263,'Cumulative Table'!$X$7:$X$201&"KIEM",'Daily Report'!$H$7:$H$199) -> 13 | H35: =SUMIF('Daily Report'!$AD$7:$AD$263,'Cumulative Table'!$X$7:$X$201&"TAIKIEM",'Daily Report'!$H$7:$H$263) -> 1 | I35: =SUMIF('Daily Report'!$AE$7:$AE$263,'Cumulative Table'!$X$7:$X$201,'Daily Report'!$I$7:$I$263) -> 13 | J35: =SUMIF('Daily Report'!AE34:AE290,'Cumulative Table'!X35:X228,'Daily Report'!R34:R290) -> 0 | N35: =SUM(K35:M35) -> 0 | O35: =SUMIF('Daily Report'!$AE$7:$AE$199,'Cumulative Table'!$X$7:$X$201,'Daily Report'!$K$7:$K$199) -> 0 | P35: =SUMIF('Daily Report'!$AE$7:$AE$263,'Cumulative Table'!X$7:$X$201,'Daily Report'!$L$7:$L$263) -> 0 | Q35: =SUMIF('Daily Report'!$AE$7:$AE$263,'Cumulative Table'!$X$7:$X$201,'Daily Report'!$M$7:$M$263) -> 0 | R35: =SUMIF('Daily Report'!$AE$7:$AE$263,'Cumulative Table'!$X$7:$X$201,'Daily Report'!$N$7:$N$263) -> 0 | S35: =SUMIF('Daily Report'!$AE$7:$AE$263,'Cumulative Table'!$X$7:$X$201,'Daily Report'!$O$7:$O$263) -> 1 | T35: =SUMIF('Daily Report'!$AE$7:$AE$263,'Cumulative Table'!$X$8:$X$201,'Daily Report'!$P$7:$P$263) -> 0 | U35: =SUMIF('Daily Report'!$AE$7:$AE$263,'Cumulative Table'!$X$7:$X$201,'Daily Report'!$Q$7:$Q$263) -> 0 | W35: =H35/G35 -> 0.076923077 | X35: =$A$28&D35&E35 -> BR9125WH5L | Z35: =SUMIFS('Daily Report'!$H$7:$H$263, 'Daily Report'!$AD$7:$AD$263, $X35&"KIEM", 'Daily Report'!$A$7:$A$263, $Y$28) -> 0 | AB35: =SUMIFS('Daily Report'!$H$7:$H$200,'Daily Report'!$AD$7:$AD$200,'Cumulative Table'!$X35&"KIEM",'Daily Report'!$A$7:$A$200,'Cumulative Table'!$AA$28) -> 0 | AD35: =SUMIFS('Daily Report'!$H$7:$H$200,'Daily Report'!$AD$7:$AD$200,'Cumulative Table'!$X35&"KIEM",'Daily Report'!$A$7:$A$200,'Cumulative Table'!$AC$28) -> 13 | AE35: =SUMIFS('Daily Report'!$H$7:$H$200,'Daily Report'!$AD$7:$AD$200,'Cumulative Table'!$X35&"KIEM",'Daily Report'!$A$7:$A$200,">="&'Cumulative Table'!$Y$28,'Daily Report'!$A$7:$A$200,"<="&'Cumulative Table'!$AC$28) -> 13 | AH35: =SUMIFS('Daily Report'!$H$7:$H$200,'Daily Report'!$AD$7:$AD$200,'Cumulative Table'!$X35&"KIEM",'Daily Report'!$A$7:$A$200,">="&'Cumulative Table'!$AF$28,'Daily Report'!$A$7:$A$200,"<="&'Cumulative Table'!$AG$28) -> 13 | AI35: =SUMIFS('Daily Report'!$H$7:$H$200,'Daily Report'!$AD$7:$AD$200,'Cumulative Table'!$X35&"TAIKIEM",'Daily Report'!$A$7:$A$200,">="&'Cumulative Table'!$AF$28,'Daily Report'!$A$7:$A$200,"<="&'Cumulative Table'!$AG$28) -> 1
A36: 合計数 Tổng | F36: =SUM(F28:F35) -> #REF! | G36: =SUM(G28:G35) -> 1102 | H36: =SUM(H28:H35) -> 137 | I36: =SUM(I28:I35) -> 1102 | J36: =SUM(J28:J35) -> 0 | K36: =SUM(K28:K35) -> 0 | L36: =SUM(L28:L35) -> 0 | M36: =SUM(M28:M35) -> 0 | ... V36: =SUM(V28:V35) -> 0 | W36: =H36/G36 -> 0.12431942 | Z36: =SUMIFS('Daily Report'!$H$7:$H$263, 'Daily Report'!$AD$7:$AD$263, $X36&"KIEM", 'Daily Report'!$A$7:$A$263, $Y$28) -> 0 | AB36: =SUMIFS('Daily Report'!$H$7:$H$200,'Daily Report'!$AD$7:$AD$200,'Cumulative Table'!$X36&"KIEM",'Daily Report'!$A$7:$A$200,'Cumulative Table'!$AA$28) -> 0 | AD36: =SUMIFS('Daily Report'!$H$7:$H$200,'Daily Report'!$AD$7:$AD$200,'Cumulative Table'!$X36&"KIEM",'Daily Report'!$A$7:$A$200,'Cumulative Table'!$AC$28) -> 0 | AE36: =SUMIFS('Daily Report'!$H$7:$H$200,'Daily Report'!$AD$7:$AD$200,'Cumulative Table'!$X36&"KIEM",'Daily Report'!$A$7:$A$200,">="&'Cumulative Table'!$Y$28,'Daily Report'!$A$7:$A$200,"<="&'Cumulative Table'!$AC$28) -> 0 | AH36: =SUMIFS('Daily Report'!$H$7:$H$200,'Daily Report'!$AD$7:$AD$200,'Cumulative Table'!$X36&"KIEM",'Daily Report'!$A$7:$A$200,">="&'Cumulative Table'!$AF$28,'Daily Report'!$A$7:$A$200,"<="&'Cumulative Table'!$AG$28) -> 0 | AI36: =SUMIFS('Daily Report'!$H$7:$H$200,'Daily Report'!$AD$7:$AD$200,'Cumulative Table'!$X36&"TAIKIEM",'Daily Report'!$A$7:$A$200,">="&'Cumulative Table'!$AF$28,'Daily Report'!$A$7:$A$200,"<="&'Cumulative Table'!$AG$28) -> 0
A37: 不良項目 | C37: 寸法不良： | D37: 袖丈-1.5CM, 着丈-4CM, 袖丈-2CM | H37: 付属・装飾不良： | I37: テープ無し, 品質ネームサイズ違い, プリント不良, 品質ネーム汚れ, サイズネーム曲がり
C38: 外観・仕上げ不良： | D38: 袖非対称, アタリ, 衿バランス不良, ダブリ, しわ, 捻じれ | H38: 生地不良： | I38: スリップ, 生折れ, キズ
C39: 汚れ不良： | D39: 油汚れ | H39: 縫製不良： | I39: パンク, 縫い止め逆付け, 糸切れ, 縫い摘み, 縫いつまみ, 縫い止め無し
C40: その他：
A41: CHI TIẾT LỖI | C41: THÔNG SỐ： | D41: DAI TAY -1.5CM, DAI AO -4CM, DAI TAY -2CM | H41: PHỤ LIỆU: | I41: THIEU TEP, NHAN GIAT LON SIZE, IN DUN, NHAN GIAT DO MUC, IN NHAN SIZE XEO
C42: HÌNH DÁNG: | D42: TAY SOLE, CAN, CO MEO, DUN, NHAN, RAP BO CO VAN | H42: VẢI: | I42: BE VAI, SOC VAI, XUOC
C43: DƠ: | D43: DAU | H43: CÁCH MAY: | I43: XI, CHOT NGUOC, DUT CHI , XEP LY, NHIU, THIEU CHOT
X44: =A44&D44&E44
A45: 品番 | B45: ブランド | C45: 品目 | D45: カラー | E45: サイズ | F45: ロット数 | G45: 検品数(初回検品のみ) | H45: 再検品数量(2回目以降の検査も含む) | I45: 良品数(初回・それ以降の検査分含む) | J45: 検針良品数(初回・それ以降の検査分含む) | K45: 出荷済み数量 | O45: Thông số | P45: Phụ liệu | Q45: Ngoại quan | R45: Vải | S45: Dơ | T45: Lổi may | U45: Khác | V45: Kiểm Kim | W45: Tỉ lệ lỗi
A46: Style No | B46: Brand | C46: Item | D46: Color | E46: Size | F46: Order Qty | G46: Inspection Qty | H46: Re-inspection Qty | I46: A-Grade Qty | J46: A-Grade Qty | K46: Shipment Qty | O46: Measurment | P46: Material | Q46: Appearance | R46: Fabric | S46: Dirt | T46: Sewing | U46: Other | V46: Needle Inspection | W46: rate
A47: Mã hàng | B47: Thương hiệu | C47: Tên hàng | D47: Màu | E47: Size | F47: Số lượng đơn hàng | G47: SL kiểm hàng | H47: SL tái kiểm | I47: SL Hàng đạt | J47: SL Hàng đạt Kiểm kim | K47: SL xuất 1 | L47: SL xuất 2 | M47: SL xuất 3 | N47: TỔNG XUẤT | O47: 採寸不良 | P47: 付属不良 | Q47: 外観不良 | R47: 生地不良 | S47: 汚れ不良 | T47: 縫製不良 | U47: その他 | V47: 検針 | W47: 不良率
A48: BR9071 | B48: =VLOOKUP($A$7,'Daily Report'!$C$7:$E$263,2,FALSE) -> GUA | C48: =VLOOKUP($A$7,'Daily Report'!$C$7:$E$263,3,FALSE) -> SHIRT | D48: WH | E48: SS | G48: =SUMIF('Daily Report'!$AD$7:$AD$263,'Cumulative Table'!$X$7:$X$201&"KIEM",'Daily Report'!$H$7:$H$199) -> 0 | H48: =SUMIF('Daily Report'!$AD$7:$AD$263,'Cumulative Table'!$X$7:$X$201&"TAIKIEM",'Daily Report'!$H$7:$H$263) -> 0 | I48: =SUMIF('Daily Report'!$AE$7:$AE$263,'Cumulative Table'!$X$7:$X$201,'Daily Report'!$I$7:$I$263) -> 0 | J48: =SUMIF('Daily Report'!AE47:AE303,'Cumulative Table'!X48:X241,'Daily Report'!R47:R303) -> 0 | N48: =SUM(K48:M48) -> 0 | O48: =SUMIF('Daily Report'!$AE$7:$AE$263, 'Cumulative Table'!$X$7:$X$265,'Daily Report'!$K$7:$K$263) -> 0 | P48: =SUMIF('Daily Report'!$AE$7:$AE$263, 'Cumulative Table'!$X$7:$X$201,'Daily Report'!$L$7:$L$263) -> 0 | Q48: =SUMIF('Daily Report'!$AE$7:$AE$263,'Cumulative Table'!$X$7:$X$201, 'Daily Report'!$M$7:$M$263) -> 0 | R48: =SUMIF('Daily Report'!$AE$7:$AE$263, 'Cumulative Table'!$X$7:$X$265, 'Daily Report'!$N$7:$N$263) -> 0 | S48: =SUMIF('Daily Report'!$AE$7:$AE$263, 'Cumulative Table'!$X$7:$X$265, 'Daily Report'!$O$7:$O$263) -> 0 | T48: =SUMIF('Daily Report'!$AE$7:$AE$263, 'Cumulative Table'!$X$7:$X$201, 'Daily Report'!$P$7:$P$263) -> 0 | U48: =SUMIF('Daily Report'!$AE$7:$AE$263,'Cumulative Table'!$X$7:$X$201,'Daily Report'!$Q$7:$Q$263) -> 0 | W48: =H48/G48 -> #DIV/0! | X48: =$A$48&D48&E48 -> BR9071WHSS
D49: WH | E49: S | G49: =SUMIF('Daily Report'!$AD$7:$AD$263,'Cumulative Table'!$X$7:$X$201&"KIEM",'Daily Report'!$H$7:$H$199) -> 101 | H49: =SUMIF('Daily Report'!$AD$7:$AD$263,'Cumulative Table'!$X$7:$X$201&"TAIKIEM",'Daily Report'!$H$7:$H$263) -> 11 | I49: =SUMIF('Daily Report'!$AE$7:$AE$263,'Cumulative Table'!$X$7:$X$201,'Daily Report'!$I$7:$I$263) -> 101 | J49: =SUMIF('Daily Report'!AE48:AE304,'Cumulative Table'!X49:X242,'Daily Report'!R48:R304) -> 0 | N49: =SUM(K49:M49) -> 0 | O49: =SUMIF('Daily Report'!$AE$7:$AE$263, 'Cumulative Table'!$X$7:$X$265,'Daily Report'!$K$7:$K$263) -> 0 | P49: =SUMIF('Daily Report'!$AE$7:$AE$263,'Cumulative Table'!$X$7:$X$201,'Daily Report'!$L$7:$L$263) -> 0 | Q49: =SUMIF('Daily Report'!$AE$7:$AE$263,'Cumulative Table'!$X$7:$X$201, 'Daily Report'!$M$7:$M$263) -> 0 | R49: =SUMIF('Daily Report'!$AE$7:$AE$263, 'Cumulative Table'!$X$7:$X$265, 'Daily Report'!$N$7:$N$263) -> 0 | S49: =SUMIF('Daily Report'!$AE$7:$AE$263, 'Cumulative Table'!$X$7:$X$265, 'Daily Report'!$O$7:$O$263) -> 9 | T49: =SUMIF('Daily Report'!$AE$7:$AE$263, 'Cumulative Table'!$X$7:$X$201, 'Daily Report'!$P$7:$P$263) -> 2 | U49: =SUMIF('Daily Report'!$AE$7:$AE$263,'Cumulative Table'!$X$7:$X$201,'Daily Report'!$Q$7:$Q$263) -> 0 | W49: =H49/G49 -> 0.10891089 | X49: =$A$48&D49&E49 -> BR9071WHS
D50: WH | E50: M | G50: =SUMIF('Daily Report'!$AD$7:$AD$263,'Cumulative Table'!$X$7:$X$201&"KIEM",'Daily Report'!$H$7:$H$199) -> 202 | H50: =SUMIF('Daily Report'!$AD$7:$AD$263,'Cumulative Table'!$X$7:$X$201&"TAIKIEM",'Daily Report'!$H$7:$H$263) -> 17 | I50: =SUMIF('Daily Report'!$AE$7:$AE$263,'Cumulative Table'!$X$7:$X$201,'Daily Report'!$I$7:$I$263) -> 202 | J50: =SUMIF('Daily Report'!AE49:AE305,'Cumulative Table'!X50:X243,'Daily Report'!R49:R305) -> 0 | N50: =SUM(K50:M50) -> 0 | O50: =SUMIF('Daily Report'!$AE$7:$AE$263, 'Cumulative Table'!$X$7:$X$265,'Daily Report'!$K$7:$K$263) -> 0 | P50: =SUMIF('Daily Report'!$AE$7:$AE$263,'Cumulative Table'!$X$7:$X$201,'Daily Report'!$L$7:$L$263) -> 0 | Q50: =SUMIF('Daily Report'!$AE$7:$AE$263,'Cumulative Table'!$X$7:$X$201, 'Daily Report'!$M$7:$M$263) -> 0 | R50: =SUMIF('Daily Report'!$AE$7:$AE$263, 'Cumulative Table'!$X$7:$X$265, 'Daily Report'!$N$7:$N$263) -> 0 | S50: =SUMIF('Daily Report'!$AE$7:$AE$263, 'Cumulative Table'!$X$7:$X$265, 'Daily Report'!$O$7:$O$263) -> 14 | T50: =SUMIF('Daily Report'!$AE$7:$AE$263, 'Cumulative Table'!$X$7:$X$201, 'Daily Report'!$P$7:$P$263) -> 3 | U50: =SUMIF('Daily Report'!$AE$7:$AE$263,'Cumulative Table'!$X$7:$X$201,'Daily Report'!$Q$7:$Q$263) -> 0 | W50: =H50/G50 -> 0.084158416 | X50: =$A$48&D50&E50 -> BR9071WHM
D51: WH | E51: L | G51: =SUMIF('Daily Report'!$AD$7:$AD$263,'Cumulative Table'!$X$7:$X$201&"KIEM",'Daily Report'!$H$7:$H$199) -> 101 | H51: =SUMIF('Daily Report'!$AD$7:$AD$263,'Cumulative Table'!$X$7:$X$201&"TAIKIEM",'Daily Report'!$H$7:$H$263) -> 12 | I51: =SUMIF('Daily Report'!$AE$7:$AE$263,'Cumulative Table'!$X$7:$X$201,'Daily Report'!$I$7:$I$263) -> 101 | J51: =SUMIF('Daily Report'!AE50:AE306,'Cumulative Table'!X51:X244,'Daily Report'!R50:R306) -> 0 | N51: =SUM(K51:M51) -> 0 | O51: =SUMIF('Daily Report'!$AE$7:$AE$263, 'Cumulative Table'!$X$7:$X$265,'Daily Report'!$K$7:$K$263) -> 0 | P51: =SUMIF('Daily Report'!$AE$7:$AE$263,'Cumulative Table'!$X$7:$X$201,'Daily Report'!$L$7:$L$263) -> 0 | Q51: =SUMIF('Daily Report'!$AE$7:$AE$263,'Cumulative Table'!$X$7:$X$201, 'Daily Report'!$M$7:$M$263) -> 0 | R51: =SUMIF('Daily Report'!$AE$7:$AE$263, 'Cumulative Table'!$X$7:$X$265, 'Daily Report'!$N$7:$N$263) -> 0 | S51: =SUMIF('Daily Report'!$AE$7:$AE$263, 'Cumulative Table'!$X$7:$X$265, 'Daily Report'!$O$7:$O$263) -> 9 | T51: =SUMIF('Daily Report'!$AE$7:$AE$263, 'Cumulative Table'!$X$7:$X$201, 'Daily Report'!$P$7:$P$263) -> 3 | U51: =SUMIF('Daily Report'!$AE$7:$AE$263,'Cumulative Table'!$X$7:$X$201,'Daily Report'!$Q$7:$Q$263) -> 0 | W51: =H51/G51 -> 0.11881188 | X51: =$A$48&D51&E51 -> BR9071WHL
D52: WH | E52: LL | G52: =SUMIF('Daily Report'!$AD$7:$AD$263,'Cumulative Table'!$X$7:$X$201&"KIEM",'Daily Report'!$H$7:$H$199) -> 51 | H52: =SUMIF('Daily Report'!$AD$7:$AD$263,'Cumulative Table'!$X$7:$X$201&"TAIKIEM",'Daily Report'!$H$7:$H$263) -> 3 | I52: =SUMIF('Daily Report'!$AE$7:$AE$263,'Cumulative Table'!$X$7:$X$201,'Daily Report'!$I$7:$I$263) -> 51 | J52: =SUMIF('Daily Report'!AE51:AE307,'Cumulative Table'!X52:X245,'Daily Report'!R51:R307) -> 0 | N52: =SUM(K52:M52) -> 0 | O52: =SUMIF('Daily Report'!$AE$7:$AE$263, 'Cumulative Table'!$X$7:$X$265,'Daily Report'!$K$7:$K$263) -> 0 | P52: =SUMIF('Daily Report'!$AE$7:$AE$263,'Cumulative Table'!$X$7:$X$201,'Daily Report'!$L$7:$L$263) -> 0 | Q52: =SUMIF('Daily Report'!$AE$7:$AE$263,'Cumulative Table'!$X$7:$X$201, 'Daily Report'!$M$7:$M$263) -> 0 | R52: =SUMIF('Daily Report'!$AE$7:$AE$263, 'Cumulative Table'!$X$7:$X$265, 'Daily Report'!$N$7:$N$263) -> 0 | S52: =SUMIF('Daily Report'!$AE$7:$AE$263, 'Cumulative Table'!$X$7:$X$265, 'Daily Report'!$O$7:$O$263) -> 2 | T52: =SUMIF('Daily Report'!$AE$7:$AE$263, 'Cumulative Table'!$X$7:$X$201, 'Daily Report'!$P$7:$P$263) -> 1 | U52: =SUMIF('Daily Report'!$AE$7:$AE$263,'Cumulative Table'!$X$7:$X$201,'Daily Report'!$Q$7:$Q$263) -> 0 | W52: =H52/G52 -> 0.058823529 | X52: =$A$48&D52&E52 -> BR9071WHLL
D53: WH | E53: BL | G53: =SUMIF('Daily Report'!$AD$7:$AD$263,'Cumulative Table'!$X$7:$X$201&"KIEM",'Daily Report'!$H$7:$H$199) -> 0 | H53: =SUMIF('Daily Report'!$AD$7:$AD$263,'Cumulative Table'!$X$7:$X$201&"TAIKIEM",'Daily Report'!$H$7:$H$263) -> 0 | I53: =SUMIF('Daily Report'!$AE$7:$AE$263,'Cumulative Table'!$X$7:$X$201,'Daily Report'!$I$7:$I$263) -> 0 | J53: =SUMIF('Daily Report'!AE52:AE308,'Cumulative Table'!X53:X246,'Daily Report'!R52:R308) -> 0 | N53: =SUM(K53:M53) -> 0 | O53: =SUMIF('Daily Report'!$AE$7:$AE$263, 'Cumulative Table'!$X$7:$X$265,'Daily Report'!$K$7:$K$263) -> 0 | P53: =SUMIF('Daily Report'!$AE$7:$AE$263,'Cumulative Table'!$X$7:$X$201,'Daily Report'!$L$7:$L$263) -> 0 | Q53: =SUMIF('Daily Report'!$AE$7:$AE$263,'Cumulative Table'!$X$7:$X$201, 'Daily Report'!$M$7:$M$263) -> 0 | R53: =SUMIF('Daily Report'!$AE$7:$AE$263, 'Cumulative Table'!$X$7:$X$265, 'Daily Report'!$N$7:$N$263) -> 0 | S53: =SUMIF('Daily Report'!$AE$7:$AE$263, 'Cumulative Table'!$X$7:$X$265, 'Daily Report'!$O$7:$O$263) -> 0 | T53: =SUMIF('Daily Report'!$AE$7:$AE$263, 'Cumulative Table'!$X$7:$X$201, 'Daily Report'!$P$7:$P$263) -> 0 | U53: =SUMIF('Daily Report'!$AE$7:$AE$263,'Cumulative Table'!$X$7:$X$201,'Daily Report'!$Q$7:$Q$263) -> 0 | W53: =H53/G53 -> #DIV/0! | X53: =$A$48&D53&E53 -> BR9071WHBL
D54: WH | E54: 4L | G54: =SUMIF('Daily Report'!$AD$7:$AD$263,'Cumulative Table'!$X$7:$X$201&"KIEM",'Daily Report'!$H$7:$H$199) -> 20 | H54: =SUMIF('Daily Report'!$AD$7:$AD$263,'Cumulative Table'!$X$7:$X$201&"TAIKIEM",'Daily Report'!$H$7:$H$263) -> 1 | I54: =SUMIF('Daily Report'!$AE$7:$AE$263,'Cumulative Table'!$X$7:$X$201,'Daily Report'!$I$7:$I$263) -> 20 | J54: =SUMIF('Daily Report'!AE53:AE309,'Cumulative Table'!X54:X247,'Daily Report'!R53:R309) -> 0 | N54: =SUM(K54:M54) -> 0 | O54: =SUMIF('Daily Report'!$AE$7:$AE$263, 'Cumulative Table'!$X$7:$X$265,'Daily Report'!$K$7:$K$263) -> 0 | P54: =SUMIF('Daily Report'!$AE$7:$AE$263,'Cumulative Table'!$X$7:$X$201,'Daily Report'!$L$7:$L$263) -> 0 | Q54: =SUMIF('Daily Report'!$AE$7:$AE$263,'Cumulative Table'!$X$7:$X$201, 'Daily Report'!$M$7:$M$263) -> 0 | R54: =SUMIF('Daily Report'!$AE$7:$AE$263, 'Cumulative Table'!$X$7:$X$265, 'Daily Report'!$N$7:$N$263) -> 0 | S54: =SUMIF('Daily Report'!$AE$7:$AE$263, 'Cumulative Table'!$X$7:$X$265, 'Daily Report'!$O$7:$O$263) -> 1 | T54: =SUMIF('Daily Report'!$AE$7:$AE$263, 'Cumulative Table'!$X$7:$X$201, 'Daily Report'!$P$7:$P$263) -> 0 | U54: =SUMIF('Daily Report'!$AE$7:$AE$263,'Cumulative Table'!$X$7:$X$201,'Daily Report'!$Q$7:$Q$263) -> 0 | W54: =H54/G54 -> 0.05 | X54: =$A$48&D54&E54 -> BR9071WH4L
D55: WH | E55: 5L | G55: =SUMIF('Daily Report'!$AD$7:$AD$263,'Cumulative Table'!$X$7:$X$201&"KIEM",'Daily Report'!$H$7:$H$199) -> 0 | H55: =SUMIF('Daily Report'!$AD$7:$AD$263,'Cumulative Table'!$X$7:$X$201&"TAIKIEM",'Daily Report'!$H$7:$H$263) -> 0 | I55: =SUMIF('Daily Report'!$AE$7:$AE$263,'Cumulative Table'!$X$7:$X$201,'Daily Report'!$I$7:$I$263) -> 0 | J55: =SUMIF('Daily Report'!AE54:AE310,'Cumulative Table'!X55:X248,'Daily Report'!R54:R310) -> 0 | N55: =SUM(K55:M55) -> 0 | O55: =SUMIF('Daily Report'!$AE$7:$AE$263, 'Cumulative Table'!$X$7:$X$265,'Daily Report'!$K$7:$K$263) -> 0 | P55: =SUMIF('Daily Report'!$AE$7:$AE$263,'Cumulative Table'!$X$7:$X$201,'Daily Report'!$L$7:$L$263) -> 0 | Q55: =SUMIF('Daily Report'!$AE$7:$AE$263,'Cumulative Table'!$X$7:$X$201, 'Daily Report'!$M$7:$M$263) -> 0 | R55: =SUMIF('Daily Report'!$AE$7:$AE$263, 'Cumulative Table'!$X$7:$X$265, 'Daily Report'!$N$7:$N$263) -> 0 | S55: =SUMIF('Daily Report'!$AE$7:$AE$263, 'Cumulative Table'!$X$7:$X$265, 'Daily Report'!$O$7:$O$263) -> 0 | T55: =SUMIF('Daily Report'!$AE$7:$AE$263, 'Cumulative Table'!$X$7:$X$201, 'Daily Report'!$P$7:$P$263) -> 0 | U55: =SUMIF('Daily Report'!$AE$7:$AE$263,'Cumulative Table'!$X$7:$X$201,'Daily Report'!$Q$7:$Q$263) -> 0 | W55: =H55/G55 -> #DIV/0! | X55: =$A$48&D55&E55 -> BR9071WH5L
A56: 合計数 Tổng | F56: =SUM(F48:F55) -> 0 | G56: =SUM(G48:G55) -> 475 | H56: =SUM(H48:H55) -> 44 | I56: =SUM(I48:I55) -> 475 | J56: =SUM(J48:J55) -> 0 | K56: =SUM(K48:K55) -> 0 | L56: =SUM(L48:L55) -> 0 | M56: =SUM(M48:M55) -> 0 | ... W56: =SUM(W48:W55) -> #DIV/0!
A57: 不良項目 | C57: 寸法不良： | D57: 袖丈-1.5CM, 着丈-4CM, 袖丈-2CM | H57: 付属・装飾不良： | I57: テープ無し, 品質ネームサイズ違い, プリント不良, 品質ネーム汚れ, サイズネーム曲がり
C58: 外観・仕上げ不良： | D58: 袖非対称, アタリ, 衿バランス不良, ダブリ, しわ, 捻じれ | H58: 生地不良： | I58: スリップ, 生折れ, キズ
C59: 汚れ不良： | D59: 油汚れ | H59: 縫製不良： | I59: パンク, 縫い止め逆付け, 糸切れ, 縫い摘み, 縫いつまみ, 縫い止め無し
C60: その他：
A61: CHI TIẾT LỖI | C61: THÔNG SỐ： | D61: DAI TAY -1.5CM, DAI AO -4CM, DAI TAY -2CM | H61: PHỤ LIỆU: | I61: THIEU TEP, NHAN GIAT LON SIZE, IN DUN, NHAN GIAT DO MUC, IN NHAN SIZE XEO
C62: HÌNH DÁNG: | D62: TAY SOLE, CAN, CO MEO, DUN, NHAN, RAP BO CO VAN | H62: VẢI: | I62: BE VAI, SOC VAI, XUOC
C63: DƠ: | D63: DAU | H63: CÁCH MAY: | I63: XI, CHOT NGUOC, DUT CHI , XEP LY, NHIU, THIEU CHOT
X64: =A64&D64&E64
A65: 品番 | B65: ブランド | C65: 品目 | D65: カラー | E65: サイズ | F65: ロット数 | G65: 検品数(初回検品のみ) | H65: 再検品数量(2回目以降の検査も含む) | I65: 良品数(初回・それ以降の検査分含む) | J65: 検針良品数(初回・それ以降の検査分含む) | K65: 出荷済み数量 | O65: Thông số | P65: Phụ liệu | Q65: Ngoại quan | R65: Vải | S65: Dơ | T65: Lổi may | U65: Khác | V65: Kiểm Kim | W65: Tỉ lệ lỗi
A66: Style No | B66: Brand | C66: Item | D66: Color | E66: Size | F66: Order Qty | G66: Inspection Qty | H66: Re-inspection Qty | I66: A-Grade Qty | J66: A-Grade Qty | K66: Shipment Qty | O66: Measurment | P66: Material | Q66: Appearance | R66: Fabric | S66: Dirt | T66: Sewing | U66: Other | V66: Needle Inspection | W66: rate
A67: Mã hàng | B67: Thương hiệu | C67: Tên hàng | D67: Màu | E67: Size | F67: Số lượng đơn hàng | G67: SL kiểm hàng | H67: SL tái kiểm | I67: SL Hàng đạt | J67: SL Hàng đạt Kiểm kim | K67: SL xuất 1 | L67: SL xuất 2 | M67: SL xuất 3 | N67: TỔNG XUẤT | O67: 採寸不良 | P67: 付属不良 | Q67: 外観不良 | R67: 生地不良 | S67: 汚れ不良 | T67: 縫製不良 | U67: その他 | V67: 検針 | W67: 不良率
A68: BR9070 | B68: =VLOOKUP($A$7,'Daily Report'!$C$7:$E$263,2,FALSE) -> GUA | C68: =VLOOKUP($A$7,'Daily Report'!$C$7:$E$263,3,FALSE) -> SHIRT | D68: WH | E68: SS | G68: =SUMIF('Daily Report'!$AD$7:$AD$263,'Cumulative Table'!$X$7:$X$201&"KIEM",'Daily Report'!$H$7:$H$199) -> 0 | H68: =SUMIF('Daily Report'!$AD$7:$AD$263,'Cumulative Table'!$X$7:$X$201&"TAIKIEM",'Daily Report'!$H$7:$H$263) -> 0 | I68: =SUMIF('Daily Report'!$AE$7:$AE$263,'Cumulative Table'!$X$7:$X$201,'Daily Report'!$I$7:$I$263) -> 0 | J68: =SUMIF('Daily Report'!AE67:AE323,'Cumulative Table'!X68:X261,'Daily Report'!R67:R323) -> 0 | N68: =SUM(K68:M68) -> 0 | O68: =SUMIF('Daily Report'!AE47:AE239,'Cumulative Table'!X48:X241,'Daily Report'!K47:K239) -> 0 | P68: =SUMIF('Daily Report'!$AE$7:$AE$263,'Cumulative Table'!$X$7:$X$201,'Daily Report'!$L$7:$L$263) -> 0 | Q68: =SUMIF('Daily Report'!$AE$7:$AE$263,'Cumulative Table'!$X$7:$X$201,'Daily Report'!$M$7:$M$263) -> 0 | R68: =SUMIF('Daily Report'!$AE$7:$AE$263,'Cumulative Table'!$X$7:$X$201,'Daily Report'!$N$7:$N$263) -> 0 | S68: =SUMIF('Daily Report'!$AE$7:$AE$263,'Cumulative Table'!$X$7:$X$201,'Daily Report'!$O$7:$O$263) -> 0 | T68: =SUMIF('Daily Report'!$AE$7:$AE$263,'Cumulative Table'!$X$8:$X$201,'Daily Report'!$P$7:$P$263) -> 0 | U68: =SUMIF('Daily Report'!$AE$7:$AE$263,'Cumulative Table'!$X$7:$X$201,'Daily Report'!$Q$7:$Q$263) -> 0 | W68: =H68/G68 -> #DIV/0! | X68: =$A$68&D68&E68 -> BR9070WHSS
D69: WH | E69: S | G69: =SUMIF('Daily Report'!$AD$7:$AD$263,'Cumulative Table'!$X$7:$X$201&"KIEM",'Daily Report'!$H$7:$H$199) -> 2 | H69: =SUMIF('Daily Report'!$AD$7:$AD$263,'Cumulative Table'!$X$7:$X$201&"TAIKIEM",'Daily Report'!$H$7:$H$263) -> 0 | I69: =SUMIF('Daily Report'!$AE$7:$AE$263,'Cumulative Table'!$X$7:$X$201,'Daily Report'!$I$7:$I$263) -> 2 | J69: =SUMIF('Daily Report'!AE68:AE324,'Cumulative Table'!X69:X262,'Daily Report'!R68:R324) -> 0 | N69: =SUM(K69:M69) -> 0 | O69: =SUMIF('Daily Report'!AE48:AE240,'Cumulative Table'!X49:X242,'Daily Report'!K48:K240) -> 0 | P69: =SUMIF('Daily Report'!$AE$7:$AE$263,'Cumulative Table'!$X$7:$X$201,'Daily Report'!$L$7:$L$263) -> 0 | Q69: =SUMIF('Daily Report'!$AE$7:$AE$263,'Cumulative Table'!$X$7:$X$201,'Daily Report'!$M$7:$M$263) -> 0 | R69: =SUMIF('Daily Report'!$AE$7:$AE$263,'Cumulative Table'!$X$7:$X$201,'Daily Report'!$N$7:$N$263) -> 0 | S69: =SUMIF('Daily Report'!$AE$7:$AE$263,'Cumulative Table'!$X$7:$X$201,'Daily Report'!$O$7:$O$263) -> 0 | T69: =SUMIF('Daily Report'!$AE$7:$AE$263,'Cumulative Table'!$X$8:$X$201,'Daily Report'!$P$7:$P$263) -> 0 | U69: =SUMIF('Daily Report'!$AE$7:$AE$263,'Cumulative Table'!$X$7:$X$201,'Daily Report'!$Q$7:$Q$263) -> 0 | W69: =H69/G69 -> 0 | X69: =$A$68&D69&E69 -> BR9070WHS
D70: WH | E70: M | G70: =SUMIF('Daily Report'!$AD$7:$AD$263,'Cumulative Table'!$X$7:$X$201&"KIEM",'Daily Report'!$H$7:$H$199) -> 2 | H70: =SUMIF('Daily Report'!$AD$7:$AD$263,'Cumulative Table'!$X$7:$X$201&"TAIKIEM",'Daily Report'!$H$7:$H$263) -> 0 | I70: =SUMIF('Daily Report'!$AE$7:$AE$263,'Cumulative Table'!$X$7:$X$201,'Daily Report'!$I$7:$I$263) -> 2 | J70: =SUMIF('Daily Report'!AE69:AE325,'Cumulative Table'!X70:X263,'Daily Report'!R69:R325) -> 0 | N70: =SUM(K70:M70) -> 0 | O70: =SUMIF('Daily Report'!AE49:AE241,'Cumulative Table'!X50:X243,'Daily Report'!K49:K241) -> 0 | P70: =SUMIF('Daily Report'!$AE$7:$AE$263,'Cumulative Table'!$X$7:$X$201,'Daily Report'!$L$7:$L$263) -> 0 | Q70: =SUMIF('Daily Report'!$AE$7:$AE$263,'Cumulative Table'!$X$7:$X$201,'Daily Report'!$M$7:$M$263) -> 0 | R70: =SUMIF('Daily Report'!$AE$7:$AE$263,'Cumulative Table'!$X$7:$X$201,'Daily Report'!$N$7:$N$263) -> 0 | S70: =SUMIF('Daily Report'!$AE$7:$AE$263,'Cumulative Table'!$X$7:$X$201,'Daily Report'!$O$7:$O$263) -> 0 | T70: =SUMIF('Daily Report'!$AE$7:$AE$263,'Cumulative Table'!$X$8:$X$201,'Daily Report'!$P$7:$P$263) -> 0 | U70: =SUMIF('Daily Report'!$AE$7:$AE$263,'Cumulative Table'!$X$7:$X$201,'Daily Report'!$Q$7:$Q$263) -> 0 | W70: =H70/G70 -> 0 | X70: =$A$68&D70&E70 -> BR9070WHM
D71: WH | E71: L | G71: =SUMIF('Daily Report'!$AD$7:$AD$263,'Cumulative Table'!$X$7:$X$201&"KIEM",'Daily Report'!$H$7:$H$199) -> 0 | H71: =SUMIF('Daily Report'!$AD$7:$AD$263,'Cumulative Table'!$X$7:$X$201&"TAIKIEM",'Daily Report'!$H$7:$H$263) -> 0 | I71: =SUMIF('Daily Report'!$AE$7:$AE$263,'Cumulative Table'!$X$7:$X$201,'Daily Report'!$I$7:$I$263) -> 0 | J71: =SUMIF('Daily Report'!AE70:AE326,'Cumulative Table'!X71:X264,'Daily Report'!R70:R326) -> 0 | N71: =SUM(K71:M71) -> 0 | O71: =SUMIF('Daily Report'!AE50:AE242,'Cumulative Table'!X51:X244,'Daily Report'!K50:K242) -> 0 | P71: =SUMIF('Daily Report'!$AE$7:$AE$263,'Cumulative Table'!$X$7:$X$201,'Daily Report'!$L$7:$L$263) -> 0 | Q71: =SUMIF('Daily Report'!$AE$7:$AE$263,'Cumulative Table'!$X$7:$X$201,'Daily Report'!$M$7:$M$263) -> 0 | R71: =SUMIF('Daily Report'!$AE$7:$AE$263,'Cumulative Table'!$X$7:$X$201,'Daily Report'!$N$7:$N$263) -> 0 | S71: =SUMIF('Daily Report'!$AE$7:$AE$263,'Cumulative Table'!$X$7:$X$201,'Daily Report'!$O$7:$O$263) -> 0 | T71: =SUMIF('Daily Report'!$AE$7:$AE$263,'Cumulative Table'!$X$8:$X$201,'Daily Report'!$P$7:$P$263) -> 0 | U71: =SUMIF('Daily Report'!$AE$7:$AE$263,'Cumulative Table'!$X$7:$X$201,'Daily Report'!$Q$7:$Q$263) -> 0 | W71: =H71/G71 -> #DIV/0! | X71: =$A$68&D71&E71 -> BR9070WHL
D72: WH | E72: LL | G72: =SUMIF('Daily Report'!$AD$7:$AD$263,'Cumulative Table'!$X$7:$X$201&"KIEM",'Daily Report'!$H$7:$H$199) -> 1 | H72: =SUMIF('Daily Report'!$AD$7:$AD$263,'Cumulative Table'!$X$7:$X$201&"TAIKIEM",'Daily Report'!$H$7:$H$263) -> 0 | I72: =SUMIF('Daily Report'!$AE$7:$AE$263,'Cumulative Table'!$X$7:$X$201,'Daily Report'!$I$7:$I$263) -> 1 | J72: =SUMIF('Daily Report'!AE71:AE327,'Cumulative Table'!X72:X265,'Daily Report'!R71:R327) -> 0 | N72: =SUM(K72:M72) -> 0 | O72: =SUMIF('Daily Report'!AE51:AE243,'Cumulative Table'!X52:X245,'Daily Report'!K51:K243) -> 0 | P72: =SUMIF('Daily Report'!$AE$7:$AE$263,'Cumulative Table'!$X$7:$X$201,'Daily Report'!$L$7:$L$263) -> 0 | Q72: =SUMIF('Daily Report'!$AE$7:$AE$263,'Cumulative Table'!$X$7:$X$201,'Daily Report'!$M$7:$M$263) -> 0 | R72: =SUMIF('Daily Report'!$AE$7:$AE$263,'Cumulative Table'!$X$7:$X$201,'Daily Report'!$N$7:$N$263) -> 0 | S72: =SUMIF('Daily Report'!$AE$7:$AE$263,'Cumulative Table'!$X$7:$X$201,'Daily Report'!$O$7:$O$263) -> 0 | T72: =SUMIF('Daily Report'!$AE$7:$AE$263,'Cumulative Table'!$X$8:$X$201,'Daily Report'!$P$7:$P$263) -> 0 | U72: =SUMIF('Daily Report'!$AE$7:$AE$263,'Cumulative Table'!$X$7:$X$201,'Daily Report'!$Q$7:$Q$263) -> 0 | W72: =H72/G72 -> 0 | X72: =$A$68&D72&E72 -> BR9070WHLL
D73: WH | E73: BL | G73: =SUMIF('Daily Report'!$AD$7:$AD$263,'Cumulative Table'!$X$7:$X$201&"KIEM",'Daily Report'!$H$7:$H$199) -> 0 | H73: =SUMIF('Daily Report'!$AD$7:$AD$263,'Cumulative Table'!$X$7:$X$201&"TAIKIEM",'Daily Report'!$H$7:$H$263) -> 0 | I73: =SUMIF('Daily Report'!$AE$7:$AE$263,'Cumulative Table'!$X$7:$X$201,'Daily Report'!$I$7:$I$263) -> 0 | J73: =SUMIF('Daily Report'!AE72:AE328,'Cumulative Table'!X73:X266,'Daily Report'!R72:R328) -> 0 | N73: =SUM(K73:M73) -> 0 | O73: =SUMIF('Daily Report'!AE52:AE244,'Cumulative Table'!X53:X246,'Daily Report'!K52:K244) -> 0 | P73: =SUMIF('Daily Report'!$AE$7:$AE$263,'Cumulative Table'!$X$7:$X$201,'Daily Report'!$L$7:$L$263) -> 0 | Q73: =SUMIF('Daily Report'!$AE$7:$AE$263,'Cumulative Table'!$X$7:$X$201,'Daily Report'!$M$7:$M$263) -> 0 | R73: =SUMIF('Daily Report'!$AE$7:$AE$263,'Cumulative Table'!$X$7:$X$201,'Daily Report'!$N$7:$N$263) -> 0 | S73: =SUMIF('Daily Report'!$AE$7:$AE$263,'Cumulative Table'!$X$7:$X$201,'Daily Report'!$O$7:$O$263) -> 0 | T73: =SUMIF('Daily Report'!$AE$7:$AE$263,'Cumulative Table'!$X$8:$X$201,'Daily Report'!$P$7:$P$263) -> 0 | U73: =SUMIF('Daily Report'!$AE$7:$AE$263,'Cumulative Table'!$X$7:$X$201,'Daily Report'!$Q$7:$Q$263) -> 0 | W73: =H73/G73 -> #DIV/0! | X73: =$A$68&D73&E73 -> BR9070WHBL
D74: WH | E74: 4L | G74: =SUMIF('Daily Report'!$AD$7:$AD$263,'Cumulative Table'!$X$7:$X$201&"KIEM",'Daily Report'!$H$7:$H$199) -> 0 | H74: =SUMIF('Daily Report'!$AD$7:$AD$263,'Cumulative Table'!$X$7:$X$201&"TAIKIEM",'Daily Report'!$H$7:$H$263) -> 0 | I74: =SUMIF('Daily Report'!$AE$7:$AE$263,'Cumulative Table'!$X$7:$X$201,'Daily Report'!$I$7:$I$263) -> 0 | J74: =SUMIF('Daily Report'!AE73:AE329,'Cumulative Table'!X74:X267,'Daily Report'!R73:R329) -> 0 | N74: =SUM(K74:M74) -> 0 | O74: =SUMIF('Daily Report'!AE53:AE245,'Cumulative Table'!X54:X247,'Daily Report'!K53:K245) -> 0 | P74: =SUMIF('Daily Report'!$AE$7:$AE$263,'Cumulative Table'!$X$7:$X$201,'Daily Report'!$L$7:$L$263) -> 0 | Q74: =SUMIF('Daily Report'!$AE$7:$AE$263,'Cumulative Table'!$X$7:$X$201,'Daily Report'!$M$7:$M$263) -> 0 | R74: =SUMIF('Daily Report'!$AE$7:$AE$263,'Cumulative Table'!$X$7:$X$201,'Daily Report'!$N$7:$N$263) -> 0 | S74: =SUMIF('Daily Report'!$AE$7:$AE$263,'Cumulative Table'!$X$7:$X$201,'Daily Report'!$O$7:$O$263) -> 0 | T74: =SUMIF('Daily Report'!$AE$7:$AE$263,'Cumulative Table'!$X$8:$X$201,'Daily Report'!$P$7:$P$263) -> 0 | U74: =SUMIF('Daily Report'!$AE$7:$AE$263,'Cumulative Table'!$X$7:$X$201,'Daily Report'!$Q$7:$Q$263) -> 0 | W74: =H74/G74 -> #DIV/0! | X74: =$A$68&D74&E74 -> BR9070WH4L
D75: WH | E75: 5L | G75: =SUMIF('Daily Report'!$AD$7:$AD$263,'Cumulative Table'!$X$7:$X$201&"KIEM",'Daily Report'!$H$7:$H$199) -> 0 | H75: =SUMIF('Daily Report'!$AD$7:$AD$263,'Cumulative Table'!$X$7:$X$201&"TAIKIEM",'Daily Report'!$H$7:$H$263) -> 0 | I75: =SUMIF('Daily Report'!$AE$7:$AE$263,'Cumulative Table'!$X$7:$X$201,'Daily Report'!$I$7:$I$263) -> 0 | J75: =SUMIF('Daily Report'!AE74:AE330,'Cumulative Table'!X75:X268,'Daily Report'!R74:R330) -> 0 | N75: =SUM(K75:M75) -> 0 | O75: =SUMIF('Daily Report'!AE54:AE246,'Cumulative Table'!X55:X248,'Daily Report'!K54:K246) -> 0 | P75: =SUMIF('Daily Report'!$AE$7:$AE$263,'Cumulative Table'!$X$7:$X$201,'Daily Report'!$L$7:$L$263) -> 0 | Q75: =SUMIF('Daily Report'!$AE$7:$AE$263,'Cumulative Table'!$X$7:$X$201,'Daily Report'!$M$7:$M$263) -> 0 | R75: =SUMIF('Daily Report'!$AE$7:$AE$263,'Cumulative Table'!$X$7:$X$201,'Daily Report'!$N$7:$N$263) -> 0 | S75: =SUMIF('Daily Report'!$AE$7:$AE$263,'Cumulative Table'!$X$7:$X$201,'Daily Report'!$O$7:$O$263) -> 0 | T75: =SUMIF('Daily Report'!$AE$7:$AE$263,'Cumulative Table'!$X$8:$X$201,'Daily Report'!$P$7:$P$263) -> 0 | U75: =SUMIF('Daily Report'!$AE$7:$AE$263,'Cumulative Table'!$X$7:$X$201,'Daily Report'!$Q$7:$Q$263) -> 0 | W75: =H75/G75 -> #DIV/0! | X75: =$A$68&D75&E75 -> BR9070WH5L
A76: 合計数 Tổng | F76: =SUM(F68:F75) -> 0 | G76: =SUM(G68:G75) -> 5 | H76: =SUM(H68:H75) -> 0 | I76: =SUM(I68:I75) -> 5 | J76: =SUM(J68:J75) -> 0 | K76: =SUM(K68:K75) -> 0 | L76: =SUM(L68:L75) -> 0 | M76: =SUM(M68:M75) -> 0 | ... V76: =SUM(V68:V75) -> 0 | W76: =H76/G76 -> 0
A77: 不良項目 | C77: 寸法不良： | D77: 袖丈-1.5CM, 着丈-4CM, 袖丈-2CM | H77: 付属・装飾不良： | I77: テープ無し, 品質ネームサイズ違い, プリント不良, 品質ネーム汚れ, サイズネーム曲がり
C78: 外観・仕上げ不良： | D78: 袖非対称, アタリ, 衿バランス不良, ダブリ, しわ, 捻じれ | H78: 生地不良： | I78: スリップ, 生折れ, キズ
C79: 汚れ不良： | D79: 油汚れ | H79: 縫製不良： | I79: パンク, 縫い止め逆付け, 糸切れ, 縫い摘み, 縫いつまみ, 縫い止め無し
C80: その他：
A81: CHI TIẾT LỖI | C81: THÔNG SỐ： | D81: DAI TAY -1.5CM, DAI AO -4CM, DAI TAY -2CM | H81: PHỤ LIỆU: | I81: THIEU TEP, NHAN GIAT LON SIZE, IN DUN, NHAN GIAT DO MUC, IN NHAN SIZE XEO
C82: HÌNH DÁNG: | D82: TAY SOLE, CAN, CO MEO, DUN, NHAN, RAP BO CO VAN | H82: VẢI: | I82: BE VAI, SOC VAI, XUOC
C83: DƠ: | D83: DAU | H83: CÁCH MAY: | I83: XI, CHOT NGUOC, DUT CHI , XEP LY, NHIU, THIEU CHOT
X84: =A84&D84&E84
A85: 品番 | B85: ブランド | C85: 品目 | D85: カラー | E85: サイズ | F85: ロット数 | G85: 検品数(初回検品のみ) | H85: 再検品数量(2回目以降の検査も含む) | I85: 良品数(初回・それ以降の検査分含む) | J85: 検針良品数(初回・それ以降の検査分含む) | K85: 出荷済み数量 | O85: Thông số | P85: Phụ liệu | Q85: Ngoại quan | R85: Vải | S85: Dơ | T85: Lổi may | U85: Khác | V85: Kiểm Kim | W85: Tỉ lệ lỗi
A86: Style No | B86: Brand | C86: Item | D86: Color | E86: Size | F86: Order Qty | G86: Inspection Qty | H86: Re-inspection Qty | I86: A-Grade Qty | J86: A-Grade Qty | K86: Shipment Qty | O86: Measurment | P86: Material | Q86: Appearance | R86: Fabric | S86: Dirt | T86: Sewing | U86: Other | V86: Needle Inspection | W86: rate
A87: Mã hàng | B87: Thương hiệu | C87: Tên hàng | D87: Màu | E87: Size | F87: Số lượng đơn hàng | G87: SL kiểm hàng | H87: SL tái kiểm | I87: SL Hàng đạt | J87: SL Hàng đạt Kiểm kim | K87: SL xuất 1 | L87: SL xuất 2 | M87: SL xuất 3 | N87: TỔNG XUẤT | O87: 採寸不良 | P87: 付属不良 | Q87: 外観不良 | R87: 生地不良 | S87: 汚れ不良 | T87: 縫製不良 | U87: その他 | V87: 検針 | W87: 不良率
A88: HS8073 | B88: =VLOOKUP($A$7,'Daily Report'!$C$7:$E$263,2,FALSE) -> GUA | C88: =VLOOKUP($A$7,'Daily Report'!$C$7:$E$263,3,FALSE) -> SHIRT | D88: WH | E88: SS | G88: =SUMIF('Daily Report'!$AD$7:$AD$263,'Cumulative Table'!$X$7:$X$201&"KIEM",'Daily Report'!$H$7:$H$199) -> 0 | H88: =SUMIF('Daily Report'!$AD$7:$AD$263,'Cumulative Table'!$X$7:$X$201&"TAIKIEM",'Daily Report'!$H$7:$H$263) -> 0 | I88: =SUMIF('Daily Report'!$AE$7:$AE$263,'Cumulative Table'!$X$7:$X$201,'Daily Report'!$I$7:$I$263) -> 0 | J88: =SUMIF('Daily Report'!AE87:AE343,'Cumulative Table'!X88:X281,'Daily Report'!R87:R343) -> 0 | N88: =SUM(K88:M88) -> 0 | O88: =SUMIF('Daily Report'!AE67:AE259,'Cumulative Table'!X68:X261,'Daily Report'!K67:K259) -> 0 | P88: =SUMIF('Daily Report'!$AE$7:$AE$263,'Cumulative Table'!$X$7:$X$201,'Daily Report'!$L$7:$L$263) -> 0 | Q88: =SUMIF('Daily Report'!$AE$7:$AE$263,'Cumulative Table'!$X$7:$X$201,'Daily Report'!$M$7:$M$263) -> 0 | R88: =SUMIF('Daily Report'!$AE$7:$AE$263,'Cumulative Table'!$X$7:$X$201,'Daily Report'!$N$7:$N$263) -> 0 | S88: =SUMIF('Daily Report'!$AE$7:$AE$263,'Cumulative Table'!$X$7:$X$201,'Daily Report'!$O$7:$O$263) -> 0 | T88: =SUMIF('Daily Report'!$AE$7:$AE$263,'Cumulative Table'!$X$8:$X$201,'Daily Report'!$P$7:$P$263) -> 0 | U88: =SUMIF('Daily Report'!$AE$7:$AE$263,'Cumulative Table'!$X$7:$X$201,'Daily Report'!$Q$7:$Q$263) -> 0 | W88: =H88/G88 -> #DIV/0! | X88: =$A$88&D88&E88 -> HS8073WHSS
D89: WH | E89: S | G89: =SUMIF('Daily Report'!$AD$7:$AD$263,'Cumulative Table'!$X$7:$X$201&"KIEM",'Daily Report'!$H$7:$H$199) -> 0 | H89: =SUMIF('Daily Report'!$AD$7:$AD$263,'Cumulative Table'!$X$7:$X$201&"TAIKIEM",'Daily Report'!$H$7:$H$263) -> 0 | I89: =SUMIF('Daily Report'!$AE$7:$AE$263,'Cumulative Table'!$X$7:$X$201,'Daily Report'!$I$7:$I$263) -> 0 | J89: =SUMIF('Daily Report'!AE88:AE344,'Cumulative Table'!X89:X282,'Daily Report'!R88:R344) -> 0 | N89: =SUM(K89:M89) -> 0 | O89: =SUMIF('Daily Report'!AE68:AE260,'Cumulative Table'!X69:X262,'Daily Report'!K68:K260) -> 0 | P89: =SUMIF('Daily Report'!$AE$7:$AE$263,'Cumulative Table'!$X$7:$X$201,'Daily Report'!$L$7:$L$263) -> 0 | Q89: =SUMIF('Daily Report'!$AE$7:$AE$263,'Cumulative Table'!$X$7:$X$201,'Daily Report'!$M$7:$M$263) -> 0 | R89: =SUMIF('Daily Report'!$AE$7:$AE$263,'Cumulative Table'!$X$7:$X$201,'Daily Report'!$N$7:$N$263) -> 0 | S89: =SUMIF('Daily Report'!$AE$7:$AE$263,'Cumulative Table'!$X$7:$X$201,'Daily Report'!$O$7:$O$263) -> 0 | T89: =SUMIF('Daily Report'!$AE$7:$AE$263,'Cumulative Table'!$X$8:$X$201,'Daily Report'!$P$7:$P$263) -> 0 | U89: =SUMIF('Daily Report'!$AE$7:$AE$263,'Cumulative Table'!$X$7:$X$201,'Daily Report'!$Q$7:$Q$263) -> 0 | W89: =H89/G89 -> #DIV/0! | X89: =$A$88&D89&E89 -> HS8073WHS
D90: WH | E90: M | G90: =SUMIF('Daily Report'!$AD$7:$AD$263,'Cumulative Table'!$X$7:$X$201&"KIEM",'Daily Report'!$H$7:$H$199) -> 2 | H90: =SUMIF('Daily Report'!$AD$7:$AD$263,'Cumulative Table'!$X$7:$X$201&"TAIKIEM",'Daily Report'!$H$7:$H$263) -> 0 | I90: =SUMIF('Daily Report'!$AE$7:$AE$263,'Cumulative Table'!$X$7:$X$201,'Daily Report'!$I$7:$I$263) -> 2 | J90: =SUMIF('Daily Report'!AE89:AE345,'Cumulative Table'!X90:X283,'Daily Report'!R89:R345) -> 0 | N90: =SUM(K90:M90) -> 0 | O90: =SUMIF('Daily Report'!AE69:AE261,'Cumulative Table'!X70:X263,'Daily Report'!K69:K261) -> 0 | P90: =SUMIF('Daily Report'!$AE$7:$AE$263,'Cumulative Table'!$X$7:$X$201,'Daily Report'!$L$7:$L$263) -> 0 | Q90: =SUMIF('Daily Report'!$AE$7:$AE$263,'Cumulative Table'!$X$7:$X$201,'Daily Report'!$M$7:$M$263) -> 0 | R90: =SUMIF('Daily Report'!$AE$7:$AE$263,'Cumulative Table'!$X$7:$X$201,'Daily Report'!$N$7:$N$263) -> 0 | S90: =SUMIF('Daily Report'!$AE$7:$AE$263,'Cumulative Table'!$X$7:$X$201,'Daily Report'!$O$7:$O$263) -> 0 | T90: =SUMIF('Daily Report'!$AE$7:$AE$263,'Cumulative Table'!$X$8:$X$201,'Daily Report'!$P$7:$P$263) -> 0 | U90: =SUMIF('Daily Report'!$AE$7:$AE$263,'Cumulative Table'!$X$7:$X$201,'Daily Report'!$Q$7:$Q$263) -> 0 | W90: =H90/G90 -> 0 | X90: =$A$88&D90&E90 -> HS8073WHM
D91: WH | E91: L | G91: =SUMIF('Daily Report'!$AD$7:$AD$263,'Cumulative Table'!$X$7:$X$201&"KIEM",'Daily Report'!$H$7:$H$199) -> 1 | H91: =SUMIF('Daily Report'!$AD$7:$AD$263,'Cumulative Table'!$X$7:$X$201&"TAIKIEM",'Daily Report'!$H$7:$H$263) -> 0 | I91: =SUMIF('Daily Report'!$AE$7:$AE$263,'Cumulative Table'!$X$7:$X$201,'Daily Report'!$I$7:$I$263) -> 1 | J91: =SUMIF('Daily Report'!AE90:AE346,'Cumulative Table'!X91:X284,'Daily Report'!R90:R346) -> 0 | N91: =SUM(K91:M91) -> 0 | O91: =SUMIF('Daily Report'!AE70:AE262,'Cumulative Table'!X71:X264,'Daily Report'!K70:K262) -> 0 | P91: =SUMIF('Daily Report'!$AE$7:$AE$263,'Cumulative Table'!$X$7:$X$201,'Daily Report'!$L$7:$L$263) -> 0 | Q91: =SUMIF('Daily Report'!$AE$7:$AE$263,'Cumulative Table'!$X$7:$X$201,'Daily Report'!$M$7:$M$263) -> 0 | R91: =SUMIF('Daily Report'!$AE$7:$AE$263,'Cumulative Table'!$X$7:$X$201,'Daily Report'!$N$7:$N$263) -> 0 | S91: =SUMIF('Daily Report'!$AE$7:$AE$263,'Cumulative Table'!$X$7:$X$201,'Daily Report'!$O$7:$O$263) -> 0 | T91: =SUMIF('Daily Report'!$AE$7:$AE$263,'Cumulative Table'!$X$8:$X$201,'Daily Report'!$P$7:$P$263) -> 0 | U91: =SUMIF('Daily Report'!$AE$7:$AE$263,'Cumulative Table'!$X$7:$X$201,'Daily Report'!$Q$7:$Q$263) -> 0 | W91: =H91/G91 -> 0 | X91: =$A$88&D91&E91 -> HS8073WHL
D92: WH | E92: LL | G92: =SUMIF('Daily Report'!$AD$7:$AD$263,'Cumulative Table'!$X$7:$X$201&"KIEM",'Daily Report'!$H$7:$H$199) -> 0 | H92: =SUMIF('Daily Report'!$AD$7:$AD$263,'Cumulative Table'!$X$7:$X$201&"TAIKIEM",'Daily Report'!$H$7:$H$263) -> 0 | I92: =SUMIF('Daily Report'!$AE$7:$AE$263,'Cumulative Table'!$X$7:$X$201,'Daily Report'!$I$7:$I$263) -> 0 | J92: =SUMIF('Daily Report'!AE91:AE347,'Cumulative Table'!X92:X285,'Daily Report'!R91:R347) -> 0 | N92: =SUM(K92:M92) -> 0 | O92: =SUMIF('Daily Report'!AE71:AE263,'Cumulative Table'!X72:X265,'Daily Report'!K71:K263) -> 0 | P92: =SUMIF('Daily Report'!$AE$7:$AE$263,'Cumulative Table'!$X$7:$X$201,'Daily Report'!$L$7:$L$263) -> 0 | Q92: =SUMIF('Daily Report'!$AE$7:$AE$263,'Cumulative Table'!$X$7:$X$201,'Daily Report'!$M$7:$M$263) -> 0 | R92: =SUMIF('Daily Report'!$AE$7:$AE$263,'Cumulative Table'!$X$7:$X$201,'Daily Report'!$N$7:$N$263) -> 0 | S92: =SUMIF('Daily Report'!$AE$7:$AE$263,'Cumulative Table'!$X$7:$X$201,'Daily Report'!$O$7:$O$263) -> 0 | T92: =SUMIF('Daily Report'!$AE$7:$AE$263,'Cumulative Table'!$X$8:$X$201,'Daily Report'!$P$7:$P$263) -> 0 | U92: =SUMIF('Daily Report'!$AE$7:$AE$263,'Cumulative Table'!$X$7:$X$201,'Daily Report'!$Q$7:$Q$263) -> 0 | W92: =H92/G92 -> #DIV/0! | X92: =$A$88&D92&E92 -> HS8073WHLL
D93: WH | E93: BL | G93: =SUMIF('Daily Report'!$AD$7:$AD$263,'Cumulative Table'!$X$7:$X$201&"KIEM",'Daily Report'!$H$7:$H$199) -> 0 | H93: =SUMIF('Daily Report'!$AD$7:$AD$263,'Cumulative Table'!$X$7:$X$201&"TAIKIEM",'Daily Report'!$H$7:$H$263) -> 0 | I93: =SUMIF('Daily Report'!$AE$7:$AE$263,'Cumulative Table'!$X$7:$X$201,'Daily Report'!$I$7:$I$263) -> 0 | J93: =SUMIF('Daily Report'!AE92:AE348,'Cumulative Table'!X93:X286,'Daily Report'!R92:R348) -> 0 | N93: =SUM(K93:M93) -> 0 | O93: =SUMIF('Daily Report'!AE72:AE264,'Cumulative Table'!X73:X266,'Daily Report'!K72:K264) -> 0 | P93: =SUMIF('Daily Report'!$AE$7:$AE$263,'Cumulative Table'!$X$7:$X$201,'Daily Report'!$L$7:$L$263) -> 0 | Q93: =SUMIF('Daily Report'!$AE$7:$AE$263,'Cumulative Table'!$X$7:$X$201,'Daily Report'!$M$7:$M$263) -> 0 | R93: =SUMIF('Daily Report'!$AE$7:$AE$263,'Cumulative Table'!$X$7:$X$201,'Daily Report'!$N$7:$N$263) -> 0 | S93: =SUMIF('Daily Report'!$AE$7:$AE$263,'Cumulative Table'!$X$7:$X$201,'Daily Report'!$O$7:$O$263) -> 0 | T93: =SUMIF('Daily Report'!$AE$7:$AE$263,'Cumulative Table'!$X$8:$X$201,'Daily Report'!$P$7:$P$263) -> 0 | U93: =SUMIF('Daily Report'!$AE$7:$AE$263,'Cumulative Table'!$X$7:$X$201,'Daily Report'!$Q$7:$Q$263) -> 0 | W93: =H93/G93 -> #DIV/0! | X93: =$A$88&D93&E93 -> HS8073WHBL
D94: WH | E94: 4L | G94: =SUMIF('Daily Report'!$AD$7:$AD$263,'Cumulative Table'!$X$7:$X$201&"KIEM",'Daily Report'!$H$7:$H$199) -> 0 | H94: =SUMIF('Daily Report'!$AD$7:$AD$263,'Cumulative Table'!$X$7:$X$201&"TAIKIEM",'Daily Report'!$H$7:$H$263) -> 0 | I94: =SUMIF('Daily Report'!$AE$7:$AE$263,'Cumulative Table'!$X$7:$X$201,'Daily Report'!$I$7:$I$263) -> 0 | J94: =SUMIF('Daily Report'!AE93:AE349,'Cumulative Table'!X94:X287,'Daily Report'!R93:R349) -> 0 | N94: =SUM(K94:M94) -> 0 | O94: =SUMIF('Daily Report'!AE73:AE265,'Cumulative Table'!X74:X267,'Daily Report'!K73:K265) -> 0 | P94: =SUMIF('Daily Report'!$AE$7:$AE$263,'Cumulative Table'!$X$7:$X$201,'Daily Report'!$L$7:$L$263) -> 0 | Q94: =SUMIF('Daily Report'!$AE$7:$AE$263,'Cumulative Table'!$X$7:$X$201,'Daily Report'!$M$7:$M$263) -> 0 | R94: =SUMIF('Daily Report'!$AE$7:$AE$263,'Cumulative Table'!$X$7:$X$201,'Daily Report'!$N$7:$N$263) -> 0 | S94: =SUMIF('Daily Report'!$AE$7:$AE$263,'Cumulative Table'!$X$7:$X$201,'Daily Report'!$O$7:$O$263) -> 0 | T94: =SUMIF('Daily Report'!$AE$7:$AE$263,'Cumulative Table'!$X$8:$X$201,'Daily Report'!$P$7:$P$263) -> 0 | U94: =SUMIF('Daily Report'!$AE$7:$AE$263,'Cumulative Table'!$X$7:$X$201,'Daily Report'!$Q$7:$Q$263) -> 0 | W94: =H94/G94 -> #DIV/0! | X94: =$A$88&D94&E94 -> HS8073WH4L
D95: WH | E95: 5L | G95: =SUMIF('Daily Report'!$AD$7:$AD$263,'Cumulative Table'!$X$7:$X$201&"KIEM",'Daily Report'!$H$7:$H$199) -> 0 | H95: =SUMIF('Daily Report'!$AD$7:$AD$263,'Cumulative Table'!$X$7:$X$201&"TAIKIEM",'Daily Report'!$H$7:$H$263) -> 0 | I95: =SUMIF('Daily Report'!$AE$7:$AE$263,'Cumulative Table'!$X$7:$X$201,'Daily Report'!$I$7:$I$263) -> 0 | J95: =SUMIF('Daily Report'!AE94:AE350,'Cumulative Table'!X95:X288,'Daily Report'!R94:R350) -> 0 | N95: =SUM(K95:M95) -> 0 | O95: =SUMIF('Daily Report'!AE74:AE266,'Cumulative Table'!X75:X268,'Daily Report'!K74:K266) -> 0 | P95: =SUMIF('Daily Report'!$AE$7:$AE$263,'Cumulative Table'!$X$7:$X$201,'Daily Report'!$L$7:$L$263) -> 0 | Q95: =SUMIF('Daily Report'!$AE$7:$AE$263,'Cumulative Table'!$X$7:$X$201,'Daily Report'!$M$7:$M$263) -> 0 | R95: =SUMIF('Daily Report'!$AE$7:$AE$263,'Cumulative Table'!$X$7:$X$201,'Daily Report'!$N$7:$N$263) -> 0 | S95: =SUMIF('Daily Report'!$AE$7:$AE$263,'Cumulative Table'!$X$7:$X$201,'Daily Report'!$O$7:$O$263) -> 0 | T95: =SUMIF('Daily Report'!$AE$7:$AE$263,'Cumulative Table'!$X$8:$X$201,'Daily Report'!$P$7:$P$263) -> 0 | U95: =SUMIF('Daily Report'!$AE$7:$AE$263,'Cumulative Table'!$X$7:$X$201,'Daily Report'!$Q$7:$Q$263) -> 0 | W95: =H95/G95 -> #DIV/0! | X95: =$A$88&D95&E95 -> HS8073WH5L
A96: 合計数 Tổng | F96: =SUM(F88:F95) -> 0 | G96: =SUM(G88:G95) -> 3 | H96: =SUM(H88:H95) -> 0 | I96: =SUM(I88:I95) -> 3 | J96: =SUM(J88:J95) -> 0 | K96: =SUM(K88:K95) -> 0 | L96: =SUM(L88:L95) -> 0 | M96: =SUM(M88:M95) -> 0 | ... V96: =SUM(V88:V95) -> 0 | W96: =H96/G96 -> 0
A97: 不良項目 | C97: 寸法不良： | D97: 袖丈-1.5CM, 着丈-4CM, 袖丈-2CM | H97: 付属・装飾不良： | I97: テープ無し, 品質ネームサイズ違い, プリント不良, 品質ネーム汚れ, サイズネーム曲がり
C98: 外観・仕上げ不良： | D98: 袖非対称, アタリ, 衿バランス不良, ダブリ, しわ, 捻じれ | H98: 生地不良： | I98: スリップ, 生折れ, キズ
C99: 汚れ不良： | D99: 油汚れ | H99: 縫製不良： | I99: パンク, 縫い止め逆付け, 糸切れ, 縫い摘み, 縫いつまみ, 縫い止め無し
C100: その他：
...

Sheet Sheet3

Sheet DEBIT T&K
B1: TAIYO NISSHIN VIET NAM CO.,LTD
B2: 2026年2月分請求書 / DEBIT NOTE - FEB 2026 | H2: 担当者名: KAORI 07 - FF03-0226
H3: 作成日: 2026年2月25日
A4: TO : 株式会社FIT FIT様 ATT : 望月様, 西村様 工場 : T&K
A5: 作業日/ Ngày kiểm | B5: 品番/ Mã hàng | C5: 品名／ Tên hàng | D5: 作業内容 Nội dung kiểm hàng | E5: 時間 Thời gian ĐĐ | F5: 数量/人数 SL (PCS OR QC) | G5: 単価 (USD) Đơn giá | H5: 作業代 (USD) Tổng | I5: 備考 Chú thích
A6: 2月6日～2月13日 | B6: 86102 | C6: SHOES | D6: KIỂM HÀNG | F6: 3281 | G6: 0.23 | H6: =F6*G6 -> 754.63
D7: TÁI KIỂM | F7: 517 | G7: 0.23 | H7: =F7*G7 -> 118.91
A8: 1月30日～2月3日 | B8: 86104 | C8: SHOES | D8: KIỂM HÀNG | F8: 2280 | G8: 0.23 | H8: =F8*G8 -> 524.4
D9: TÁI KIỂM | F9: 312 | G9: 0.23 | H9: =F9*G9 -> 71.76
A10: 2月6日～2月13日 | B10: 86111 | C10: SHOES | D10: KIỂM HÀNG | F10: 2350 | G10: 0.23 | H10: =F10*G10 -> 540.5
D11: TÁI KIỂM | F11: 282 | G11: 0.23 | H11: =F11*G11 -> 64.86
A12: 1月26日～2月2日 | B12: 86121 | C12: SHOES | D12: KIỂM HÀNG | F12: 3990 | G12: 0.23 | H12: =F12*G12 -> 917.7
D13: TÁI KIỂM | F13: 432 | G13: 0.23 | H13: =F13*G13 -> 99.36
A14: 2月10日～12日 | B14: 86127 | C14: SHOES | D14: KIỂM HÀNG | F14: 1320 | G14: 0.23 | H14: =F14*G14 -> 303.6
D15: TÁI KIỂM | F15: 204 | G15: 0.23 | H15: =F15*G15 -> 46.92
A17: 46048 | D17: GIO ĐI ĐƯỜNG | E17: 2.5 | F17: 3 | G17: 3.8 | H17: =F17*G17*E17 -> 28.5
A18: 46049 | D18: GIO ĐI ĐƯỜNG | E18: 2.5 | F18: 4 | G18: 3.8 | H18: =F18*G18*E18 -> 38
A19: 46052 | D19: GIO ĐI ĐƯỜNG | E19: 2.5 | F19: 3 | G19: 3.8 | H19: =F19*G19*E19 -> 28.5
A20: 46053 | D20: GIO ĐI ĐƯỜNG | E20: 2.5 | F20: 3 | G20: 3.8 | H20: =F20*G20*E20 -> 28.5
A21: 46055 | D21: GIO ĐI ĐƯỜNG | E21: 2.5 | F21: 4 | G21: 3.8 | H21: =F21*G21*E21 -> 38
A22: 46059 | D22: GIO ĐI ĐƯỜNG | E22: 2.5 | F22: 2 | G22: 3.8 | H22: =F22*G22*E22 -> 19
A23: 46060 | D23: GIO ĐI ĐƯỜNG | E23: 2.5 | F23: 3 | G23: 3.8 | H23: =F23*G23*E23 -> 28.5
A24: 46062 | D24: GIO ĐI ĐƯỜNG | E24: 2.5 | F24: 3 | G24: 3.8 | H24: =F24*G24*E24 -> 28.5
A25: 46063 | D25: GIO ĐI ĐƯỜNG | E25: 2.5 | F25: 4 | G25: 3.8 | H25: =F25*G25*E25 -> 38
A26: 46064 | D26: GIO ĐI ĐƯỜNG | E26: 2.5 | F26: 3 | G26: 3.8 | H26: =F26*G26*E26 -> 28.5
A27: 46065 | D27: GIO ĐI ĐƯỜNG | E27: 2.5 | F27: 3 | G27: 3.8 | H27: =F27*G27*E27 -> 28.5
A28: 46066 | D28: GIO ĐI ĐƯỜNG | E28: 2.5 | F28: 5 | G28: 3.8 | H28: =F28*G28*E28 -> 47.5
A30: 01月26日～02月13日 | D30: TIỀN XE | E30: 12 | F30: 1 | G30: 59.18 | H30: =F30*G30*E30 -> 710.16 | I30: 往復1,343,000 VND | J30: =1343100/22695 -> 59.180436
H31: =F31*G31 -> 0
H32: =F32*G32 -> 0
E33: 合計 | H33: =SUM(H5:H31) -> 4532.8
E34: VAT 8% | H34: =H33*8% -> 362.624
E35: 総合計 | H35: =H33+H34 -> 4895.424 | I35: USD
A36: TOTAL EQUIVALENTS TO JPY | D36: ドル円ＴＴＳレート 2026/02/25 | F36: 156.83 | H36: =H35*F36 -> 767749.35 | I36: JPY
A37: Payment at Japan | E37: Payment at / to VietNam
A38: Company Name : TAIYO RYUTSU CENTER CO., LTD | E38: Company Name : TAIYO NISSHIN VIETNAM CO., LTD
A39: Address : 1-8-4 Oyodonaka Kita-Ku Osaka, Japan | E39: Address : C12B Le Duc Tho Street, Ward 17, Go Vap District, HCM city, Vietnam
A40: Fax. No : 81-6-6458-6217 | E40: Fax. No : 84.8.3742.2911
A41: Bank Name : The Bank of Tokyo-Mitsuibishi UFJ, Ltd | E41: Bank Name : SAIGON THUONG TIN COMMERCIAL JOINT STOCK BANK
A42: Bank address : 1-8-17 Umeda Kita-ku Osaka, Japan | E42: Bank Address:94-96-98Nguyen Oanh Street, Ward 7, Go Vap District, HCM city, VN
A43: Bank Account : 067.0319384 | E43: Bank Account : 0600.4744.8819 (VND),0600.4744.8908 (USD),
A44: Swift Code : BOTKJPJT | E44: 0600.4845.1211 (JPY)
A45: Swift Code : BOTKJPJT | F45: Swift Code : SGTTVNVX

Sheet MỤC TIÊU
B1: CẢI THIỆN CÔNG VIỆC VP SAU 14 NĂM CỌC CẠCH
A2: STT | B2: DATA NGUỒN | C2: ACTION | D2: MỤC ĐÍCH | E2: NOTE
A3: 1 | B3: SHEET DỮ LIÊU | C3: TẬP HỌP SẲN NGAY LÚC KẾ HOẠCH BÁO GIÁ/KẾ HOẠCH THÁNG/NĂM | D3: Lưu total theo năm Đối chiếu với debit note để xem sự chenh lệch Theo dỏi từ lùi các lần tính debit ở các tháng Đối chiếu tính repeat /thay đổi của khách regular | E3: Ghi chú các sự vụ thêm để làm cơ sở review hằng năm/định kỳ v.v..
A4: 2 | B4: SHEET DAILY REPORT | C4: TẬP HỢP THÔNG TIN HẰNG NGÀY DATA NGUỒN ĐỂ RÀ SOÁT, KIỂM TRA, CHẠY CÔNG THỨC ĐỐI SOÁT V… TÍNH REAL TIME TRONG CÔNG VIỆC | D4: TIẾN ĐẾN VIỆC ĐƠN GIẢN HÓA CÁC FILE LƯU TRÁNH 1 MÃ = 1 FILE 100 MÃ = 100 FILE CHO 1 KHÁCH HÀNG ??? | E4: Lắc nhắc, mất thời gian file lưu tùm lum.
A5: 3 | B5: SHEET CUMULATIVE TABLE | C5: FILE SUM THEO MÃ/SKU | D5: TIẾN ĐẾN VIỆC LINK FILE BÁO CÁO /DEBIT NOTE MỤC TIÊU 5 FORM = 5 SHEET = 1 FILE QL
